Workbook

Sheet Общий
B2: Общий медиаплан
B3: Клиент: | F3: Всего экранов: | G3: =D32
B4: Бренд: | F4: Кол-во дней размещения: | G4: =D6-D5+1
B5: Начало РК: | D5: 45689 | F5: Показов всего за период: | G5: =АЗС!L12+'Азбука вкуса'!K12+Фитнес!K12+БЦ!K12+ТРЦ!K12+Автодор!K12+MetroCC!I14
B6: Окончание РК: | D6: 45716 | E6: OTS: | G6: =АЗС!L13+'Азбука вкуса'!K13+Фитнес!K13+БЦ!K13+ТРЦ!K13+Автодор!K13+MetroCC!I13
B7: Ролик1, сек: | D7: 15 | E7: CPT: | G7: =(D16-I29)/G6*1000
B8: Ролик2, сек: | F8: Предоставление ролика до: | G8: =D5-3
B9: Карта охвата (ALL): | D9: ССЫЛКА = > | E9: Оплата до: | G9: =D5-5
B10: Применяемые скидки (последовательно)
B11: За кол-во (средн): | D11: =(E22*F22+E23*F23+E24*F24+E25*F25+E26*F26+E27*F27+E29*F29)/E32
B12: За период: | D12: =SUBTOTAL(1,G22:G29)
B15: Стоимость размещения
B16: Всего, руб. NET: | D16: =I32 | CM16: 20% | EP16: 20%
B17: Всего, руб. GROSS: | D17: =J32 | CM17: 20% | EP17: 20%
CM18: 20% | EP18: 20%
B19: Расчет стоимости кампании | CM19: 20% | EP19: 20%
CM20: 20% | EP20: 20%
B21: № | C21: Площадки | D21: Количество | E21: Стоимость размещения по выбранной АП за период, без НДС | F21: Скидка за кол-во | G21: Скидка за период | H21: Итоговая скидка | I21: Стоимость c учетом всех скидок, без НДС | J21: Стоимость c учетом всех скидок, вкл. НДС | K21: Сумма НДС (20%) | L21: Фото | CM21: 20% | EP21: 20%
B22: 1 | C22: АЗС | D22: =АЗС!D88 | E22: =АЗС!F88 | F22: =АЗС!D11 | G22: =АЗС!D12 | H22: =SUBTOTAL(1,АЗС!J22:J85) | I22: =АЗС!K88 | J22: =АЗС!L88 | K22: =АЗС!M88 | L22: фото АЗС | CM22: 20% | EP22: 20%
B23: 2 | C23: Азбука Вкуса | D23: ='Азбука вкуса'!D26 | E23: ='Азбука вкуса'!F26 | F23: ='Азбука вкуса'!D11 | G23: ='Азбука вкуса'!D12 | H23: =SUBTOTAL(1,'Азбука вкуса'!I22:I24) | I23: ='Азбука вкуса'!J26 | J23: ='Азбука вкуса'!K26 | K23: ='Азбука вкуса'!L26 | L23: фото Азбука вкуса | CM23: 20% | EP23: 20%
B24: 3 | C24: Metro C&C | D24: =MetroCC!I4 | E24: =MetroCC!F40 | F24: =MetroCC!D10 | G24: =MetroCC!D11 | H24: =MetroCC!D14 | I24: =MetroCC!D16 | J24: =MetroCC!D17 | K24: =MetroCC!I40 | CM24: 20% | EP24: 20%
B25: 4 | C25: Фитнес центры | D25: =Фитнес!D38 | E25: =Фитнес!F38 | F25: =Фитнес!D11 | G25: =Фитнес!D12 | H25: =SUBTOTAL(1,Фитнес!I22:I36) | I25: =Фитнес!J38 | J25: =Фитнес!K38 | K25: =Фитнес!L38 | CM25: 20% | EP25: 20%
B26: 5 | C26: БЦ | D26: =БЦ!D25 | E26: =БЦ!F25 | F26: =БЦ!D11 | G26: =БЦ!D12 | H26: =SUBTOTAL(1,БЦ!I22:I23) | I26: =БЦ!J25 | J26: =БЦ!K25 | K26: =БЦ!L25 | CM26: 20% | EP26: 20%
B27: 6 | C27: ТРЦ | D27: =ТРЦ!K3 | E27: =ТРЦ!F28 | F27: =ТРЦ!D11 | G27: =ТРЦ!D12 | H27: =SUBTOTAL(1,ТРЦ!I24:I26) | I27: =ТРЦ!D16 | J27: =ТРЦ!D17 | K27: =ТРЦ!L28 | CM27: 20% | EP27: 20%
B28: 7 | C28: Афимолл Центр. атриум | D28: ='Афимолл - Цетральный атриум'!J3 | E28: ='Афимолл - Цетральный атриум'!F22 | F28: 0 | G28: 0 | H28: ='Афимолл - Цетральный атриум'!G22 | I28: ='Афимолл - Цетральный атриум'!H22 | J28: ='Афимолл - Цетральный атриум'!I22 | K28: ='Афимолл - Цетральный атриум'!J22 | CM28: 20% | EP28: 20%
B29: 8 | C29: Wifi аналитика | D29: ='Wi-Fi'!D36 | E29: ='Wi-Fi'!E36 | F29: ='Wi-Fi'!D11 | G29: ='Wi-Fi'!D12 | H29: =SUBTOTAL(1,'Wi-Fi'!H22:H34) | I29: ='Wi-Fi'!D16 | J29: ='Wi-Fi'!D17 | K29: ='Wi-Fi'!K36 | CM29: 20% | EP29: 20%
B30: 9 | C30: Радио | D30: =Радио!D25 | E30: =Радио!F25 | F30: =Радио!D11 | G30: 0 | H30: =Радио!D11 | I30: =Радио!I25 | J30: =Радио!J25 | K30: =Радио!K25 | CM30: 20% | EP30: 20%
CM31: 20% | EP31: 20%
D32: =SUM(D22:D29) | E32: =SUM(E22:E30) | I32: =SUM(I22:I30) | J32: =SUM(J22:J30) | K32: =SUM(K22:K30) | CM32: 20% | EP32: 20%
CM33: 20% | EP33: 20%
B34: Скачать описание целевой аудитории | CM34: 20% | EP34: 20%
CM35: 20% | EP35: 20%
B36: Скачать технические требования | CM36: 20% | EP36: 20%
CM37: 20% | EP37: 20%
B38: Скачать информацию по предоставлению фотоотчетов | CM38: 20% | EP38: 20%

Sheet АЗС
B2: Сети АЗС | AO2: ПК | AP2: 0
B3: Клиент: | J3: Всего экранов: | L3: =D88 | AO3: РА | AP3: 0.05 | AQ3: Доп скидка
B4: Бренд: | J4: Часов работы одного экрана в сутки: | L4: 24 | AP4: 0.1 | AQ4: Welcome скидка
B5: Начало РК: | D5: =Общий!D5 | J5: Продолжительность блока в минутах: | L5: 3 | AP5: 0.15 | AQ5: Сезонная скидка
B6: Окончание РК: | D6: =Общий!D6 | J6: Блоков в сутки на одном экране: | L6: =L4*60/L5 | AP6: 0.2
B7: Ролик1, сек: | D7: =Общий!D7 | J7: Кол-во дней размещения: | L7: =D6-D5+1 | AP7: 0.25
B8: Ролик2, сек: | J8: Кол-во роликов в блоке: | L8: =COUNT(D$7,D$8,D$9)
B9: Карта охвата (ALL) | D9: фото АЗС | J9: Итого секунд в блоке: | L9: =SUM(D7:D9)
B10: Применяемые скидки (последовательно) | J10: Показов в день на одном экране: | L10: =L6*L8 | AP10: 0
B11: За кол-во экранов(средн): | D11: =SUBTOTAL(1,G22:G85) | J11: Минут в день на одном экране: | L11: =L6*L9/60 | AP11: 0.05
B12: За период: | D12: =IF(L7>69,'Цены|Скидки'!$C$100,IF(L7>39,'Цены|Скидки'!$C$99,0%)) | J12: Показов на всех экранах за период: | L12: =L10*L7*L3 | AP12: 0.1
B13: =IF(AC2="РА","Скидка для РА:"," ") | D13: =IF(AC2="РА",AD2," ") | J13: OTS: | L13: =N88 | AP13: 0.15
B14: =IF(AC3=0," ",AC3) | D14: =IF(OR(AC3="Доп скидка",AC3="Сезонная скидка",AC3="Welcome скидка")=TRUE,AD3," ") | J14: CPT: | L14: =O88 | AP14: 0.2
B15: Стоимость размещения | J15: % предоставляемого фотоотчета: | AP15: 0.25
B16: Всего, руб. NET: | D16: =K88 | J16: Предоставление ролика до: | L16: =D5-3
B17: Всего, руб. GROSS: | D17: =L88 | J17: Оплата до: | L17: =D5-5
AO18: Автобренд
B19: Расчет стоимости кампании на АЗС
B21: Регион | C21: Сеть | D21: Количество экранов | E21: Стоимость размещения в сутки на одном экране, без НДС | F21: Стоимость размещения по выбранной АП за период, без НДС | G21: Скидка за кол-во экранов | H21: Скидка за период | I21: Скидка за кол-во регионов | J21: Итоговая скидка | K21: Стоимость c учетом всех скидок, без НДС | L21: Стоимость c учетом всех скидок, вкл. НДС | M21: Сумма НДС (20%) | N21: OTS | O21: CPT
B22: Москва | C22: Роснефть | D22: =IF(C22="АЗС",SUMIFS('Адресная программа'!$O$20:$O$4940,'Адресная программа'!$L$20:$L$4940,1,'Адресная программа'!$C$20:$C$4940,АЗС!B22,'Адресная программа'!$F$20:$F$4940,"АЗС",'Адресная программа'!$G$20:$G$4940,"<>Газпромнефть"),SUMIFS('Адресная программа'!$O$20:$O$4940,'Адресная программа'!$L$20:$L$4940,1,'Адресная программа'!$C$20:$C$4940,АЗС!B22,'Адресная программа'!$G$20:$G$4940,АЗС!C22,'Адресная программа'!$F$20:$F$4940,"АЗС")) | E22: ='Цены|Скидки'!$D$11/15*$L$9 | F22: =E22*$L$7*D22 | G22: =IF(SUM($D$22:$D$23)=SUMIFS('Адресная программа'!$K$20:$K$4940,'Адресная программа'!$L$20:$L$4940,1,'Адресная программа'!$C$20:$C$4940,АЗС!B22,'Адресная программа'!$G$20:$G$4940,"<>Газпромнефть",'Адресная программа'!$F$20:$F$4940,"АЗС"),'Цены|Скидки'!$C$31,IF(SUM($D$22:$D$23)>=(SUMIFS('Адресная программа'!$K$20:$K$4940,'Адресная программа'!$L$20:$L$4940,1,'Адресная программа'!$C$20:$C$4940,АЗС!B22,'Адресная программа'!$G$20:$G$4940,"<>Газпромнефть",'Адресная программа'!$F$20:$F$4940,"АЗС")*'Цены|Скидки'!$B$32),'Цены|Скидки'!$C$32,IF(SUM($D$22:$D$23)>=(SUMIFS('Адресная программа'!$K$20:$K$4940,'Адресная программа'!$L$20:$L$4940,1,'Адресная программа'!$C$20:$C$4940,АЗС!B22,'Адресная программа'!$G$20:$G$4940,"<>Газпромнефть",'Адресная программа'!$F$20:$F$4940,"АЗС")*'Цены|Скидки'!$B$33),'Цены|Скидки'!$C$33,IF(SUM($D$22:$D$23)>=(SUMIFS('Адресная программа'!$K$20:$K$4940,'Адресная программа'!$L$20:$L$4940,1,'Адресная программа'!$C$20:$C$4940,АЗС!B22,'Адресная программа'!$G$20:$G$4940,"<>Газпромнефть",'Адресная программа'!$F$20:$F$4940,"АЗС")*'Цены|Скидки'!$B$34),'Цены|Скидки'!$C$34,IF(SUM($D$22:$D$23)>=(SUMIFS('Адресная программа'!$K$20:$K$4940,'Адресная программа'!$L$20:$L$4940,1,'Адресная программа'!$C$20:$C$4940,АЗС!B22,'Адресная программа'!$G$20:$G$4940,"<>Газпромнефть",'Адресная программа'!$F$20:$F$4940,"АЗС")*'Цены|Скидки'!$B$35),'Цены|Скидки'!$C$35,IF(SUM($D$22:$D$23)>=(SUMIFS('Адресная программа'!$K$20:$K$4940,'Адресная программа'!$L$20:$L$4940,1,'Адресная программа'!$C$20:$C$4940,АЗС!B22,'Адресная программа'!$G$20:$G$4940,"<>Газпромнефть",'Адресная программа'!$F$20:$F$4940,"АЗС")*'Цены|Скидки'!$B$36),'Цены|Скидки'!$C$36,0%)))))) | H22: =$D$12 | J22: =IF(SUM($D$22:$D$23)=0,0,1-SUM($K$22:$K$23)/SUM($F$22:$F$23)) | K22: =F22*(1-G22)*(1-H22)*(1-IF($AC$2="РА",$AD$2,0))*(1-IF(OR($AC$3="Доп скидка",$AC$3="Сезонная скидка",$AC$3="Welcome скидка")=TRUE,$AD$3,0)) | L22: =K22+M22 | M22: =K22*0.2 | N22: =D22*$L$7*1210 | O22: =IF(N22=0,0,(K22/N22*1000)/$D$7*10)
B23: Москва | C23: Нефтьмагистраль | D23: =IF(C23="АЗС",SUMIFS('Адресная программа'!$O$20:$O$4940,'Адресная программа'!$L$20:$L$4940,1,'Адресная программа'!$C$20:$C$4940,АЗС!B23,'Адресная программа'!$F$20:$F$4940,"АЗС",'Адресная программа'!$G$20:$G$4940,"<>Газпромнефть"),SUMIFS('Адресная программа'!$O$20:$O$4940,'Адресная программа'!$L$20:$L$4940,1,'Адресная программа'!$C$20:$C$4940,АЗС!B23,'Адресная программа'!$G$20:$G$4940,АЗС!C23,'Адресная программа'!$F$20:$F$4940,"АЗС")) | E23: ='Цены|Скидки'!$D$11/15*$L$9 | F23: =E23*$L$7*D23 | G23: =IF(SUM($D$22:$D$23)=SUMIFS('Адресная программа'!$K$20:$K$4940,'Адресная программа'!$L$20:$L$4940,1,'Адресная программа'!$C$20:$C$4940,АЗС!B23,'Адресная программа'!$G$20:$G$4940,"<>Газпромнефть",'Адресная программа'!$F$20:$F$4940,"АЗС"),'Цены|Скидки'!$C$31,IF(SUM($D$22:$D$23)>=(SUMIFS('Адресная программа'!$K$20:$K$4940,'Адресная программа'!$L$20:$L$4940,1,'Адресная программа'!$C$20:$C$4940,АЗС!B23,'Адресная программа'!$G$20:$G$4940,"<>Газпромнефть",'Адресная программа'!$F$20:$F$4940,"АЗС")*'Цены|Скидки'!$B$32),'Цены|Скидки'!$C$32,IF(SUM($D$22:$D$23)>=(SUMIFS('Адресная программа'!$K$20:$K$4940,'Адресная программа'!$L$20:$L$4940,1,'Адресная программа'!$C$20:$C$4940,АЗС!B23,'Адресная программа'!$G$20:$G$4940,"<>Газпромнефть",'Адресная программа'!$F$20:$F$4940,"АЗС")*'Цены|Скидки'!$B$33),'Цены|Скидки'!$C$33,IF(SUM($D$22:$D$23)>=(SUMIFS('Адресная программа'!$K$20:$K$4940,'Адресная программа'!$L$20:$L$4940,1,'Адресная программа'!$C$20:$C$4940,АЗС!B23,'Адресная программа'!$G$20:$G$4940,"<>Газпромнефть",'Адресная программа'!$F$20:$F$4940,"АЗС")*'Цены|Скидки'!$B$34),'Цены|Скидки'!$C$34,IF(SUM($D$22:$D$23)>=(SUMIFS('Адресная программа'!$K$20:$K$4940,'Адресная программа'!$L$20:$L$4940,1,'Адресная программа'!$C$20:$C$4940,АЗС!B23,'Адресная программа'!$G$20:$G$4940,"<>Газпромнефть",'Адресная программа'!$F$20:$F$4940,"АЗС")*'Цены|Скидки'!$B$35),'Цены|Скидки'!$C$35,IF(SUM($D$22:$D$23)>=(SUMIFS('Адресная программа'!$K$20:$K$4940,'Адресная программа'!$L$20:$L$4940,1,'Адресная программа'!$C$20:$C$4940,АЗС!B23,'Адресная программа'!$G$20:$G$4940,"<>Газпромнефть",'Адресная программа'!$F$20:$F$4940,"АЗС")*'Цены|Скидки'!$B$36),'Цены|Скидки'!$C$36,0%)))))) | H23: =$D$12 | J23: =IF(SUM($D$22:$D$23)=0,0,1-SUM($K$22:$K$23)/SUM($F$22:$F$23)) | K23: =F23*(1-G23)*(1-H23)*(1-IF($AC$2="РА",$AD$2,0))*(1-IF(OR($AC$3="Доп скидка",$AC$3="Сезонная скидка",$AC$3="Welcome скидка")=TRUE,$AD$3,0)) | L23: =K23+M23 | M23: =K23*0.2 | N23: =D23*$L$7*1210 | O23: =IF(N23=0,0,(K23/N23*1000)/$D$7*10)
B24: Москва | C24: Газпромнефть | D24: =IF(C24="АЗС",SUMIFS('Адресная программа'!$O$20:$O$4940,'Адресная программа'!$L$20:$L$4940,1,'Адресная программа'!$C$20:$C$4940,АЗС!B24,'Адресная программа'!$F$20:$F$4940,"АЗС",'Адресная программа'!$G$20:$G$4940,"<>Газпромнефть"),SUMIFS('Адресная программа'!$O$20:$O$4940,'Адресная программа'!$L$20:$L$4940,1,'Адресная программа'!$C$20:$C$4940,АЗС!B24,'Адресная программа'!$G$20:$G$4940,АЗС!C24,'Адресная программа'!$F$20:$F$4940,"АЗС")) | E24: ='Цены|Скидки'!G11/15*$L$9 | F24: =E24*$L$7*D24 | G24: =IF(D24=SUMIFS('Адресная программа'!$K$20:$K$4940,'Адресная программа'!$L$20:$L$4940,1,'Адресная программа'!$C$20:$C$4940,АЗС!B24,'Адресная программа'!$G$20:$G$4940,"=Газпромнефть",'Адресная программа'!$F$20:$F$4940,"АЗС"),'Цены|Скидки'!$C$43,IF(D24>=(SUMIFS('Адресная программа'!$K$20:$K$4940,'Адресная программа'!$L$20:$L$4940,1,'Адресная программа'!$C$20:$C$4940,АЗС!B24,'Адресная программа'!$G$20:$G$4940,"=Газпромнефть",'Адресная программа'!$F$20:$F$4940,"АЗС")*'Цены|Скидки'!$B$44),'Цены|Скидки'!$C$44,IF(D24>=(SUMIFS('Адресная программа'!$K$20:$K$4940,'Адресная программа'!$L$20:$L$4940,1,'Адресная программа'!$C$20:$C$4940,АЗС!B24,'Адресная программа'!$G$20:$G$4940,"=Газпромнефть",'Адресная программа'!$F$20:$F$4940,"АЗС")*'Цены|Скидки'!$B$45),'Цены|Скидки'!$C$45,IF(D24>=(SUMIFS('Адресная программа'!$K$20:$K$4940,'Адресная программа'!$L$20:$L$4940,1,'Адресная программа'!$C$20:$C$4940,АЗС!B24,'Адресная программа'!$G$20:$G$4940,"=Газпромнефть",'Адресная программа'!$F$20:$F$4940,"АЗС")*'Цены|Скидки'!$B$46),'Цены|Скидки'!$C$46,0%)))) | H24: =$D$12 | I24: ='Адресная программа'!Y19 | J24: =IF(D24=0,0,1-K24/F24) | K24: =F24*(1-G24)*(1-H24)*(1-IF($AC$2="РА",$AD$2,0))*(1-IF(OR($AC$3="Доп скидка",$AC$3="Сезонная скидка",$AC$3="Welcome скидка")=TRUE,$AD$3,0))*(1-'Адресная программа'!Y19) | L24: =K24+M24 | M24: =K24*0.2 | N24: =D24*$L$7*1485 | O24: =IF(N24=0,0,(K24/N24*1000)/$D$7*10)
B25: Санкт-Петербург | C25: Роснефть | D25: =IF(C25="АЗС",SUMIFS('Адресная программа'!$O$20:$O$4940,'Адресная программа'!$L$20:$L$4940,1,'Адресная программа'!$C$20:$C$4940,АЗС!B25,'Адресная программа'!$F$20:$F$4940,"АЗС",'Адресная программа'!$G$20:$G$4940,"<>Газпромнефть"),SUMIFS('Адресная программа'!$O$20:$O$4940,'Адресная программа'!$L$20:$L$4940,1,'Адресная программа'!$C$20:$C$4940,АЗС!B25,'Адресная программа'!$G$20:$G$4940,АЗС!C25,'Адресная программа'!$F$20:$F$4940,"АЗС")) | E25: ='Цены|Скидки'!$E$11/15*$L$9 | F25: =E25*$L$7*D25 | G25: =IF(SUM($D$25:$D$25)=SUMIFS('Адресная программа'!$K$20:$K$4940,'Адресная программа'!$L$20:$L$4940,1,'Адресная программа'!$C$20:$C$4940,АЗС!B25,'Адресная программа'!$G$20:$G$4940,"<>Газпромнефть",'Адресная программа'!$F$20:$F$4940,"АЗС"),'Цены|Скидки'!$C$31,IF(SUM($D$25:$D$25)>=(SUMIFS('Адресная программа'!$K$20:$K$4940,'Адресная программа'!$L$20:$L$4940,1,'Адресная программа'!$C$20:$C$4940,АЗС!B25,'Адресная программа'!$G$20:$G$4940,"<>Газпромнефть",'Адресная программа'!$F$20:$F$4940,"АЗС")*'Цены|Скидки'!$B$32),'Цены|Скидки'!$C$32,IF(SUM($D$25:$D$25)>=(SUMIFS('Адресная программа'!$K$20:$K$4940,'Адресная программа'!$L$20:$L$4940,1,'Адресная программа'!$C$20:$C$4940,АЗС!B25,'Адресная программа'!$G$20:$G$4940,"<>Газпромнефть",'Адресная программа'!$F$20:$F$4940,"АЗС")*'Цены|Скидки'!$B$33),'Цены|Скидки'!$C$33,IF(SUM($D$25:$D$25)>=(SUMIFS('Адресная программа'!$K$20:$K$4940,'Адресная программа'!$L$20:$L$4940,1,'Адресная программа'!$C$20:$C$4940,АЗС!B25,'Адресная программа'!$G$20:$G$4940,"<>Газпромнефть",'Адресная программа'!$F$20:$F$4940,"АЗС")*'Цены|Скидки'!$B$34),'Цены|Скидки'!$C$34,IF(SUM($D$25:$D$25)>=(SUMIFS('Адресная программа'!$K$20:$K$4940,'Адресная программа'!$L$20:$L$4940,1,'Адресная программа'!$C$20:$C$4940,АЗС!B25,'Адресная программа'!$G$20:$G$4940,"<>Газпромнефть",'Адресная программа'!$F$20:$F$4940,"АЗС")*'Цены|Скидки'!$B$35),'Цены|Скидки'!$C$35,IF(SUM($D$25:$D$25)>=(SUMIFS('Адресная программа'!$K$20:$K$4940,'Адресная программа'!$L$20:$L$4940,1,'Адресная программа'!$C$20:$C$4940,АЗС!B25,'Адресная программа'!$G$20:$G$4940,"<>Газпромнефть",'Адресная программа'!$F$20:$F$4940,"АЗС")*'Цены|Скидки'!$B$36),'Цены|Скидки'!$C$36,0%)))))) | H25: =$D$12 | J25: =IF(SUM($D$25:$D$25)=0,0,1-SUM($K$25:$K$25)/SUM($F$25:$F$25)) | K25: =F25*(1-G25)*(1-H25)*(1-IF($AC$2="РА",$AD$2,0))*(1-IF(OR($AC$3="Доп скидка",$AC$3="Сезонная скидка",$AC$3="Welcome скидка")=TRUE,$AD$3,0)) | L25: =K25+M25 | M25: =K25*0.2 | N25: =D25*$L$7*1210 | O25: =IF(N25=0,0,(K25/N25*1000)/$D$7*10)
B26: Санкт-Петербург | C26: Газпромнефть | D26: =IF(C26="АЗС",SUMIFS('Адресная программа'!$O$20:$O$4940,'Адресная программа'!$L$20:$L$4940,1,'Адресная программа'!$C$20:$C$4940,АЗС!B26,'Адресная программа'!$F$20:$F$4940,"АЗС",'Адресная программа'!$G$20:$G$4940,"<>Газпромнефть"),SUMIFS('Адресная программа'!$O$20:$O$4940,'Адресная программа'!$L$20:$L$4940,1,'Адресная программа'!$C$20:$C$4940,АЗС!B26,'Адресная программа'!$G$20:$G$4940,АЗС!C26,'Адресная программа'!$F$20:$F$4940,"АЗС")) | E26: ='Цены|Скидки'!H11/15*$L$9 | F26: =E26*$L$7*D26 | G26: =IF(D26=SUMIFS('Адресная программа'!$K$20:$K$4940,'Адресная программа'!$L$20:$L$4940,1,'Адресная программа'!$C$20:$C$4940,АЗС!B26,'Адресная программа'!$G$20:$G$4940,"=Газпромнефть",'Адресная программа'!$F$20:$F$4940,"АЗС"),'Цены|Скидки'!$C$43,IF(D26>=(SUMIFS('Адресная программа'!$K$20:$K$4940,'Адресная программа'!$L$20:$L$4940,1,'Адресная программа'!$C$20:$C$4940,АЗС!B26,'Адресная программа'!$G$20:$G$4940,"=Газпромнефть",'Адресная программа'!$F$20:$F$4940,"АЗС")*'Цены|Скидки'!$B$44),'Цены|Скидки'!$C$44,IF(D26>=(SUMIFS('Адресная программа'!$K$20:$K$4940,'Адресная программа'!$L$20:$L$4940,1,'Адресная программа'!$C$20:$C$4940,АЗС!B26,'Адресная программа'!$G$20:$G$4940,"=Газпромнефть",'Адресная программа'!$F$20:$F$4940,"АЗС")*'Цены|Скидки'!$B$45),'Цены|Скидки'!$C$45,IF(D26>=(SUMIFS('Адресная программа'!$K$20:$K$4940,'Адресная программа'!$L$20:$L$4940,1,'Адресная программа'!$C$20:$C$4940,АЗС!B26,'Адресная программа'!$G$20:$G$4940,"=Газпромнефть",'Адресная программа'!$F$20:$F$4940,"АЗС")*'Цены|Скидки'!$B$46),'Цены|Скидки'!$C$46,0%)))) | H26: =$D$12 | I26: ='Адресная программа'!Y19 | J26: =IF(D26=0,0,1-K26/F26) | K26: =F26*(1-G26)*(1-H26)*(1-IF($AC$2="РА",$AD$2,0))*(1-IF(OR($AC$3="Доп скидка",$AC$3="Сезонная скидка",$AC$3="Welcome скидка")=TRUE,$AD$3,0))*(1-'Адресная программа'!Y19) | L26: =K26+M26 | M26: =K26*0.2 | N26: =D26*$L$7*1375 | O26: =IF(N26=0,0,(K26/N26*1000)/$D$7*10)
B27: Архангельск | C27: Роснефть | D27: =IF(C27="АЗС",SUMIFS('Адресная программа'!$O$20:$O$4940,'Адресная программа'!$L$20:$L$4940,1,'Адресная программа'!$C$20:$C$4940,АЗС!B27,'Адресная программа'!$F$20:$F$4940,"АЗС",'Адресная программа'!$G$20:$G$4940,"<>Газпромнефть"),SUMIFS('Адресная программа'!$O$20:$O$4940,'Адресная программа'!$L$20:$L$4940,1,'Адресная программа'!$C$20:$C$4940,АЗС!B27,'Адресная программа'!$G$20:$G$4940,АЗС!C27,'Адресная программа'!$F$20:$F$4940,"АЗС")) | E27: ='Цены|Скидки'!$F$11/15*$L$9 | F27: =E27*$L$7*D27 | G27: =IF(D27=SUMIFS('Адресная программа'!$K$20:$K$4940,'Адресная программа'!$L$20:$L$4940,1,'Адресная программа'!$C$20:$C$4940,АЗС!B27,'Адресная программа'!$G$20:$G$4940,"<>Газпромнефть",'Адресная программа'!$F$20:$F$4940,"АЗС"),'Цены|Скидки'!$C$31,IF(D27>=(SUMIFS('Адресная программа'!$K$20:$K$4940,'Адресная программа'!$L$20:$L$4940,1,'Адресная программа'!$C$20:$C$4940,АЗС!B27,'Адресная программа'!$G$20:$G$4940,"<>Газпромнефть",'Адресная программа'!$F$20:$F$4940,"АЗС")*'Цены|Скидки'!$B$32),'Цены|Скидки'!$C$32,IF(D27>=(SUMIFS('Адресная программа'!$K$20:$K$4940,'Адресная программа'!$L$20:$L$4940,1,'Адресная программа'!$C$20:$C$4940,АЗС!B27,'Адресная программа'!$G$20:$G$4940,"<>Газпромнефть",'Адресная программа'!$F$20:$F$4940,"АЗС")*'Цены|Скидки'!$B$33),'Цены|Скидки'!$C$33,IF(D27>=(SUMIFS('Адресная программа'!$K$20:$K$4940,'Адресная программа'!$L$20:$L$4940,1,'Адресная программа'!$C$20:$C$4940,АЗС!B27,'Адресная программа'!$G$20:$G$4940,"<>Газпромнефть",'Адресная программа'!$F$20:$F$4940,"АЗС")*'Цены|Скидки'!$B$34),'Цены|Скидки'!$C$34,0%)))) | H27: =D$12 | J27: =IF(D27=0,0,1-K27/F27) | K27: =F27*(1-G27)*(1-H27)*(1-IF($AC$2="РА",$AD$2,0))*(1-IF(OR($AC$3="Доп скидка",$AC$3="Сезонная скидка",$AC$3="Welcome скидка")=TRUE,$AD$3,0)) | L27: =K27+M27 | M27: =K27*0.2 | N27: =D27*L$7*1045 | O27: =IF(N27=0,0,(K27/N27*1000)/$D$7*10)
B28: Абхазия | C28: Подорожник | D28: =IF(C28="АЗС",SUMIFS('Адресная программа'!$O$20:$O$4940,'Адресная программа'!$L$20:$L$4940,1,'Адресная программа'!$C$20:$C$4940,АЗС!B28,'Адресная программа'!$F$20:$F$4940,"АЗС",'Адресная программа'!$G$20:$G$4940,"<>Газпромнефть"),SUMIFS('Адресная программа'!$O$20:$O$4940,'Адресная программа'!$L$20:$L$4940,1,'Адресная программа'!$C$20:$C$4940,АЗС!B28,'Адресная программа'!$G$20:$G$4940,АЗС!C28,'Адресная программа'!$F$20:$F$4940,"АЗС")) | E28: ='Цены|Скидки'!$F$11/15*$L$9 | F28: =E28*$L$7*D28 | G28: =IF(D28=SUMIFS('Адресная программа'!$K$20:$K$4940,'Адресная программа'!$L$20:$L$4940,1,'Адресная программа'!$C$20:$C$4940,АЗС!B28,'Адресная программа'!$G$20:$G$4940,"<>Газпромнефть",'Адресная программа'!$F$20:$F$4940,"АЗС"),'Цены|Скидки'!$C$31,IF(D28>=(SUMIFS('Адресная программа'!$K$20:$K$4940,'Адресная программа'!$L$20:$L$4940,1,'Адресная программа'!$C$20:$C$4940,АЗС!B28,'Адресная программа'!$G$20:$G$4940,"<>Газпромнефть",'Адресная программа'!$F$20:$F$4940,"АЗС")*'Цены|Скидки'!$B$32),'Цены|Скидки'!$C$32,IF(D28>=(SUMIFS('Адресная программа'!$K$20:$K$4940,'Адресная программа'!$L$20:$L$4940,1,'Адресная программа'!$C$20:$C$4940,АЗС!B28,'Адресная программа'!$G$20:$G$4940,"<>Газпромнефть",'Адресная программа'!$F$20:$F$4940,"АЗС")*'Цены|Скидки'!$B$33),'Цены|Скидки'!$C$33,IF(D28>=(SUMIFS('Адресная программа'!$K$20:$K$4940,'Адресная программа'!$L$20:$L$4940,1,'Адресная программа'!$C$20:$C$4940,АЗС!B28,'Адресная программа'!$G$20:$G$4940,"<>Газпромнефть",'Адресная программа'!$F$20:$F$4940,"АЗС")*'Цены|Скидки'!$B$34),'Цены|Скидки'!$C$34,0%)))) | H28: =D$12 | J28: =IF(D28=0,0,1-K28/F28) | K28: =F28*(1-G28)*(1-H28)*(1-IF($AC$2="РА",$AD$2,0))*(1-IF(OR($AC$3="Доп скидка",$AC$3="Сезонная скидка",$AC$3="Welcome скидка")=TRUE,$AD$3,0)) | L28: =K28+M28 | M28: =K28*0.2 | N28: =D28*L$7*1045 | O28: =IF(N28=0,0,(K28/N28*1000)/$D$7*10)
B29: Алтайский край | C29: Роснефть | D29: =IF(C29="АЗС",SUMIFS('Адресная программа'!$O$20:$O$4940,'Адресная программа'!$L$20:$L$4940,1,'Адресная программа'!$C$20:$C$4940,АЗС!B29,'Адресная программа'!$F$20:$F$4940,"АЗС",'Адресная программа'!$G$20:$G$4940,"<>Газпромнефть"),SUMIFS('Адресная программа'!$O$20:$O$4940,'Адресная программа'!$L$20:$L$4940,1,'Адресная программа'!$C$20:$C$4940,АЗС!B29,'Адресная программа'!$G$20:$G$4940,АЗС!C29,'Адресная программа'!$F$20:$F$4940,"АЗС")) | E29: ='Цены|Скидки'!$F$11/15*$L$9 | F29: =E29*$L$7*D29 | G29: =IF(D29=SUMIFS('Адресная программа'!$K$20:$K$4940,'Адресная программа'!$L$20:$L$4940,1,'Адресная программа'!$C$20:$C$4940,АЗС!B29,'Адресная программа'!$G$20:$G$4940,"<>Газпромнефть",'Адресная программа'!$F$20:$F$4940,"АЗС"),'Цены|Скидки'!$C$31,IF(D29>=(SUMIFS('Адресная программа'!$K$20:$K$4940,'Адресная программа'!$L$20:$L$4940,1,'Адресная программа'!$C$20:$C$4940,АЗС!B29,'Адресная программа'!$G$20:$G$4940,"<>Газпромнефть",'Адресная программа'!$F$20:$F$4940,"АЗС")*'Цены|Скидки'!$B$32),'Цены|Скидки'!$C$32,IF(D29>=(SUMIFS('Адресная программа'!$K$20:$K$4940,'Адресная программа'!$L$20:$L$4940,1,'Адресная программа'!$C$20:$C$4940,АЗС!B29,'Адресная программа'!$G$20:$G$4940,"<>Газпромнефть",'Адресная программа'!$F$20:$F$4940,"АЗС")*'Цены|Скидки'!$B$33),'Цены|Скидки'!$C$33,IF(D29>=(SUMIFS('Адресная программа'!$K$20:$K$4940,'Адресная программа'!$L$20:$L$4940,1,'Адресная программа'!$C$20:$C$4940,АЗС!B29,'Адресная программа'!$G$20:$G$4940,"<>Газпромнефть",'Адресная программа'!$F$20:$F$4940,"АЗС")*'Цены|Скидки'!$B$34),'Цены|Скидки'!$C$34,0%)))) | H29: =D$12 | J29: =IF(D29=0,0,1-K29/F29) | K29: =F29*(1-G29)*(1-H29)*(1-IF($AC$2="РА",$AD$2,0))*(1-IF(OR($AC$3="Доп скидка",$AC$3="Сезонная скидка",$AC$3="Welcome скидка")=TRUE,$AD$3,0)) | L29: =K29+M29 | M29: =K29*0.2 | N29: =D29*$L$7*1210 | O29: =IF(N29=0,0,(K29/N29*1000)/$D$7*10)
B30: Алтайский край | C30: Газпромнефть | D30: =IF(C30="АЗС",SUMIFS('Адресная программа'!$O$20:$O$4940,'Адресная программа'!$L$20:$L$4940,1,'Адресная программа'!$C$20:$C$4940,АЗС!B30,'Адресная программа'!$F$20:$F$4940,"АЗС",'Адресная программа'!$G$20:$G$4940,"<>Газпромнефть"),SUMIFS('Адресная программа'!$O$20:$O$4940,'Адресная программа'!$L$20:$L$4940,1,'Адресная программа'!$C$20:$C$4940,АЗС!B30,'Адресная программа'!$G$20:$G$4940,АЗС!C30,'Адресная программа'!$F$20:$F$4940,"АЗС")) | E30: ='Цены|Скидки'!$I$11/15*$L$9 | F30: =E30*$L$7*D30 | G30: =IF(D30=SUMIFS('Адресная программа'!$K$20:$K$4940,'Адресная программа'!$L$20:$L$4940,1,'Адресная программа'!$C$20:$C$4940,АЗС!B30,'Адресная программа'!$G$20:$G$4940,"=Газпромнефть",'Адресная программа'!$F$20:$F$4940,"АЗС"),'Цены|Скидки'!$C$43,IF(D30>=(SUMIFS('Адресная программа'!$K$20:$K$4940,'Адресная программа'!$L$20:$L$4940,1,'Адресная программа'!$C$20:$C$4940,АЗС!B30,'Адресная программа'!$G$20:$G$4940,"=Газпромнефть",'Адресная программа'!$F$20:$F$4940,"АЗС")*'Цены|Скидки'!$B$44),'Цены|Скидки'!$C$44,IF(D30>=(SUMIFS('Адресная программа'!$K$20:$K$4940,'Адресная программа'!$L$20:$L$4940,1,'Адресная программа'!$C$20:$C$4940,АЗС!B30,'Адресная программа'!$G$20:$G$4940,"=Газпромнефть",'Адресная программа'!$F$20:$F$4940,"АЗС")*'Цены|Скидки'!$B$45),'Цены|Скидки'!$C$45,IF(D30>=(SUMIFS('Адресная программа'!$K$20:$K$4940,'Адресная программа'!$L$20:$L$4940,1,'Адресная программа'!$C$20:$C$4940,АЗС!B30,'Адресная программа'!$G$20:$G$4940,"=Газпромнефть",'Адресная программа'!$F$20:$F$4940,"АЗС")*'Цены|Скидки'!$B$46),'Цены|Скидки'!$C$46,0%)))) | H30: =$D$12 | I30: ='Адресная программа'!Y19 | J30: =IF(D30=0,0,1-K30/F30) | K30: =F30*(1-G30)*(1-H30)*(1-IF($AC$2="РА",$AD$2,0))*(1-IF(OR($AC$3="Доп скидка",$AC$3="Сезонная скидка",$AC$3="Welcome скидка")=TRUE,$AD$3,0))*(1-'Адресная программа'!Y19) | L30: =K30+M30 | M30: =K30*0.2 | N30: =D30*$L$7*1210 | O30: =IF(N30=0,0,(K30/N30*1000)/$D$7*10)
B31: Белгород | C31: Роснефть | D31: =IF(C31="АЗС",SUMIFS('Адресная программа'!$O$20:$O$4940,'Адресная программа'!$L$20:$L$4940,1,'Адресная программа'!$C$20:$C$4940,АЗС!B31,'Адресная программа'!$F$20:$F$4940,"АЗС",'Адресная программа'!$G$20:$G$4940,"<>Газпромнефть"),SUMIFS('Адресная программа'!$O$20:$O$4940,'Адресная программа'!$L$20:$L$4940,1,'Адресная программа'!$C$20:$C$4940,АЗС!B31,'Адресная программа'!$G$20:$G$4940,АЗС!C31,'Адресная программа'!$F$20:$F$4940,"АЗС")) | E31: ='Цены|Скидки'!$F$11/15*$L$9 | F31: =E31*$L$7*D31 | G31: =IF(D31=SUMIFS('Адресная программа'!$K$20:$K$4940,'Адресная программа'!$L$20:$L$4940,1,'Адресная программа'!$C$20:$C$4940,АЗС!B31,'Адресная программа'!$G$20:$G$4940,"<>Газпромнефть",'Адресная программа'!$F$20:$F$4940,"АЗС"),'Цены|Скидки'!$C$31,IF(D31>=(SUMIFS('Адресная программа'!$K$20:$K$4940,'Адресная программа'!$L$20:$L$4940,1,'Адресная программа'!$C$20:$C$4940,АЗС!B31,'Адресная программа'!$G$20:$G$4940,"<>Газпромнефть",'Адресная программа'!$F$20:$F$4940,"АЗС")*'Цены|Скидки'!$B$32),'Цены|Скидки'!$C$32,IF(D31>=(SUMIFS('Адресная программа'!$K$20:$K$4940,'Адресная программа'!$L$20:$L$4940,1,'Адресная программа'!$C$20:$C$4940,АЗС!B31,'Адресная программа'!$G$20:$G$4940,"<>Газпромнефть",'Адресная программа'!$F$20:$F$4940,"АЗС")*'Цены|Скидки'!$B$33),'Цены|Скидки'!$C$33,IF(D31>=(SUMIFS('Адресная программа'!$K$20:$K$4940,'Адресная программа'!$L$20:$L$4940,1,'Адресная программа'!$C$20:$C$4940,АЗС!B31,'Адресная программа'!$G$20:$G$4940,"<>Газпромнефть",'Адресная программа'!$F$20:$F$4940,"АЗС")*'Цены|Скидки'!$B$34),'Цены|Скидки'!$C$34,0%)))) | H31: =D$12 | J31: =IF(D31=0,0,1-K31/F31) | K31: =F31*(1-G31)*(1-H31)*(1-IF($AC$2="РА",$AD$2,0))*(1-IF(OR($AC$3="Доп скидка",$AC$3="Сезонная скидка",$AC$3="Welcome скидка")=TRUE,$AD$3,0)) | L31: =K31+M31 | M31: =K31*0.2 | N31: =D31*L$7*1195 | O31: =IF(N31=0,0,(K31/N31*1000)/$D$7*10)
B32: Брянск | C32: Роснефть | D32: =IF(C32="АЗС",SUMIFS('Адресная программа'!$O$20:$O$4940,'Адресная программа'!$L$20:$L$4940,1,'Адресная программа'!$C$20:$C$4940,АЗС!B32,'Адресная программа'!$F$20:$F$4940,"АЗС",'Адресная программа'!$G$20:$G$4940,"<>Газпромнефть"),SUMIFS('Адресная программа'!$O$20:$O$4940,'Адресная программа'!$L$20:$L$4940,1,'Адресная программа'!$C$20:$C$4940,АЗС!B32,'Адресная программа'!$G$20:$G$4940,АЗС!C32,'Адресная программа'!$F$20:$F$4940,"АЗС")) | E32: ='Цены|Скидки'!$F$11/15*$L$9 | F32: =E32*$L$7*D32 | G32: =IF(D32=SUMIFS('Адресная программа'!$K$20:$K$4940,'Адресная программа'!$L$20:$L$4940,1,'Адресная программа'!$C$20:$C$4940,АЗС!B32,'Адресная программа'!$G$20:$G$4940,"<>Газпромнефть",'Адресная программа'!$F$20:$F$4940,"АЗС"),'Цены|Скидки'!$C$31,IF(D32>=(SUMIFS('Адресная программа'!$K$20:$K$4940,'Адресная программа'!$L$20:$L$4940,1,'Адресная программа'!$C$20:$C$4940,АЗС!B32,'Адресная программа'!$G$20:$G$4940,"<>Газпромнефть",'Адресная программа'!$F$20:$F$4940,"АЗС")*'Цены|Скидки'!$B$32),'Цены|Скидки'!$C$32,IF(D32>=(SUMIFS('Адресная программа'!$K$20:$K$4940,'Адресная программа'!$L$20:$L$4940,1,'Адресная программа'!$C$20:$C$4940,АЗС!B32,'Адресная программа'!$G$20:$G$4940,"<>Газпромнефть",'Адресная программа'!$F$20:$F$4940,"АЗС")*'Цены|Скидки'!$B$33),'Цены|Скидки'!$C$33,IF(D32>=(SUMIFS('Адресная программа'!$K$20:$K$4940,'Адресная программа'!$L$20:$L$4940,1,'Адресная программа'!$C$20:$C$4940,АЗС!B32,'Адресная программа'!$G$20:$G$4940,"<>Газпромнефть",'Адресная программа'!$F$20:$F$4940,"АЗС")*'Цены|Скидки'!$B$34),'Цены|Скидки'!$C$34,0%)))) | H32: =D$12 | J32: =IF(D32=0,0,1-K32/F32) | K32: =F32*(1-G32)*(1-H32)*(1-IF($AC$2="РА",$AD$2,0))*(1-IF(OR($AC$3="Доп скидка",$AC$3="Сезонная скидка",$AC$3="Welcome скидка")=TRUE,$AD$3,0)) | L32: =K32+M32 | M32: =K32*0.2 | N32: =D32*L$7*1015 | O32: =IF(N32=0,0,(K32/N32*1000)/$D$7*10)
B33: Владимир | C33: Роснефть | D33: =IF(C33="АЗС",SUMIFS('Адресная программа'!$O$20:$O$4940,'Адресная программа'!$L$20:$L$4940,1,'Адресная программа'!$C$20:$C$4940,АЗС!B33,'Адресная программа'!$F$20:$F$4940,"АЗС",'Адресная программа'!$G$20:$G$4940,"<>Газпромнефть"),SUMIFS('Адресная программа'!$O$20:$O$4940,'Адресная программа'!$L$20:$L$4940,1,'Адресная программа'!$C$20:$C$4940,АЗС!B33,'Адресная программа'!$G$20:$G$4940,АЗС!C33,'Адресная программа'!$F$20:$F$4940,"АЗС")) | E33: ='Цены|Скидки'!$F$11/15*$L$9 | F33: =E33*$L$7*D33 | G33: =IF(D33=SUMIFS('Адресная программа'!$K$20:$K$4940,'Адресная программа'!$L$20:$L$4940,1,'Адресная программа'!$C$20:$C$4940,АЗС!B33,'Адресная программа'!$G$20:$G$4940,"<>Газпромнефть",'Адресная программа'!$F$20:$F$4940,"АЗС"),'Цены|Скидки'!$C$31,IF(D33>=(SUMIFS('Адресная программа'!$K$20:$K$4940,'Адресная программа'!$L$20:$L$4940,1,'Адресная программа'!$C$20:$C$4940,АЗС!B33,'Адресная программа'!$G$20:$G$4940,"<>Газпромнефть",'Адресная программа'!$F$20:$F$4940,"АЗС")*'Цены|Скидки'!$B$32),'Цены|Скидки'!$C$32,IF(D33>=(SUMIFS('Адресная программа'!$K$20:$K$4940,'Адресная программа'!$L$20:$L$4940,1,'Адресная программа'!$C$20:$C$4940,АЗС!B33,'Адресная программа'!$G$20:$G$4940,"<>Газпромнефть",'Адресная программа'!$F$20:$F$4940,"АЗС")*'Цены|Скидки'!$B$33),'Цены|Скидки'!$C$33,IF(D33>=(SUMIFS('Адресная программа'!$K$20:$K$4940,'Адресная программа'!$L$20:$L$4940,1,'Адресная программа'!$C$20:$C$4940,АЗС!B33,'Адресная программа'!$G$20:$G$4940,"<>Газпромнефть",'Адресная программа'!$F$20:$F$4940,"АЗС")*'Цены|Скидки'!$B$34),'Цены|Скидки'!$C$34,0%)))) | H33: =D$12 | J33: =IF(D33=0,0,1-K33/F33) | K33: =F33*(1-G33)*(1-H33)*(1-IF($AC$2="РА",$AD$2,0))*(1-IF(OR($AC$3="Доп скидка",$AC$3="Сезонная скидка",$AC$3="Welcome скидка")=TRUE,$AD$3,0)) | L33: =K33+M33 | M33: =K33*0.2 | N33: =D33*L$7*1090 | O33: =IF(N33=0,0,(K33/N33*1000)/$D$7*10)
B34: ЦФО (Калуга, Тула, Тверь, Рязань,Смоленск,Владимир,Воронеж, Ярославль) | C34: Газпромнефть | D34: =IF(C34="АЗС",SUMIFS('Адресная программа'!$O$20:$O$4940,'Адресная программа'!$L$20:$L$4940,1,'Адресная программа'!$C$20:$C$4940,АЗС!B34,'Адресная программа'!$F$20:$F$4940,"АЗС",'Адресная программа'!$G$20:$G$4940,"<>Газпромнефть"),SUMIFS('Адресная программа'!$O$20:$O$4940,'Адресная программа'!$L$20:$L$4940,1,'Адресная программа'!$C$20:$C$4940,АЗС!B34,'Адресная программа'!$G$20:$G$4940,АЗС!C34,'Адресная программа'!$F$20:$F$4940,"АЗС")) | E34: ='Цены|Скидки'!$I$11/15*$L$9 | F34: =E34*$L$7*D34 | G34: =IF(D34=SUMIFS('Адресная программа'!$K$20:$K$4940,'Адресная программа'!$L$20:$L$4940,1,'Адресная программа'!$C$20:$C$4940,АЗС!B34,'Адресная программа'!$G$20:$G$4940,"=Газпромнефть",'Адресная программа'!$F$20:$F$4940,"АЗС"),'Цены|Скидки'!$C$43,IF(D34>=(SUMIFS('Адресная программа'!$K$20:$K$4940,'Адресная программа'!$L$20:$L$4940,1,'Адресная программа'!$C$20:$C$4940,АЗС!B34,'Адресная программа'!$G$20:$G$4940,"=Газпромнефть",'Адресная программа'!$F$20:$F$4940,"АЗС")*'Цены|Скидки'!$B$44),'Цены|Скидки'!$C$44,IF(D34>=(SUMIFS('Адресная программа'!$K$20:$K$4940,'Адресная программа'!$L$20:$L$4940,1,'Адресная программа'!$C$20:$C$4940,АЗС!B34,'Адресная программа'!$G$20:$G$4940,"=Газпромнефть",'Адресная программа'!$F$20:$F$4940,"АЗС")*'Цены|Скидки'!$B$45),'Цены|Скидки'!$C$45,IF(D34>=(SUMIFS('Адресная программа'!$K$20:$K$4940,'Адресная программа'!$L$20:$L$4940,1,'Адресная программа'!$C$20:$C$4940,АЗС!B34,'Адресная программа'!$G$20:$G$4940,"=Газпромнефть",'Адресная программа'!$F$20:$F$4940,"АЗС")*'Цены|Скидки'!$B$46),'Цены|Скидки'!$C$46,0%)))) | H34: =D$12 | I34: ='Адресная программа'!Y19 | J34: =IF(D34=0,0,1-K34/F34) | K34: =F34*(1-G34)*(1-H34)*(1-IF($AC$2="РА",$AD$2,0))*(1-IF(OR($AC$3="Доп скидка",$AC$3="Сезонная скидка",$AC$3="Welcome скидка")=TRUE,$AD$3,0))*(1-'Адресная программа'!Y19) | L34: =K34+M34 | M34: =K34*0.2 | N34: =D34*L$7*1090 | O34: =IF(N34=0,0,(K34/N34*1000)/$D$7*10)
B35: Владикавказ | C35: Лукойл | D35: =IF(C35="АЗС",SUMIFS('Адресная программа'!$O$20:$O$4940,'Адресная программа'!$L$20:$L$4940,1,'Адресная программа'!$C$20:$C$4940,АЗС!B35,'Адресная программа'!$F$20:$F$4940,"АЗС",'Адресная программа'!$G$20:$G$4940,"<>Газпромнефть"),SUMIFS('Адресная программа'!$O$20:$O$4940,'Адресная программа'!$L$20:$L$4940,1,'Адресная программа'!$C$20:$C$4940,АЗС!B35,'Адресная программа'!$G$20:$G$4940,АЗС!C35,'Адресная программа'!$F$20:$F$4940,"АЗС")) | E35: ='Цены|Скидки'!$F$11/15*$L$9 | F35: =E35*$L$7*D35 | G35: =IF(D35=SUMIFS('Адресная программа'!$K$20:$K$4940,'Адресная программа'!$L$20:$L$4940,1,'Адресная программа'!$C$20:$C$4940,АЗС!B35,'Адресная программа'!$G$20:$G$4940,"<>Газпромнефть",'Адресная программа'!$F$20:$F$4940,"АЗС"),'Цены|Скидки'!$C$31,IF(D35>=(SUMIFS('Адресная программа'!$K$20:$K$4940,'Адресная программа'!$L$20:$L$4940,1,'Адресная программа'!$C$20:$C$4940,АЗС!B35,'Адресная программа'!$G$20:$G$4940,"<>Газпромнефть",'Адресная программа'!$F$20:$F$4940,"АЗС")*'Цены|Скидки'!$B$32),'Цены|Скидки'!$C$32,IF(D35>=(SUMIFS('Адресная программа'!$K$20:$K$4940,'Адресная программа'!$L$20:$L$4940,1,'Адресная программа'!$C$20:$C$4940,АЗС!B35,'Адресная программа'!$G$20:$G$4940,"<>Газпромнефть",'Адресная программа'!$F$20:$F$4940,"АЗС")*'Цены|Скидки'!$B$33),'Цены|Скидки'!$C$33,IF(D35>=(SUMIFS('Адресная программа'!$K$20:$K$4940,'Адресная программа'!$L$20:$L$4940,1,'Адресная программа'!$C$20:$C$4940,АЗС!B35,'Адресная программа'!$G$20:$G$4940,"<>Газпромнефть",'Адресная программа'!$F$20:$F$4940,"АЗС")*'Цены|Скидки'!$B$34),'Цены|Скидки'!$C$34,0%)))) | H35: =D$12 | J35: =IF(D35=0,0,1-K35/F35) | K35: =F35*(1-G35)*(1-H35)*(1-IF($AC$2="РА",$AD$2,0))*(1-IF(OR($AC$3="Доп скидка",$AC$3="Сезонная скидка",$AC$3="Welcome скидка")=TRUE,$AD$3,0)) | L35: =K35+M35 | M35: =K35*0.2 | N35: =D35*$L$7*1045 | O35: =IF(N35=0,0,(K35/N35*1000)/$D$7*10)
B36: Волгоград | C36: Роснефть | D36: =IF(C36="АЗС",SUMIFS('Адресная программа'!$O$20:$O$4940,'Адресная программа'!$L$20:$L$4940,1,'Адресная программа'!$C$20:$C$4940,АЗС!B36,'Адресная программа'!$F$20:$F$4940,"АЗС",'Адресная программа'!$G$20:$G$4940,"<>Газпромнефть"),SUMIFS('Адресная программа'!$O$20:$O$4940,'Адресная программа'!$L$20:$L$4940,1,'Адресная программа'!$C$20:$C$4940,АЗС!B36,'Адресная программа'!$G$20:$G$4940,АЗС!C36,'Адресная программа'!$F$20:$F$4940,"АЗС")) | E36: ='Цены|Скидки'!$F$11/15*$L$9 | F36: =E36*$L$7*D36 | G36: =IF(D36=SUMIFS('Адресная программа'!$K$20:$K$4940,'Адресная программа'!$L$20:$L$4940,1,'Адресная программа'!$C$20:$C$4940,АЗС!B36,'Адресная программа'!$G$20:$G$4940,"<>Газпромнефть",'Адресная программа'!$F$20:$F$4940,"АЗС"),'Цены|Скидки'!$C$31,IF(D36>=(SUMIFS('Адресная программа'!$K$20:$K$4940,'Адресная программа'!$L$20:$L$4940,1,'Адресная программа'!$C$20:$C$4940,АЗС!B36,'Адресная программа'!$G$20:$G$4940,"<>Газпромнефть",'Адресная программа'!$F$20:$F$4940,"АЗС")*'Цены|Скидки'!$B$32),'Цены|Скидки'!$C$32,IF(D36>=(SUMIFS('Адресная программа'!$K$20:$K$4940,'Адресная программа'!$L$20:$L$4940,1,'Адресная программа'!$C$20:$C$4940,АЗС!B36,'Адресная программа'!$G$20:$G$4940,"<>Газпромнефть",'Адресная программа'!$F$20:$F$4940,"АЗС")*'Цены|Скидки'!$B$33),'Цены|Скидки'!$C$33,IF(D36>=(SUMIFS('Адресная программа'!$K$20:$K$4940,'Адресная программа'!$L$20:$L$4940,1,'Адресная программа'!$C$20:$C$4940,АЗС!B36,'Адресная программа'!$G$20:$G$4940,"<>Газпромнефть",'Адресная программа'!$F$20:$F$4940,"АЗС")*'Цены|Скидки'!$B$34),'Цены|Скидки'!$C$34,0%)))) | H36: =D$12 | J36: =IF(D36=0,0,1-K36/F36) | K36: =F36*(1-G36)*(1-H36)*(1-IF($AC$2="РА",$AD$2,0))*(1-IF(OR($AC$3="Доп скидка",$AC$3="Сезонная скидка",$AC$3="Welcome скидка")=TRUE,$AD$3,0)) | L36: =K36+M36 | M36: =K36*0.2 | N36: =D36*$L$7*1045 | O36: =IF(N36=0,0,(K36/N36*1000)/$D$7*10)
B37: Воронеж | C37: Роснефть | D37: =IF(C37="АЗС",SUMIFS('Адресная программа'!$O$20:$O$4940,'Адресная программа'!$L$20:$L$4940,1,'Адресная программа'!$C$20:$C$4940,АЗС!B37,'Адресная программа'!$F$20:$F$4940,"АЗС",'Адресная программа'!$G$20:$G$4940,"<>Газпромнефть"),SUMIFS('Адресная программа'!$O$20:$O$4940,'Адресная программа'!$L$20:$L$4940,1,'Адресная программа'!$C$20:$C$4940,АЗС!B37,'Адресная программа'!$G$20:$G$4940,АЗС!C37,'Адресная программа'!$F$20:$F$4940,"АЗС")) | E37: ='Цены|Скидки'!$F$11/15*$L$9 | F37: =E37*$L$7*D37 | G37: =IF(D37=SUMIFS('Адресная программа'!$K$20:$K$4940,'Адресная программа'!$L$20:$L$4940,1,'Адресная программа'!$C$20:$C$4940,АЗС!B37,'Адресная программа'!$G$20:$G$4940,"<>Газпромнефть",'Адресная программа'!$F$20:$F$4940,"АЗС"),'Цены|Скидки'!$C$31,IF(D37>=(SUMIFS('Адресная программа'!$K$20:$K$4940,'Адресная программа'!$L$20:$L$4940,1,'Адресная программа'!$C$20:$C$4940,АЗС!B37,'Адресная программа'!$G$20:$G$4940,"<>Газпромнефть",'Адресная программа'!$F$20:$F$4940,"АЗС")*'Цены|Скидки'!$B$32),'Цены|Скидки'!$C$32,IF(D37>=(SUMIFS('Адресная программа'!$K$20:$K$4940,'Адресная программа'!$L$20:$L$4940,1,'Адресная программа'!$C$20:$C$4940,АЗС!B37,'Адресная программа'!$G$20:$G$4940,"<>Газпромнефть",'Адресная программа'!$F$20:$F$4940,"АЗС")*'Цены|Скидки'!$B$33),'Цены|Скидки'!$C$33,IF(D37>=(SUMIFS('Адресная программа'!$K$20:$K$4940,'Адресная программа'!$L$20:$L$4940,1,'Адресная программа'!$C$20:$C$4940,АЗС!B37,'Адресная программа'!$G$20:$G$4940,"<>Газпромнефть",'Адресная программа'!$F$20:$F$4940,"АЗС")*'Цены|Скидки'!$B$34),'Цены|Скидки'!$C$34,0%)))) | H37: =D$12 | J37: =IF(D37=0,0,1-K37/F37) | K37: =F37*(1-G37)*(1-H37)*(1-IF($AC$2="РА",$AD$2,0))*(1-IF(OR($AC$3="Доп скидка",$AC$3="Сезонная скидка",$AC$3="Welcome скидка")=TRUE,$AD$3,0)) | L37: =K37+M37 | M37: =K37*0.2 | N37: =D37*L$7*1155 | O37: =IF(N37=0,0,(K37/N37*1000)/$D$7*10)
B38: Екатеринбург | C38: Башнефть | D38: =IF(C38="АЗС",SUMIFS('Адресная программа'!$O$20:$O$4940,'Адресная программа'!$L$20:$L$4940,1,'Адресная программа'!$C$20:$C$4940,АЗС!B38,'Адресная программа'!$F$20:$F$4940,"АЗС",'Адресная программа'!$G$20:$G$4940,"<>Газпромнефть"),SUMIFS('Адресная программа'!$O$20:$O$4940,'Адресная программа'!$L$20:$L$4940,1,'Адресная программа'!$C$20:$C$4940,АЗС!B38,'Адресная программа'!$G$20:$G$4940,АЗС!C38,'Адресная программа'!$F$20:$F$4940,"АЗС")) | E38: ='Цены|Скидки'!$F$11/15*$L$9 | F38: =E38*$L$7*D38 | G38: =IF(D38=SUMIFS('Адресная программа'!$K$20:$K$4940,'Адресная программа'!$L$20:$L$4940,1,'Адресная программа'!$C$20:$C$4940,АЗС!B38,'Адресная программа'!$G$20:$G$4940,"<>Газпромнефть",'Адресная программа'!$F$20:$F$4940,"АЗС"),'Цены|Скидки'!$C$31,IF(D38>=(SUMIFS('Адресная программа'!$K$20:$K$4940,'Адресная программа'!$L$20:$L$4940,1,'Адресная программа'!$C$20:$C$4940,АЗС!B38,'Адресная программа'!$G$20:$G$4940,"<>Газпромнефть",'Адресная программа'!$F$20:$F$4940,"АЗС")*'Цены|Скидки'!$B$32),'Цены|Скидки'!$C$32,IF(D38>=(SUMIFS('Адресная программа'!$K$20:$K$4940,'Адресная программа'!$L$20:$L$4940,1,'Адресная программа'!$C$20:$C$4940,АЗС!B38,'Адресная программа'!$G$20:$G$4940,"<>Газпромнефть",'Адресная программа'!$F$20:$F$4940,"АЗС")*'Цены|Скидки'!$B$33),'Цены|Скидки'!$C$33,IF(D38>=(SUMIFS('Адресная программа'!$K$20:$K$4940,'Адресная программа'!$L$20:$L$4940,1,'Адресная программа'!$C$20:$C$4940,АЗС!B38,'Адресная программа'!$G$20:$G$4940,"<>Газпромнефть",'Адресная программа'!$F$20:$F$4940,"АЗС")*'Цены|Скидки'!$B$34),'Цены|Скидки'!$C$34,0%)))) | H38: =D$12 | J38: =IF(D38=0,0,1-K38/F38) | K38: =F38*(1-G38)*(1-H38)*(1-IF($AC$2="РА",$AD$2,0))*(1-IF(OR($AC$3="Доп скидка",$AC$3="Сезонная скидка",$AC$3="Welcome скидка")=TRUE,$AD$3,0)) | L38: =K38+M38 | M38: =K38*0.2 | N38: =D38*L$7*1260 | O38: =IF(N38=0,0,(K38/N38*1000)/$D$7*10)
B39: Екатеринбург | C39: Газпромнефть | D39: =IF(C39="АЗС",SUMIFS('Адресная программа'!$O$20:$O$4940,'Адресная программа'!$L$20:$L$4940,1,'Адресная программа'!$C$20:$C$4940,АЗС!B39,'Адресная программа'!$F$20:$F$4940,"АЗС",'Адресная программа'!$G$20:$G$4940,"<>Газпромнефть"),SUMIFS('Адресная программа'!$O$20:$O$4940,'Адресная программа'!$L$20:$L$4940,1,'Адресная программа'!$C$20:$C$4940,АЗС!B39,'Адресная программа'!$G$20:$G$4940,АЗС!C39,'Адресная программа'!$F$20:$F$4940,"АЗС")) | E39: ='Цены|Скидки'!$I$11/15*$L$9 | F39: =E39*$L$7*D39 | G39: =IF(D39=SUMIFS('Адресная программа'!$K$20:$K$4940,'Адресная программа'!$L$20:$L$4940,1,'Адресная программа'!$C$20:$C$4940,АЗС!B39,'Адресная программа'!$G$20:$G$4940,"=Газпромнефть",'Адресная программа'!$F$20:$F$4940,"АЗС"),'Цены|Скидки'!$C$43,IF(D39>=(SUMIFS('Адресная программа'!$K$20:$K$4940,'Адресная программа'!$L$20:$L$4940,1,'Адресная программа'!$C$20:$C$4940,АЗС!B39,'Адресная программа'!$G$20:$G$4940,"=Газпромнефть",'Адресная программа'!$F$20:$F$4940,"АЗС")*'Цены|Скидки'!$B$44),'Цены|Скидки'!$C$44,IF(D39>=(SUMIFS('Адресная программа'!$K$20:$K$4940,'Адресная программа'!$L$20:$L$4940,1,'Адресная программа'!$C$20:$C$4940,АЗС!B39,'Адресная программа'!$G$20:$G$4940,"=Газпромнефть",'Адресная программа'!$F$20:$F$4940,"АЗС")*'Цены|Скидки'!$B$45),'Цены|Скидки'!$C$45,IF(D39>=(SUMIFS('Адресная программа'!$K$20:$K$4940,'Адресная программа'!$L$20:$L$4940,1,'Адресная программа'!$C$20:$C$4940,АЗС!B39,'Адресная программа'!$G$20:$G$4940,"=Газпромнефть",'Адресная программа'!$F$20:$F$4940,"АЗС")*'Цены|Скидки'!$B$46),'Цены|Скидки'!$C$46,0%)))) | H39: =$D$12 | I39: ='Адресная программа'!Y19 | J39: =IF(D39=0,0,1-K39/F39) | K39: =F39*(1-G39)*(1-H39)*(1-IF($AC$2="РА",$AD$2,0))*(1-IF(OR($AC$3="Доп скидка",$AC$3="Сезонная скидка",$AC$3="Welcome скидка")=TRUE,$AD$3,0))*(1-'Адресная программа'!Y19) | L39: =K39+M39 | M39: =K39*0.2 | N39: =D39*$L$7*1210 | O39: =IF(N39=0,0,(K39/N39*1000)/$D$7*10)
B40: Ижевск | C40: Башнефть | D40: =IF(C40="АЗС",SUMIFS('Адресная программа'!$O$20:$O$4940,'Адресная программа'!$L$20:$L$4940,1,'Адресная программа'!$C$20:$C$4940,АЗС!B40,'Адресная программа'!$F$20:$F$4940,"АЗС",'Адресная программа'!$G$20:$G$4940,"<>Газпромнефть"),SUMIFS('Адресная программа'!$O$20:$O$4940,'Адресная программа'!$L$20:$L$4940,1,'Адресная программа'!$C$20:$C$4940,АЗС!B40,'Адресная программа'!$G$20:$G$4940,АЗС!C40,'Адресная программа'!$F$20:$F$4940,"АЗС")) | E40: ='Цены|Скидки'!$F$11/15*$L$9 | F40: =E40*$L$7*D40 | G40: =IF(D40=SUMIFS('Адресная программа'!$K$20:$K$4940,'Адресная программа'!$L$20:$L$4940,1,'Адресная программа'!$C$20:$C$4940,АЗС!B40,'Адресная программа'!$G$20:$G$4940,"<>Газпромнефть",'Адресная программа'!$F$20:$F$4940,"АЗС"),'Цены|Скидки'!$C$31,IF(D40>=(SUMIFS('Адресная программа'!$K$20:$K$4940,'Адресная программа'!$L$20:$L$4940,1,'Адресная программа'!$C$20:$C$4940,АЗС!B40,'Адресная программа'!$G$20:$G$4940,"<>Газпромнефть",'Адресная программа'!$F$20:$F$4940,"АЗС")*'Цены|Скидки'!$B$32),'Цены|Скидки'!$C$32,IF(D40>=(SUMIFS('Адресная программа'!$K$20:$K$4940,'Адресная программа'!$L$20:$L$4940,1,'Адресная программа'!$C$20:$C$4940,АЗС!B40,'Адресная программа'!$G$20:$G$4940,"<>Газпромнефть",'Адресная программа'!$F$20:$F$4940,"АЗС")*'Цены|Скидки'!$B$33),'Цены|Скидки'!$C$33,IF(D40>=(SUMIFS('Адресная программа'!$K$20:$K$4940,'Адресная программа'!$L$20:$L$4940,1,'Адресная программа'!$C$20:$C$4940,АЗС!B40,'Адресная программа'!$G$20:$G$4940,"<>Газпромнефть",'Адресная программа'!$F$20:$F$4940,"АЗС")*'Цены|Скидки'!$B$34),'Цены|Скидки'!$C$34,0%)))) | H40: =D$12 | J40: =IF(D40=0,0,1-K40/F40) | K40: =F40*(1-G40)*(1-H40)*(1-IF($AC$2="РА",$AD$2,0))*(1-IF(OR($AC$3="Доп скидка",$AC$3="Сезонная скидка",$AC$3="Welcome скидка")=TRUE,$AD$3,0)) | L40: =K40+M40 | M40: =K40*0.2 | N40: =D40*L$7*1085 | O40: =IF(N40=0,0,(K40/N40*1000)/$D$7*10)
B41: Иркутск | C41: Роснефть | D41: =IF(C41="АЗС",SUMIFS('Адресная программа'!$O$20:$O$4940,'Адресная программа'!$L$20:$L$4940,1,'Адресная программа'!$C$20:$C$4940,АЗС!B41,'Адресная программа'!$F$20:$F$4940,"АЗС",'Адресная программа'!$G$20:$G$4940,"<>Газпромнефть"),SUMIFS('Адресная программа'!$O$20:$O$4940,'Адресная программа'!$L$20:$L$4940,1,'Адресная программа'!$C$20:$C$4940,АЗС!B41,'Адресная программа'!$G$20:$G$4940,АЗС!C41,'Адресная программа'!$F$20:$F$4940,"АЗС")) | E41: ='Цены|Скидки'!$F$11/15*$L$9 | F41: =E41*$L$7*D41 | G41: =IF(D41=SUMIFS('Адресная программа'!$K$20:$K$4940,'Адресная программа'!$L$20:$L$4940,1,'Адресная программа'!$C$20:$C$4940,АЗС!B41,'Адресная программа'!$G$20:$G$4940,"<>Газпромнефть",'Адресная программа'!$F$20:$F$4940,"АЗС"),'Цены|Скидки'!$C$31,IF(D41>=(SUMIFS('Адресная программа'!$K$20:$K$4940,'Адресная программа'!$L$20:$L$4940,1,'Адресная программа'!$C$20:$C$4940,АЗС!B41,'Адресная программа'!$G$20:$G$4940,"<>Газпромнефть",'Адресная программа'!$F$20:$F$4940,"АЗС")*'Цены|Скидки'!$B$32),'Цены|Скидки'!$C$32,IF(D41>=(SUMIFS('Адресная программа'!$K$20:$K$4940,'Адресная программа'!$L$20:$L$4940,1,'Адресная программа'!$C$20:$C$4940,АЗС!B41,'Адресная программа'!$G$20:$G$4940,"<>Газпромнефть",'Адресная программа'!$F$20:$F$4940,"АЗС")*'Цены|Скидки'!$B$33),'Цены|Скидки'!$C$33,IF(D41>=(SUMIFS('Адресная программа'!$K$20:$K$4940,'Адресная программа'!$L$20:$L$4940,1,'Адресная программа'!$C$20:$C$4940,АЗС!B41,'Адресная программа'!$G$20:$G$4940,"<>Газпромнефть",'Адресная программа'!$F$20:$F$4940,"АЗС")*'Цены|Скидки'!$B$34),'Цены|Скидки'!$C$34,0%)))) | H41: =D$12 | J41: =IF(D41=0,0,1-K41/F41) | K41: =F41*(1-G41)*(1-H41)*(1-IF($AC$2="РА",$AD$2,0))*(1-IF(OR($AC$3="Доп скидка",$AC$3="Сезонная скидка",$AC$3="Welcome скидка")=TRUE,$AD$3,0)) | L41: =K41+M41 | M41: =K41*0.2 | N41: =D41*L$7*1085 | O41: =IF(N41=0,0,(K41/N41*1000)/$D$7*10)
B42: Калуга | C42: Роснефть | D42: =IF(C42="АЗС",SUMIFS('Адресная программа'!$O$20:$O$4940,'Адресная программа'!$L$20:$L$4940,1,'Адресная программа'!$C$20:$C$4940,АЗС!B42,'Адресная программа'!$F$20:$F$4940,"АЗС",'Адресная программа'!$G$20:$G$4940,"<>Газпромнефть"),SUMIFS('Адресная программа'!$O$20:$O$4940,'Адресная программа'!$L$20:$L$4940,1,'Адресная программа'!$C$20:$C$4940,АЗС!B42,'Адресная программа'!$G$20:$G$4940,АЗС!C42,'Адресная программа'!$F$20:$F$4940,"АЗС")) | E42: ='Цены|Скидки'!$F$11/15*$L$9 | F42: =E42*$L$7*D42 | G42: =IF(D42=SUMIFS('Адресная программа'!$K$20:$K$4940,'Адресная программа'!$L$20:$L$4940,1,'Адресная программа'!$C$20:$C$4940,АЗС!B42,'Адресная программа'!$G$20:$G$4940,"<>Газпромнефть",'Адресная программа'!$F$20:$F$4940,"АЗС"),'Цены|Скидки'!$C$31,IF(D42>=(SUMIFS('Адресная программа'!$K$20:$K$4940,'Адресная программа'!$L$20:$L$4940,1,'Адресная программа'!$C$20:$C$4940,АЗС!B42,'Адресная программа'!$G$20:$G$4940,"<>Газпромнефть",'Адресная программа'!$F$20:$F$4940,"АЗС")*'Цены|Скидки'!$B$32),'Цены|Скидки'!$C$32,IF(D42>=(SUMIFS('Адресная программа'!$K$20:$K$4940,'Адресная программа'!$L$20:$L$4940,1,'Адресная программа'!$C$20:$C$4940,АЗС!B42,'Адресная программа'!$G$20:$G$4940,"<>Газпромнефть",'Адресная программа'!$F$20:$F$4940,"АЗС")*'Цены|Скидки'!$B$33),'Цены|Скидки'!$C$33,IF(D42>=(SUMIFS('Адресная программа'!$K$20:$K$4940,'Адресная программа'!$L$20:$L$4940,1,'Адресная программа'!$C$20:$C$4940,АЗС!B42,'Адресная программа'!$G$20:$G$4940,"<>Газпромнефть",'Адресная программа'!$F$20:$F$4940,"АЗС")*'Цены|Скидки'!$B$34),'Цены|Скидки'!$C$34,0%)))) | H42: =D$12 | J42: =IF(D42=0,0,1-K42/F42) | K42: =F42*(1-G42)*(1-H42)*(1-IF($AC$2="РА",$AD$2,0))*(1-IF(OR($AC$3="Доп скидка",$AC$3="Сезонная скидка",$AC$3="Welcome скидка")=TRUE,$AD$3,0)) | L42: =K42+M42 | M42: =K42*0.2 | N42: =D42*L$7*1085 | O42: =IF(N42=0,0,(K42/N42*1000)/$D$7*10)
B43: Татарстан | C43: АЗС | D43: =IF(C43="АЗС",SUMIFS('Адресная программа'!$O$20:$O$4940,'Адресная программа'!$L$20:$L$4940,1,'Адресная программа'!$C$20:$C$4940,АЗС!B43,'Адресная программа'!$F$20:$F$4940,"АЗС",'Адресная программа'!$G$20:$G$4940,"<>Газпромнефть"),SUMIFS('Адресная программа'!$O$20:$O$4940,'Адресная программа'!$L$20:$L$4940,1,'Адресная программа'!$C$20:$C$4940,АЗС!B43,'Адресная программа'!$G$20:$G$4940,АЗС!C43,'Адресная программа'!$F$20:$F$4940,"АЗС")) | E43: ='Цены|Скидки'!$F$11/15*$L$9 | F43: =E43*$L$7*D43 | G43: =IF(D43=SUMIFS('Адресная программа'!$K$20:$K$4940,'Адресная программа'!$L$20:$L$4940,1,'Адресная программа'!$C$20:$C$4940,АЗС!B43,'Адресная программа'!$G$20:$G$4940,"<>Газпромнефть",'Адресная программа'!$F$20:$F$4940,"АЗС"),'Цены|Скидки'!$C$31,IF(D43>=(SUMIFS('Адресная программа'!$K$20:$K$4940,'Адресная программа'!$L$20:$L$4940,1,'Адресная программа'!$C$20:$C$4940,АЗС!B43,'Адресная программа'!$G$20:$G$4940,"<>Газпромнефть",'Адресная программа'!$F$20:$F$4940,"АЗС")*'Цены|Скидки'!$B$32),'Цены|Скидки'!$C$32,IF(D43>=(SUMIFS('Адресная программа'!$K$20:$K$4940,'Адресная программа'!$L$20:$L$4940,1,'Адресная программа'!$C$20:$C$4940,АЗС!B43,'Адресная программа'!$G$20:$G$4940,"<>Газпромнефть",'Адресная программа'!$F$20:$F$4940,"АЗС")*'Цены|Скидки'!$B$33),'Цены|Скидки'!$C$33,IF(D43>=(SUMIFS('Адресная программа'!$K$20:$K$4940,'Адресная программа'!$L$20:$L$4940,1,'Адресная программа'!$C$20:$C$4940,АЗС!B43,'Адресная программа'!$G$20:$G$4940,"<>Газпромнефть",'Адресная программа'!$F$20:$F$4940,"АЗС")*'Цены|Скидки'!$B$34),'Цены|Скидки'!$C$34,0%)))) | H43: =D$12 | J43: =IF(D43=0,0,1-K43/F43) | K43: =F43*(1-G43)*(1-H43)*(1-IF($AC$2="РА",$AD$2,0))*(1-IF(OR($AC$3="Доп скидка",$AC$3="Сезонная скидка",$AC$3="Welcome скидка")=TRUE,$AD$3,0)) | L43: =K43+M43 | M43: =K43*0.2 | N43: =D43*L$7*1210 | O43: =IF(N43=0,0,(K43/N43*1000)/$D$7*10)
B44: Татарстан | C44: Башнефть | D44: =IF(C44="АЗС",SUMIFS('Адресная программа'!$O$20:$O$4940,'Адресная программа'!$L$20:$L$4940,1,'Адресная программа'!$C$20:$C$4940,АЗС!B44,'Адресная программа'!$F$20:$F$4940,"АЗС",'Адресная программа'!$G$20:$G$4940,"<>Газпромнефть"),SUMIFS('Адресная программа'!$O$20:$O$4940,'Адресная программа'!$L$20:$L$4940,1,'Адресная программа'!$C$20:$C$4940,АЗС!B44,'Адресная программа'!$G$20:$G$4940,АЗС!C44,'Адресная программа'!$F$20:$F$4940,"АЗС")) | E44: ='Цены|Скидки'!$F$11/15*$L$9 | F44: =E44*$L$7*D44 | G44: =IF(SUM($D$44:$D$45)=SUMIFS('Адресная программа'!$K$20:$K$4940,'Адресная программа'!$L$20:$L$4940,1,'Адресная программа'!$C$20:$C$4940,АЗС!B44,'Адресная программа'!$G$20:$G$4940,"<>Газпромнефть",'Адресная программа'!$F$20:$F$4940,"АЗС"),'Цены|Скидки'!$C$31,IF(SUM($D$44:$D$45)>=(SUMIFS('Адресная программа'!$K$20:$K$4940,'Адресная программа'!$L$20:$L$4940,1,'Адресная программа'!$C$20:$C$4940,АЗС!B44,'Адресная программа'!$G$20:$G$4940,"<>Газпромнефть",'Адресная программа'!$F$20:$F$4940,"АЗС")*'Цены|Скидки'!$B$32),'Цены|Скидки'!$C$32,IF(SUM($D$44:$D$45)>=(SUMIFS('Адресная программа'!$K$20:$K$4940,'Адресная программа'!$L$20:$L$4940,1,'Адресная программа'!$C$20:$C$4940,АЗС!B44,'Адресная программа'!$G$20:$G$4940,"<>Газпромнефть",'Адресная программа'!$F$20:$F$4940,"АЗС")*'Цены|Скидки'!$B$33),'Цены|Скидки'!$C$33,IF(SUM($D$44:$D$45)>=(SUMIFS('Адресная программа'!$K$20:$K$4940,'Адресная программа'!$L$20:$L$4940,1,'Адресная программа'!$C$20:$C$4940,АЗС!B44,'Адресная программа'!$G$20:$G$4940,"<>Газпромнефть",'Адресная программа'!$F$20:$F$4940,"АЗС")*'Цены|Скидки'!$B$34),'Цены|Скидки'!$C$34,IF(SUM($D$44:$D$45)>=(SUMIFS('Адресная программа'!$K$20:$K$4940,'Адресная программа'!$L$20:$L$4940,1,'Адресная программа'!$C$20:$C$4940,АЗС!B44,'Адресная программа'!$G$20:$G$4940,"<>Газпромнефть",'Адресная программа'!$F$20:$F$4940,"АЗС")*'Цены|Скидки'!$B$36-1),'Цены|Скидки'!$C$36,0%))))) | H44: =D$12 | J44: =IF(D44=0,0,1-K44/F44) | K44: =F44*(1-G44)*(1-H44)*(1-IF($AC$2="РА",$AD$2,0))*(1-IF(OR($AC$3="Доп скидка",$AC$3="Сезонная скидка",$AC$3="Welcome скидка")=TRUE,$AD$3,0)) | L44: =K44+M44 | M44: =K44*0.2 | N44: =D44*L$7*1210 | O44: =IF(N44=0,0,(K44/N44*1000)/$D$7*10)
B45: Татарстан | C45: ТАИФ | D45: =IF(C45="АЗС",SUMIFS('Адресная программа'!$O$20:$O$4940,'Адресная программа'!$L$20:$L$4940,1,'Адресная программа'!$C$20:$C$4940,АЗС!B45,'Адресная программа'!$F$20:$F$4940,"АЗС",'Адресная программа'!$G$20:$G$4940,"<>Газпромнефть"),SUMIFS('Адресная программа'!$O$20:$O$4940,'Адресная программа'!$L$20:$L$4940,1,'Адресная программа'!$C$20:$C$4940,АЗС!B45,'Адресная программа'!$G$20:$G$4940,АЗС!C45,'Адресная программа'!$F$20:$F$4940,"АЗС")) | E45: ='Цены|Скидки'!$F$11/15*$L$9 | F45: =E45*$L$7*D45 | G45: =IF(SUM($D$44:$D$45)=SUMIFS('Адресная программа'!$K$20:$K$4940,'Адресная программа'!$L$20:$L$4940,1,'Адресная программа'!$C$20:$C$4940,АЗС!B45,'Адресная программа'!$G$20:$G$4940,"<>Газпромнефть",'Адресная программа'!$F$20:$F$4940,"АЗС"),'Цены|Скидки'!$C$31,IF(SUM($D$44:$D$45)>=(SUMIFS('Адресная программа'!$K$20:$K$4940,'Адресная программа'!$L$20:$L$4940,1,'Адресная программа'!$C$20:$C$4940,АЗС!B45,'Адресная программа'!$G$20:$G$4940,"<>Газпромнефть",'Адресная программа'!$F$20:$F$4940,"АЗС")*'Цены|Скидки'!$B$32),'Цены|Скидки'!$C$32,IF(SUM($D$44:$D$45)>=(SUMIFS('Адресная программа'!$K$20:$K$4940,'Адресная программа'!$L$20:$L$4940,1,'Адресная программа'!$C$20:$C$4940,АЗС!B45,'Адресная программа'!$G$20:$G$4940,"<>Газпромнефть",'Адресная программа'!$F$20:$F$4940,"АЗС")*'Цены|Скидки'!$B$33),'Цены|Скидки'!$C$33,IF(SUM($D$44:$D$45)>=(SUMIFS('Адресная программа'!$K$20:$K$4940,'Адресная программа'!$L$20:$L$4940,1,'Адресная программа'!$C$20:$C$4940,АЗС!B45,'Адресная программа'!$G$20:$G$4940,"<>Газпромнефть",'Адресная программа'!$F$20:$F$4940,"АЗС")*'Цены|Скидки'!$B$34),'Цены|Скидки'!$C$34,IF(SUM($D$44:$D$45)>=(SUMIFS('Адресная программа'!$K$20:$K$4940,'Адресная программа'!$L$20:$L$4940,1,'Адресная программа'!$C$20:$C$4940,АЗС!B45,'Адресная программа'!$G$20:$G$4940,"<>Газпромнефть",'Адресная программа'!$F$20:$F$4940,"АЗС")*'Цены|Скидки'!$B$36-1),'Цены|Скидки'!$C$36,0%))))) | H45: =D$12 | J45: =IF(D45=0,0,1-K45/F45) | K45: =F45*(1-G45)*(1-H45)*(1-IF($AC$2="РА",$AD$2,0))*(1-IF(OR($AC$3="Доп скидка",$AC$3="Сезонная скидка",$AC$3="Welcome скидка")=TRUE,$AD$3,0)) | L45: =K45+M45 | M45: =K45*0.2 | N45: =D45*L$7*1210 | O45: =IF(N45=0,0,(K45/N45*1000)/$D$7*10)
B46: Карелия | C46: Роснефть | D46: =IF(C46="АЗС",SUMIFS('Адресная программа'!$O$20:$O$4940,'Адресная программа'!$L$20:$L$4940,1,'Адресная программа'!$C$20:$C$4940,АЗС!B46,'Адресная программа'!$F$20:$F$4940,"АЗС",'Адресная программа'!$G$20:$G$4940,"<>Газпромнефть"),SUMIFS('Адресная программа'!$O$20:$O$4940,'Адресная программа'!$L$20:$L$4940,1,'Адресная программа'!$C$20:$C$4940,АЗС!B46,'Адресная программа'!$G$20:$G$4940,АЗС!C46,'Адресная программа'!$F$20:$F$4940,"АЗС")) | E46: ='Цены|Скидки'!$F$11/15*$L$9 | F46: =E46*$L$7*D46 | G46: =IF(D46=SUMIFS('Адресная программа'!$K$20:$K$4940,'Адресная программа'!$L$20:$L$4940,1,'Адресная программа'!$C$20:$C$4940,АЗС!B46,'Адресная программа'!$G$20:$G$4940,"<>Газпромнефть",'Адресная программа'!$F$20:$F$4940,"АЗС"),'Цены|Скидки'!$C$31,IF(D46>=(SUMIFS('Адресная программа'!$K$20:$K$4940,'Адресная программа'!$L$20:$L$4940,1,'Адресная программа'!$C$20:$C$4940,АЗС!B46,'Адресная программа'!$G$20:$G$4940,"<>Газпромнефть",'Адресная программа'!$F$20:$F$4940,"АЗС")*'Цены|Скидки'!$B$32),'Цены|Скидки'!$C$32,IF(D46>=(SUMIFS('Адресная программа'!$K$20:$K$4940,'Адресная программа'!$L$20:$L$4940,1,'Адресная программа'!$C$20:$C$4940,АЗС!B46,'Адресная программа'!$G$20:$G$4940,"<>Газпромнефть",'Адресная программа'!$F$20:$F$4940,"АЗС")*'Цены|Скидки'!$B$33),'Цены|Скидки'!$C$33,IF(D46>=(SUMIFS('Адресная программа'!$K$20:$K$4940,'Адресная программа'!$L$20:$L$4940,1,'Адресная программа'!$C$20:$C$4940,АЗС!B46,'Адресная программа'!$G$20:$G$4940,"<>Газпромнефть",'Адресная программа'!$F$20:$F$4940,"АЗС")*'Цены|Скидки'!$B$34),'Цены|Скидки'!$C$34,0%)))) | H46: =D$12 | J46: =IF(D46=0,0,1-K46/F46) | K46: =F46*(1-G46)*(1-H46)*(1-IF($AC$2="РА",$AD$2,0))*(1-IF(OR($AC$3="Доп скидка",$AC$3="Сезонная скидка",$AC$3="Welcome скидка")=TRUE,$AD$3,0)) | L46: =K46+M46 | M46: =K46*0.2 | N46: =D46*L$7*935 | O46: =IF(N46=0,0,(K46/N46*1000)/$D$7*10)
B47: Кострома | C47: Роснефть | D47: =IF(C47="АЗС",SUMIFS('Адресная программа'!$O$20:$O$4940,'Адресная программа'!$L$20:$L$4940,1,'Адресная программа'!$C$20:$C$4940,АЗС!B47,'Адресная программа'!$F$20:$F$4940,"АЗС",'Адресная программа'!$G$20:$G$4940,"<>Газпромнефть"),SUMIFS('Адресная программа'!$O$20:$O$4940,'Адресная программа'!$L$20:$L$4940,1,'Адресная программа'!$C$20:$C$4940,АЗС!B47,'Адресная программа'!$G$20:$G$4940,АЗС!C47,'Адресная программа'!$F$20:$F$4940,"АЗС")) | E47: ='Цены|Скидки'!$F$11/15*$L$9 | F47: =E47*$L$7*D47 | G47: =IF(D47=SUMIFS('Адресная программа'!$K$20:$K$4940,'Адресная программа'!$L$20:$L$4940,1,'Адресная программа'!$C$20:$C$4940,АЗС!B47,'Адресная программа'!$G$20:$G$4940,"<>Газпромнефть",'Адресная программа'!$F$20:$F$4940,"АЗС"),'Цены|Скидки'!$C$31,IF(D47>=(SUMIFS('Адресная программа'!$K$20:$K$4940,'Адресная программа'!$L$20:$L$4940,1,'Адресная программа'!$C$20:$C$4940,АЗС!B47,'Адресная программа'!$G$20:$G$4940,"<>Газпромнефть",'Адресная программа'!$F$20:$F$4940,"АЗС")*'Цены|Скидки'!$B$32),'Цены|Скидки'!$C$32,IF(D47>=(SUMIFS('Адресная программа'!$K$20:$K$4940,'Адресная программа'!$L$20:$L$4940,1,'Адресная программа'!$C$20:$C$4940,АЗС!B47,'Адресная программа'!$G$20:$G$4940,"<>Газпромнефть",'Адресная программа'!$F$20:$F$4940,"АЗС")*'Цены|Скидки'!$B$33),'Цены|Скидки'!$C$33,IF(D47>=(SUMIFS('Адресная программа'!$K$20:$K$4940,'Адресная программа'!$L$20:$L$4940,1,'Адресная программа'!$C$20:$C$4940,АЗС!B47,'Адресная программа'!$G$20:$G$4940,"<>Газпромнефть",'Адресная программа'!$F$20:$F$4940,"АЗС")*'Цены|Скидки'!$B$34),'Цены|Скидки'!$C$34,0%)))) | H47: =D$12 | J47: =IF(D47=0,0,1-K47/F47) | K47: =F47*(1-G47)*(1-H47)*(1-IF($AC$2="РА",$AD$2,0))*(1-IF(OR($AC$3="Доп скидка",$AC$3="Сезонная скидка",$AC$3="Welcome скидка")=TRUE,$AD$3,0)) | L47: =K47+M47 | M47: =K47*0.2 | N47: =D47*L$7*1155 | O47: =IF(N47=0,0,(K47/N47*1000)/$D$7*10)
B48: Красноярск | C48: Газпромнефть | D48: =IF(C48="АЗС",SUMIFS('Адресная программа'!$O$20:$O$4940,'Адресная программа'!$L$20:$L$4940,1,'Адресная программа'!$C$20:$C$4940,АЗС!B48,'Адресная программа'!$F$20:$F$4940,"АЗС",'Адресная программа'!$G$20:$G$4940,"<>Газпромнефть"),SUMIFS('Адресная программа'!$O$20:$O$4940,'Адресная программа'!$L$20:$L$4940,1,'Адресная программа'!$C$20:$C$4940,АЗС!B48,'Адресная программа'!$G$20:$G$4940,АЗС!C48,'Адресная программа'!$F$20:$F$4940,"АЗС")) | E48: ='Цены|Скидки'!$I$11/15*$L$9 | F48: =E48*$L$7*D48 | G48: =IF(D48=SUMIFS('Адресная программа'!$K$20:$K$4940,'Адресная программа'!$L$20:$L$4940,1,'Адресная программа'!$C$20:$C$4940,АЗС!B48,'Адресная программа'!$G$20:$G$4940,"=Газпромнефть",'Адресная программа'!$F$20:$F$4940,"АЗС"),'Цены|Скидки'!$C$43,IF(D48>=(SUMIFS('Адресная программа'!$K$20:$K$4940,'Адресная программа'!$L$20:$L$4940,1,'Адресная программа'!$C$20:$C$4940,АЗС!B48,'Адресная программа'!$G$20:$G$4940,"=Газпромнефть",'Адресная программа'!$F$20:$F$4940,"АЗС")*'Цены|Скидки'!$B$44),'Цены|Скидки'!$C$44,IF(D48>=(SUMIFS('Адресная программа'!$K$20:$K$4940,'Адресная программа'!$L$20:$L$4940,1,'Адресная программа'!$C$20:$C$4940,АЗС!B48,'Адресная программа'!$G$20:$G$4940,"=Газпромнефть",'Адресная программа'!$F$20:$F$4940,"АЗС")*'Цены|Скидки'!$B$45),'Цены|Скидки'!$C$45,IF(D48>=(SUMIFS('Адресная программа'!$K$20:$K$4940,'Адресная программа'!$L$20:$L$4940,1,'Адресная программа'!$C$20:$C$4940,АЗС!B48,'Адресная программа'!$G$20:$G$4940,"=Газпромнефть",'Адресная программа'!$F$20:$F$4940,"АЗС")*'Цены|Скидки'!$B$46),'Цены|Скидки'!$C$46,0%)))) | H48: =$D$12 | I48: ='Адресная программа'!Y19 | J48: =IF(D48=0,0,1-K48/F48) | K48: =F48*(1-G48)*(1-H48)*(1-IF($AC$2="РА",$AD$2,0))*(1-IF(OR($AC$3="Доп скидка",$AC$3="Сезонная скидка",$AC$3="Welcome скидка")=TRUE,$AD$3,0))*(1-'Адресная программа'!Y19) | L48: =K48+M48 | M48: =K48*0.2 | N48: =D48*$L$7*1210 | O48: =IF(N48=0,0,(K48/N48*1000)/$D$7*10)
B49: Краснодар | C49: Роснефть | D49: =IF(C49="АЗС",SUMIFS('Адресная программа'!$O$20:$O$4940,'Адресная программа'!$L$20:$L$4940,1,'Адресная программа'!$C$20:$C$4940,АЗС!B49,'Адресная программа'!$F$20:$F$4940,"АЗС",'Адресная программа'!$G$20:$G$4940,"<>Газпромнефть"),SUMIFS('Адресная программа'!$O$20:$O$4940,'Адресная программа'!$L$20:$L$4940,1,'Адресная программа'!$C$20:$C$4940,АЗС!B49,'Адресная программа'!$G$20:$G$4940,АЗС!C49,'Адресная программа'!$F$20:$F$4940,"АЗС")) | E49: ='Цены|Скидки'!$F$11/15*$L$9 | F49: =E49*$L$7*D49 | G49: =IF(D49=SUMIFS('Адресная программа'!$K$20:$K$4940,'Адресная программа'!$L$20:$L$4940,1,'Адресная программа'!$C$20:$C$4940,АЗС!B49,'Адресная программа'!$G$20:$G$4940,"<>Газпромнефть",'Адресная программа'!$F$20:$F$4940,"АЗС"),'Цены|Скидки'!$C$31,IF(D49>=(SUMIFS('Адресная программа'!$K$20:$K$4940,'Адресная программа'!$L$20:$L$4940,1,'Адресная программа'!$C$20:$C$4940,АЗС!B49,'Адресная программа'!$G$20:$G$4940,"<>Газпромнефть",'Адресная программа'!$F$20:$F$4940,"АЗС")*'Цены|Скидки'!$B$32),'Цены|Скидки'!$C$32,IF(D49>=(SUMIFS('Адресная программа'!$K$20:$K$4940,'Адресная программа'!$L$20:$L$4940,1,'Адресная программа'!$C$20:$C$4940,АЗС!B49,'Адресная программа'!$G$20:$G$4940,"<>Газпромнефть",'Адресная программа'!$F$20:$F$4940,"АЗС")*'Цены|Скидки'!$B$33),'Цены|Скидки'!$C$33,IF(D49>=(SUMIFS('Адресная программа'!$K$20:$K$4940,'Адресная программа'!$L$20:$L$4940,1,'Адресная программа'!$C$20:$C$4940,АЗС!B49,'Адресная программа'!$G$20:$G$4940,"<>Газпромнефть",'Адресная программа'!$F$20:$F$4940,"АЗС")*'Цены|Скидки'!$B$34),'Цены|Скидки'!$C$34,0%)))) | H49: =D$12 | J49: =IF(D49=0,0,1-K49/F49) | K49: =F49*(1-G49)*(1-H49)*(1-IF($AC$2="РА",$AD$2,0))*(1-IF(OR($AC$3="Доп скидка",$AC$3="Сезонная скидка",$AC$3="Welcome скидка")=TRUE,$AD$3,0)) | L49: =K49+M49 | M49: =K49*0.2 | N49: =D49*L$7*1260 | O49: =IF(N49=0,0,(K49/N49*1000)/$D$7*10)
B50: Краснодар | C50: Газпромнефть | D50: =IF(C50="АЗС",SUMIFS('Адресная программа'!$O$20:$O$4940,'Адресная программа'!$L$20:$L$4940,1,'Адресная программа'!$C$20:$C$4940,АЗС!B50,'Адресная программа'!$F$20:$F$4940,"АЗС",'Адресная программа'!$G$20:$G$4940,"<>Газпромнефть"),SUMIFS('Адресная программа'!$O$20:$O$4940,'Адресная программа'!$L$20:$L$4940,1,'Адресная программа'!$C$20:$C$4940,АЗС!B50,'Адресная программа'!$G$20:$G$4940,АЗС!C50,'Адресная программа'!$F$20:$F$4940,"АЗС")) | E50: ='Цены|Скидки'!$I$11/15*$L$9 | F50: =E50*$L$7*D50 | G50: =IF(D50=SUMIFS('Адресная программа'!$K$20:$K$4940,'Адресная программа'!$L$20:$L$4940,1,'Адресная программа'!$C$20:$C$4940,АЗС!B50,'Адресная программа'!$G$20:$G$4940,"=Газпромнефть",'Адресная программа'!$F$20:$F$4940,"АЗС"),'Цены|Скидки'!$C$43,IF(D50>=(SUMIFS('Адресная программа'!$K$20:$K$4940,'Адресная программа'!$L$20:$L$4940,1,'Адресная программа'!$C$20:$C$4940,АЗС!B50,'Адресная программа'!$G$20:$G$4940,"=Газпромнефть",'Адресная программа'!$F$20:$F$4940,"АЗС")*'Цены|Скидки'!$B$44),'Цены|Скидки'!$C$44,IF(D50>=(SUMIFS('Адресная программа'!$K$20:$K$4940,'Адресная программа'!$L$20:$L$4940,1,'Адресная программа'!$C$20:$C$4940,АЗС!B50,'Адресная программа'!$G$20:$G$4940,"=Газпромнефть",'Адресная программа'!$F$20:$F$4940,"АЗС")*'Цены|Скидки'!$B$45),'Цены|Скидки'!$C$45,IF(D50>=(SUMIFS('Адресная программа'!$K$20:$K$4940,'Адресная программа'!$L$20:$L$4940,1,'Адресная программа'!$C$20:$C$4940,АЗС!B50,'Адресная программа'!$G$20:$G$4940,"=Газпромнефть",'Адресная программа'!$F$20:$F$4940,"АЗС")*'Цены|Скидки'!$B$46),'Цены|Скидки'!$C$46,0%)))) | H50: =$D$12 | I50: ='Адресная программа'!Y19 | J50: =IF(D50=0,0,1-K50/F50) | K50: =F50*(1-G50)*(1-H50)*(1-IF($AC$2="РА",$AD$2,0))*(1-IF(OR($AC$3="Доп скидка",$AC$3="Сезонная скидка",$AC$3="Welcome скидка")=TRUE,$AD$3,0))*(1-'Адресная программа'!Y19) | L50: =K50+M50 | M50: =K50*0.2 | N50: =D50*$L$7*1210 | O50: =IF(N50=0,0,(K50/N50*1000)/$D$7*10)
B51: Курск | C51: Роснефть | D51: =IF(C51="АЗС",SUMIFS('Адресная программа'!$O$20:$O$4940,'Адресная программа'!$L$20:$L$4940,1,'Адресная программа'!$C$20:$C$4940,АЗС!B51,'Адресная программа'!$F$20:$F$4940,"АЗС",'Адресная программа'!$G$20:$G$4940,"<>Газпромнефть"),SUMIFS('Адресная программа'!$O$20:$O$4940,'Адресная программа'!$L$20:$L$4940,1,'Адресная программа'!$C$20:$C$4940,АЗС!B51,'Адресная программа'!$G$20:$G$4940,АЗС!C51,'Адресная программа'!$F$20:$F$4940,"АЗС")) | E51: ='Цены|Скидки'!$F$11/15*$L$9 | F51: =E51*$L$7*D51 | G51: =IF(D51=SUMIFS('Адресная программа'!$K$20:$K$4940,'Адресная программа'!$L$20:$L$4940,1,'Адресная программа'!$C$20:$C$4940,АЗС!B51,'Адресная программа'!$G$20:$G$4940,"<>Газпромнефть",'Адресная программа'!$F$20:$F$4940,"АЗС"),'Цены|Скидки'!$C$31,IF(D51>=(SUMIFS('Адресная программа'!$K$20:$K$4940,'Адресная программа'!$L$20:$L$4940,1,'Адресная программа'!$C$20:$C$4940,АЗС!B51,'Адресная программа'!$G$20:$G$4940,"<>Газпромнефть",'Адресная программа'!$F$20:$F$4940,"АЗС")*'Цены|Скидки'!$B$32),'Цены|Скидки'!$C$32,IF(D51>=(SUMIFS('Адресная программа'!$K$20:$K$4940,'Адресная программа'!$L$20:$L$4940,1,'Адресная программа'!$C$20:$C$4940,АЗС!B51,'Адресная программа'!$G$20:$G$4940,"<>Газпромнефть",'Адресная программа'!$F$20:$F$4940,"АЗС")*'Цены|Скидки'!$B$33),'Цены|Скидки'!$C$33,IF(D51>=(SUMIFS('Адресная программа'!$K$20:$K$4940,'Адресная программа'!$L$20:$L$4940,1,'Адресная программа'!$C$20:$C$4940,АЗС!B51,'Адресная программа'!$G$20:$G$4940,"<>Газпромнефть",'Адресная программа'!$F$20:$F$4940,"АЗС")*'Цены|Скидки'!$B$34),'Цены|Скидки'!$C$34,0%)))) | H51: =D$12 | J51: =IF(D51=0,0,1-K51/F51) | K51: =F51*(1-G51)*(1-H51)*(1-IF($AC$2="РА",$AD$2,0))*(1-IF(OR($AC$3="Доп скидка",$AC$3="Сезонная скидка",$AC$3="Welcome скидка")=TRUE,$AD$3,0)) | L51: =K51+M51 | M51: =K51*0.2 | N51: =D51*L$7*1050 | O51: =IF(N51=0,0,(K51/N51*1000)/$D$7*10)
B52: Липецк | C52: Роснефть | D52: =IF(C52="АЗС",SUMIFS('Адресная программа'!$O$20:$O$4940,'Адресная программа'!$L$20:$L$4940,1,'Адресная программа'!$C$20:$C$4940,АЗС!B52,'Адресная программа'!$F$20:$F$4940,"АЗС",'Адресная программа'!$G$20:$G$4940,"<>Газпромнефть"),SUMIFS('Адресная программа'!$O$20:$O$4940,'Адресная программа'!$L$20:$L$4940,1,'Адресная программа'!$C$20:$C$4940,АЗС!B52,'Адресная программа'!$G$20:$G$4940,АЗС!C52,'Адресная программа'!$F$20:$F$4940,"АЗС")) | E52: ='Цены|Скидки'!$F$11/15*$L$9 | F52: =E52*$L$7*D52 | G52: =IF(D52=SUMIFS('Адресная программа'!$K$20:$K$4940,'Адресная программа'!$L$20:$L$4940,1,'Адресная программа'!$C$20:$C$4940,АЗС!B52,'Адресная программа'!$G$20:$G$4940,"<>Газпромнефть",'Адресная программа'!$F$20:$F$4940,"АЗС"),'Цены|Скидки'!$C$31,IF(D52>=(SUMIFS('Адресная программа'!$K$20:$K$4940,'Адресная программа'!$L$20:$L$4940,1,'Адресная программа'!$C$20:$C$4940,АЗС!B52,'Адресная программа'!$G$20:$G$4940,"<>Газпромнефть",'Адресная программа'!$F$20:$F$4940,"АЗС")*'Цены|Скидки'!$B$32),'Цены|Скидки'!$C$32,IF(D52>=(SUMIFS('Адресная программа'!$K$20:$K$4940,'Адресная программа'!$L$20:$L$4940,1,'Адресная программа'!$C$20:$C$4940,АЗС!B52,'Адресная программа'!$G$20:$G$4940,"<>Газпромнефть",'Адресная программа'!$F$20:$F$4940,"АЗС")*'Цены|Скидки'!$B$33),'Цены|Скидки'!$C$33,IF(D52>=(SUMIFS('Адресная программа'!$K$20:$K$4940,'Адресная программа'!$L$20:$L$4940,1,'Адресная программа'!$C$20:$C$4940,АЗС!B52,'Адресная программа'!$G$20:$G$4940,"<>Газпромнефть",'Адресная программа'!$F$20:$F$4940,"АЗС")*'Цены|Скидки'!$B$34),'Цены|Скидки'!$C$34,0%)))) | H52: =D$12 | J52: =IF(D52=0,0,1-K52/F52) | K52: =F52*(1-G52)*(1-H52)*(1-IF($AC$2="РА",$AD$2,0))*(1-IF(OR($AC$3="Доп скидка",$AC$3="Сезонная скидка",$AC$3="Welcome скидка")=TRUE,$AD$3,0)) | L52: =K52+M52 | M52: =K52*0.2 | N52: =D52*L$7*1045 | O52: =IF(N52=0,0,(K52/N52*1000)/$D$7*10)
B53: Нижний Новгород | C53: Роснефть | D53: =IF(C53="АЗС",SUMIFS('Адресная программа'!$O$20:$O$4940,'Адресная программа'!$L$20:$L$4940,1,'Адресная программа'!$C$20:$C$4940,АЗС!B53,'Адресная программа'!$F$20:$F$4940,"АЗС",'Адресная программа'!$G$20:$G$4940,"<>Газпромнефть"),SUMIFS('Адресная программа'!$O$20:$O$4940,'Адресная программа'!$L$20:$L$4940,1,'Адресная программа'!$C$20:$C$4940,АЗС!B53,'Адресная программа'!$G$20:$G$4940,АЗС!C53,'Адресная программа'!$F$20:$F$4940,"АЗС")) | E53: ='Цены|Скидки'!$F$11/15*$L$9 | F53: =E53*$L$7*D53 | G53: =IF(D53=SUMIFS('Адресная программа'!$K$20:$K$4940,'Адресная программа'!$L$20:$L$4940,1,'Адресная программа'!$C$20:$C$4940,АЗС!B53,'Адресная программа'!$G$20:$G$4940,"<>Газпромнефть",'Адресная программа'!$F$20:$F$4940,"АЗС"),'Цены|Скидки'!$C$31,IF(D53>=(SUMIFS('Адресная программа'!$K$20:$K$4940,'Адресная программа'!$L$20:$L$4940,1,'Адресная программа'!$C$20:$C$4940,АЗС!B53,'Адресная программа'!$G$20:$G$4940,"<>Газпромнефть",'Адресная программа'!$F$20:$F$4940,"АЗС")*'Цены|Скидки'!$B$32),'Цены|Скидки'!$C$32,IF(D53>=(SUMIFS('Адресная программа'!$K$20:$K$4940,'Адресная программа'!$L$20:$L$4940,1,'Адресная программа'!$C$20:$C$4940,АЗС!B53,'Адресная программа'!$G$20:$G$4940,"<>Газпромнефть",'Адресная программа'!$F$20:$F$4940,"АЗС")*'Цены|Скидки'!$B$33),'Цены|Скидки'!$C$33,IF(D53>=(SUMIFS('Адресная программа'!$K$20:$K$4940,'Адресная программа'!$L$20:$L$4940,1,'Адресная программа'!$C$20:$C$4940,АЗС!B53,'Адресная программа'!$G$20:$G$4940,"<>Газпромнефть",'Адресная программа'!$F$20:$F$4940,"АЗС")*'Цены|Скидки'!$B$34),'Цены|Скидки'!$C$34,0%)))) | H53: =D$12 | J53: =IF(D53=0,0,1-K53/F53) | K53: =F53*(1-G53)*(1-H53)*(1-IF($AC$2="РА",$AD$2,0))*(1-IF(OR($AC$3="Доп скидка",$AC$3="Сезонная скидка",$AC$3="Welcome скидка")=TRUE,$AD$3,0)) | L53: =K53+M53 | M53: =K53*0.2 | N53: =D53*L$7*1320 | O53: =IF(N53=0,0,(K53/N53*1000)/$D$7*10)
B54: Приволжье (Нижний Новгород, Казань) | C54: Газпромнефть | D54: =IF(C54="АЗС",SUMIFS('Адресная программа'!$O$20:$O$4940,'Адресная программа'!$L$20:$L$4940,1,'Адресная программа'!$C$20:$C$4940,АЗС!B54,'Адресная программа'!$F$20:$F$4940,"АЗС",'Адресная программа'!$G$20:$G$4940,"<>Газпромнефть"),SUMIFS('Адресная программа'!$O$20:$O$4940,'Адресная программа'!$L$20:$L$4940,1,'Адресная программа'!$C$20:$C$4940,АЗС!B54,'Адресная программа'!$G$20:$G$4940,АЗС!C54,'Адресная программа'!$F$20:$F$4940,"АЗС")) | E54: ='Цены|Скидки'!$I$11/15*$L$9 | F54: =E54*$L$7*D54 | G54: =IF(D54=SUMIFS('Адресная программа'!$K$20:$K$4940,'Адресная программа'!$L$20:$L$4940,1,'Адресная программа'!$C$20:$C$4940,АЗС!B54,'Адресная программа'!$G$20:$G$4940,"=Газпромнефть",'Адресная программа'!$F$20:$F$4940,"АЗС"),'Цены|Скидки'!$C$43,IF(D54>=(SUMIFS('Адресная программа'!$K$20:$K$4940,'Адресная программа'!$L$20:$L$4940,1,'Адресная программа'!$C$20:$C$4940,АЗС!B54,'Адресная программа'!$G$20:$G$4940,"=Газпромнефть",'Адресная программа'!$F$20:$F$4940,"АЗС")*'Цены|Скидки'!$B$44),'Цены|Скидки'!$C$44,IF(D54>=(SUMIFS('Адресная программа'!$K$20:$K$4940,'Адресная программа'!$L$20:$L$4940,1,'Адресная программа'!$C$20:$C$4940,АЗС!B54,'Адресная программа'!$G$20:$G$4940,"=Газпромнефть",'Адресная программа'!$F$20:$F$4940,"АЗС")*'Цены|Скидки'!$B$45),'Цены|Скидки'!$C$45,IF(D54>=(SUMIFS('Адресная программа'!$K$20:$K$4940,'Адресная программа'!$L$20:$L$4940,1,'Адресная программа'!$C$20:$C$4940,АЗС!B54,'Адресная программа'!$G$20:$G$4940,"=Газпромнефть",'Адресная программа'!$F$20:$F$4940,"АЗС")*'Цены|Скидки'!$B$46),'Цены|Скидки'!$C$46,0%)))) | H54: =$D$12 | I54: ='Адресная программа'!Y19 | J54: =IF(D54=0,0,1-K54/F54) | K54: =F54*(1-G54)*(1-H54)*(1-IF($AC$2="РА",$AD$2,0))*(1-IF(OR($AC$3="Доп скидка",$AC$3="Сезонная скидка",$AC$3="Welcome скидка")=TRUE,$AD$3,0))*(1-'Адресная программа'!Y19) | L54: =K54+M54 | M54: =K54*0.2 | N54: =D54*$L$7*1210 | O54: =IF(N54=0,0,(K54/N54*1000)/$D$7*10)
B55: Новосибирск | C55: Газпромнефть | D55: =IF(C55="АЗС",SUMIFS('Адресная программа'!$O$20:$O$4940,'Адресная программа'!$L$20:$L$4940,1,'Адресная программа'!$C$20:$C$4940,АЗС!B55,'Адресная программа'!$F$20:$F$4940,"АЗС",'Адресная программа'!$G$20:$G$4940,"<>Газпромнефть"),SUMIFS('Адресная программа'!$O$20:$O$4940,'Адресная программа'!$L$20:$L$4940,1,'Адресная программа'!$C$20:$C$4940,АЗС!B55,'Адресная программа'!$G$20:$G$4940,АЗС!C55,'Адресная программа'!$F$20:$F$4940,"АЗС")) | E55: ='Цены|Скидки'!$I$11/15*$L$9 | F55: =E55*$L$7*D55 | G55: =IF(D55=SUMIFS('Адресная программа'!$K$20:$K$4940,'Адресная программа'!$L$20:$L$4940,1,'Адресная программа'!$C$20:$C$4940,АЗС!B55,'Адресная программа'!$G$20:$G$4940,"=Газпромнефть",'Адресная программа'!$F$20:$F$4940,"АЗС"),'Цены|Скидки'!$C$43,IF(D55>=(SUMIFS('Адресная программа'!$K$20:$K$4940,'Адресная программа'!$L$20:$L$4940,1,'Адресная программа'!$C$20:$C$4940,АЗС!B55,'Адресная программа'!$G$20:$G$4940,"=Газпромнефть",'Адресная программа'!$F$20:$F$4940,"АЗС")*'Цены|Скидки'!$B$44),'Цены|Скидки'!$C$44,IF(D55>=(SUMIFS('Адресная программа'!$K$20:$K$4940,'Адресная программа'!$L$20:$L$4940,1,'Адресная программа'!$C$20:$C$4940,АЗС!B55,'Адресная программа'!$G$20:$G$4940,"=Газпромнефть",'Адресная программа'!$F$20:$F$4940,"АЗС")*'Цены|Скидки'!$B$45),'Цены|Скидки'!$C$45,IF(D55>=(SUMIFS('Адресная программа'!$K$20:$K$4940,'Адресная программа'!$L$20:$L$4940,1,'Адресная программа'!$C$20:$C$4940,АЗС!B55,'Адресная программа'!$G$20:$G$4940,"=Газпромнефть",'Адресная программа'!$F$20:$F$4940,"АЗС")*'Цены|Скидки'!$B$46),'Цены|Скидки'!$C$46,0%)))) | H55: =$D$12 | I55: ='Адресная программа'!Y19 | J55: =IF(D55=0,0,1-K55/F55) | K55: =F55*(1-G55)*(1-H55)*(1-IF($AC$2="РА",$AD$2,0))*(1-IF(OR($AC$3="Доп скидка",$AC$3="Сезонная скидка",$AC$3="Welcome скидка")=TRUE,$AD$3,0))*(1-'Адресная программа'!Y19) | L55: =K55+M55 | M55: =K55*0.2 | N55: =D55*$L$7*1210 | O55: =IF(N55=0,0,(K55/N55*1000)/$D$7*10)
B56: Орел | C56: Роснефть | D56: =IF(C56="АЗС",SUMIFS('Адресная программа'!$O$20:$O$4940,'Адресная программа'!$L$20:$L$4940,1,'Адресная программа'!$C$20:$C$4940,АЗС!B56,'Адресная программа'!$F$20:$F$4940,"АЗС",'Адресная программа'!$G$20:$G$4940,"<>Газпромнефть"),SUMIFS('Адресная программа'!$O$20:$O$4940,'Адресная программа'!$L$20:$L$4940,1,'Адресная программа'!$C$20:$C$4940,АЗС!B56,'Адресная программа'!$G$20:$G$4940,АЗС!C56,'Адресная программа'!$F$20:$F$4940,"АЗС")) | E56: ='Цены|Скидки'!$F$11/15*$L$9 | F56: =E56*$L$7*D56 | G56: =IF(D56=SUMIFS('Адресная программа'!$K$20:$K$4940,'Адресная программа'!$L$20:$L$4940,1,'Адресная программа'!$C$20:$C$4940,АЗС!B56,'Адресная программа'!$G$20:$G$4940,"<>Газпромнефть",'Адресная программа'!$F$20:$F$4940,"АЗС"),'Цены|Скидки'!$C$31,IF(D56>=(SUMIFS('Адресная программа'!$K$20:$K$4940,'Адресная программа'!$L$20:$L$4940,1,'Адресная программа'!$C$20:$C$4940,АЗС!B56,'Адресная программа'!$G$20:$G$4940,"<>Газпромнефть",'Адресная программа'!$F$20:$F$4940,"АЗС")*'Цены|Скидки'!$B$32),'Цены|Скидки'!$C$32,IF(D56>=(SUMIFS('Адресная программа'!$K$20:$K$4940,'Адресная программа'!$L$20:$L$4940,1,'Адресная программа'!$C$20:$C$4940,АЗС!B56,'Адресная программа'!$G$20:$G$4940,"<>Газпромнефть",'Адресная программа'!$F$20:$F$4940,"АЗС")*'Цены|Скидки'!$B$33),'Цены|Скидки'!$C$33,IF(D56>=(SUMIFS('Адресная программа'!$K$20:$K$4940,'Адресная программа'!$L$20:$L$4940,1,'Адресная программа'!$C$20:$C$4940,АЗС!B56,'Адресная программа'!$G$20:$G$4940,"<>Газпромнефть",'Адресная программа'!$F$20:$F$4940,"АЗС")*'Цены|Скидки'!$B$34),'Цены|Скидки'!$C$34,0%)))) | H56: =D$12 | J56: =IF(D56=0,0,1-K56/F56) | K56: =F56*(1-G56)*(1-H56)*(1-IF($AC$2="РА",$AD$2,0))*(1-IF(OR($AC$3="Доп скидка",$AC$3="Сезонная скидка",$AC$3="Welcome скидка")=TRUE,$AD$3,0)) | L56: =K56+M56 | M56: =K56*0.2 | N56: =D56*L$7*1045 | O56: =IF(N56=0,0,(K56/N56*1000)/$D$7*10)
B57: Оренбург | C57: Башнефть | D57: =IF(C57="АЗС",SUMIFS('Адресная программа'!$O$20:$O$4940,'Адресная программа'!$L$20:$L$4940,1,'Адресная программа'!$C$20:$C$4940,АЗС!B57,'Адресная программа'!$F$20:$F$4940,"АЗС",'Адресная программа'!$G$20:$G$4940,"<>Газпромнефть"),SUMIFS('Адресная программа'!$O$20:$O$4940,'Адресная программа'!$L$20:$L$4940,1,'Адресная программа'!$C$20:$C$4940,АЗС!B57,'Адресная программа'!$G$20:$G$4940,АЗС!C57,'Адресная программа'!$F$20:$F$4940,"АЗС")) | E57: ='Цены|Скидки'!$F$11/15*$L$9 | F57: =E57*$L$7*D57 | G57: =IF(D57=SUMIFS('Адресная программа'!$K$20:$K$4940,'Адресная программа'!$L$20:$L$4940,1,'Адресная программа'!$C$20:$C$4940,АЗС!B57,'Адресная программа'!$G$20:$G$4940,"<>Газпромнефть",'Адресная программа'!$F$20:$F$4940,"АЗС"),'Цены|Скидки'!$C$31,IF(D57>=(SUMIFS('Адресная программа'!$K$20:$K$4940,'Адресная программа'!$L$20:$L$4940,1,'Адресная программа'!$C$20:$C$4940,АЗС!B57,'Адресная программа'!$G$20:$G$4940,"<>Газпромнефть",'Адресная программа'!$F$20:$F$4940,"АЗС")*'Цены|Скидки'!$B$32),'Цены|Скидки'!$C$32,IF(D57>=(SUMIFS('Адресная программа'!$K$20:$K$4940,'Адресная программа'!$L$20:$L$4940,1,'Адресная программа'!$C$20:$C$4940,АЗС!B57,'Адресная программа'!$G$20:$G$4940,"<>Газпромнефть",'Адресная программа'!$F$20:$F$4940,"АЗС")*'Цены|Скидки'!$B$33),'Цены|Скидки'!$C$33,IF(D57>=(SUMIFS('Адресная программа'!$K$20:$K$4940,'Адресная программа'!$L$20:$L$4940,1,'Адресная программа'!$C$20:$C$4940,АЗС!B57,'Адресная программа'!$G$20:$G$4940,"<>Газпромнефть",'Адресная программа'!$F$20:$F$4940,"АЗС")*'Цены|Скидки'!$B$34),'Цены|Скидки'!$C$34,0%)))) | H57: =D$12 | J57: =IF(D57=0,0,1-K57/F57) | K57: =F57*(1-G57)*(1-H57)*(1-IF($AC$2="РА",$AD$2,0))*(1-IF(OR($AC$3="Доп скидка",$AC$3="Сезонная скидка",$AC$3="Welcome скидка")=TRUE,$AD$3,0)) | L57: =K57+M57 | M57: =K57*0.2 | N57: =D57*L$7*1085 | O57: =IF(N57=0,0,(K57/N57*1000)/$D$7*10)
B58: Омск | C58: Газпромнефть | D58: =IF(C58="АЗС",SUMIFS('Адресная программа'!$O$20:$O$4940,'Адресная программа'!$L$20:$L$4940,1,'Адресная программа'!$C$20:$C$4940,АЗС!B58,'Адресная программа'!$F$20:$F$4940,"АЗС",'Адресная программа'!$G$20:$G$4940,"<>Газпромнефть"),SUMIFS('Адресная программа'!$O$20:$O$4940,'Адресная программа'!$L$20:$L$4940,1,'Адресная программа'!$C$20:$C$4940,АЗС!B58,'Адресная программа'!$G$20:$G$4940,АЗС!C58,'Адресная программа'!$F$20:$F$4940,"АЗС")) | E58: ='Цены|Скидки'!$I$11/15*$L$9 | F58: =E58*$L$7*D58 | G58: =IF(D58=SUMIFS('Адресная программа'!$K$20:$K$4940,'Адресная программа'!$L$20:$L$4940,1,'Адресная программа'!$C$20:$C$4940,АЗС!B58,'Адресная программа'!$G$20:$G$4940,"=Газпромнефть",'Адресная программа'!$F$20:$F$4940,"АЗС"),'Цены|Скидки'!$C$43,IF(D58>=(SUMIFS('Адресная программа'!$K$20:$K$4940,'Адресная программа'!$L$20:$L$4940,1,'Адресная программа'!$C$20:$C$4940,АЗС!B58,'Адресная программа'!$G$20:$G$4940,"=Газпромнефть",'Адресная программа'!$F$20:$F$4940,"АЗС")*'Цены|Скидки'!$B$44),'Цены|Скидки'!$C$44,IF(D58>=(SUMIFS('Адресная программа'!$K$20:$K$4940,'Адресная программа'!$L$20:$L$4940,1,'Адресная программа'!$C$20:$C$4940,АЗС!B58,'Адресная программа'!$G$20:$G$4940,"=Газпромнефть",'Адресная программа'!$F$20:$F$4940,"АЗС")*'Цены|Скидки'!$B$45),'Цены|Скидки'!$C$45,IF(D58>=(SUMIFS('Адресная программа'!$K$20:$K$4940,'Адресная программа'!$L$20:$L$4940,1,'Адресная программа'!$C$20:$C$4940,АЗС!B58,'Адресная программа'!$G$20:$G$4940,"=Газпромнефть",'Адресная программа'!$F$20:$F$4940,"АЗС")*'Цены|Скидки'!$B$46),'Цены|Скидки'!$C$46,0%)))) | H58: =$D$12 | I58: ='Адресная программа'!Y19 | J58: =IF(D58=0,0,1-K58/F58) | K58: =F58*(1-G58)*(1-H58)*(1-IF($AC$2="РА",$AD$2,0))*(1-IF(OR($AC$3="Доп скидка",$AC$3="Сезонная скидка",$AC$3="Welcome скидка")=TRUE,$AD$3,0))*(1-'Адресная программа'!Y19) | L58: =K58+M58 | M58: =K58*0.2 | N58: =D58*$L$7*1210 | O58: =IF(N58=0,0,(K58/N58*1000)/$D$7*10)
B59: Пенза | C59: Роснефть | D59: =IF(C59="АЗС",SUMIFS('Адресная программа'!$O$20:$O$4940,'Адресная программа'!$L$20:$L$4940,1,'Адресная программа'!$C$20:$C$4940,АЗС!B59,'Адресная программа'!$F$20:$F$4940,"АЗС",'Адресная программа'!$G$20:$G$4940,"<>Газпромнефть"),SUMIFS('Адресная программа'!$O$20:$O$4940,'Адресная программа'!$L$20:$L$4940,1,'Адресная программа'!$C$20:$C$4940,АЗС!B59,'Адресная программа'!$G$20:$G$4940,АЗС!C59,'Адресная программа'!$F$20:$F$4940,"АЗС")) | E59: ='Цены|Скидки'!$F$11/15*$L$9 | F59: =E59*$L$7*D59 | G59: =IF(D59=SUMIFS('Адресная программа'!$K$20:$K$4940,'Адресная программа'!$L$20:$L$4940,1,'Адресная программа'!$C$20:$C$4940,АЗС!B59,'Адресная программа'!$G$20:$G$4940,"<>Газпромнефть",'Адресная программа'!$F$20:$F$4940,"АЗС"),'Цены|Скидки'!$C$31,IF(D59>=(SUMIFS('Адресная программа'!$K$20:$K$4940,'Адресная программа'!$L$20:$L$4940,1,'Адресная программа'!$C$20:$C$4940,АЗС!B59,'Адресная программа'!$G$20:$G$4940,"<>Газпромнефть",'Адресная программа'!$F$20:$F$4940,"АЗС")*'Цены|Скидки'!$B$32),'Цены|Скидки'!$C$32,IF(D59>=(SUMIFS('Адресная программа'!$K$20:$K$4940,'Адресная программа'!$L$20:$L$4940,1,'Адресная программа'!$C$20:$C$4940,АЗС!B59,'Адресная программа'!$G$20:$G$4940,"<>Газпромнефть",'Адресная программа'!$F$20:$F$4940,"АЗС")*'Цены|Скидки'!$B$33),'Цены|Скидки'!$C$33,IF(D59>=(SUMIFS('Адресная программа'!$K$20:$K$4940,'Адресная программа'!$L$20:$L$4940,1,'Адресная программа'!$C$20:$C$4940,АЗС!B59,'Адресная программа'!$G$20:$G$4940,"<>Газпромнефть",'Адресная программа'!$F$20:$F$4940,"АЗС")*'Цены|Скидки'!$B$34),'Цены|Скидки'!$C$34,0%)))) | H59: =D$12 | J59: =IF(D59=0,0,1-K59/F59) | K59: =F59*(1-G59)*(1-H59)*(1-IF($AC$2="РА",$AD$2,0))*(1-IF(OR($AC$3="Доп скидка",$AC$3="Сезонная скидка",$AC$3="Welcome скидка")=TRUE,$AD$3,0)) | L59: =K59+M59 | M59: =K59*0.2 | N59: =D59*L$7*1210 | O59: =IF(N59=0,0,(K59/N59*1000)/$D$7*10)
B60: Ростов-на-Дону | C60: АЗС | D60: =IF(C60="АЗС",SUMIFS('Адресная программа'!$O$20:$O$4940,'Адресная программа'!$L$20:$L$4940,1,'Адресная программа'!$C$20:$C$4940,АЗС!B60,'Адресная программа'!$F$20:$F$4940,"АЗС",'Адресная программа'!$G$20:$G$4940,"<>Газпромнефть"),SUMIFS('Адресная программа'!$O$20:$O$4940,'Адресная программа'!$L$20:$L$4940,1,'Адресная программа'!$C$20:$C$4940,АЗС!B60,'Адресная программа'!$G$20:$G$4940,АЗС!C60,'Адресная программа'!$F$20:$F$4940,"АЗС")) | E60: ='Цены|Скидки'!$F$11/15*$L$9 | F60: =E60*$L$7*D60 | G60: =IF(D60=SUMIFS('Адресная программа'!$K$20:$K$4940,'Адресная программа'!$L$20:$L$4940,1,'Адресная программа'!$C$20:$C$4940,АЗС!B60,'Адресная программа'!$G$20:$G$4940,"<>Газпромнефть",'Адресная программа'!$F$20:$F$4940,"АЗС"),'Цены|Скидки'!$C$31,IF(D60>=(SUMIFS('Адресная программа'!$K$20:$K$4940,'Адресная программа'!$L$20:$L$4940,1,'Адресная программа'!$C$20:$C$4940,АЗС!B60,'Адресная программа'!$G$20:$G$4940,"<>Газпромнефть",'Адресная программа'!$F$20:$F$4940,"АЗС")*'Цены|Скидки'!$B$32),'Цены|Скидки'!$C$32,IF(D60>=(SUMIFS('Адресная программа'!$K$20:$K$4940,'Адресная программа'!$L$20:$L$4940,1,'Адресная программа'!$C$20:$C$4940,АЗС!B60,'Адресная программа'!$G$20:$G$4940,"<>Газпромнефть",'Адресная программа'!$F$20:$F$4940,"АЗС")*'Цены|Скидки'!$B$33),'Цены|Скидки'!$C$33,IF(D60>=(SUMIFS('Адресная программа'!$K$20:$K$4940,'Адресная программа'!$L$20:$L$4940,1,'Адресная программа'!$C$20:$C$4940,АЗС!B60,'Адресная программа'!$G$20:$G$4940,"<>Газпромнефть",'Адресная программа'!$F$20:$F$4940,"АЗС")*'Цены|Скидки'!$B$34),'Цены|Скидки'!$C$34,0%)))) | H60: =D$12 | J60: =IF(D60=0,0,1-K60/F60) | K60: =F60*(1-G60)*(1-H60)*(1-IF($AC$2="РА",$AD$2,0))*(1-IF(OR($AC$3="Доп скидка",$AC$3="Сезонная скидка",$AC$3="Welcome скидка")=TRUE,$AD$3,0)) | L60: =K60+M60 | M60: =K60*0.2 | N60: =D60*L$7*1260 | O60: =IF(N60=0,0,(K60/N60*1000)/$D$7*10)
B61: Ростов-на-Дону | C61: Роснефть | D61: =IF(C61="АЗС",SUMIFS('Адресная программа'!$O$20:$O$4940,'Адресная программа'!$L$20:$L$4940,1,'Адресная программа'!$C$20:$C$4940,АЗС!B61,'Адресная программа'!$F$20:$F$4940,"АЗС",'Адресная программа'!$G$20:$G$4940,"<>Газпромнефть"),SUMIFS('Адресная программа'!$O$20:$O$4940,'Адресная программа'!$L$20:$L$4940,1,'Адресная программа'!$C$20:$C$4940,АЗС!B61,'Адресная программа'!$G$20:$G$4940,АЗС!C61,'Адресная программа'!$F$20:$F$4940,"АЗС")) | E61: ='Цены|Скидки'!$F$11/15*$L$9 | F61: =E61*$L$7*D61 | G61: =IF(SUM($D$61:$D$62)=SUMIFS('Адресная программа'!$K$20:$K$4940,'Адресная программа'!$L$20:$L$4940,1,'Адресная программа'!$C$20:$C$4940,АЗС!B61,'Адресная программа'!$G$20:$G$4940,"<>Газпромнефть",'Адресная программа'!$F$20:$F$4940,"АЗС"),'Цены|Скидки'!$C$31,IF(SUM($D$61:$D$62)>=(SUMIFS('Адресная программа'!$K$20:$K$4940,'Адресная программа'!$L$20:$L$4940,1,'Адресная программа'!$C$20:$C$4940,АЗС!B61,'Адресная программа'!$G$20:$G$4940,"<>Газпромнефть",'Адресная программа'!$F$20:$F$4940,"АЗС")*'Цены|Скидки'!$B$32),'Цены|Скидки'!$C$32,IF(SUM($D$61:$D$62)>=(SUMIFS('Адресная программа'!$K$20:$K$4940,'Адресная программа'!$L$20:$L$4940,1,'Адресная программа'!$C$20:$C$4940,АЗС!B61,'Адресная программа'!$G$20:$G$4940,"<>Газпромнефть",'Адресная программа'!$F$20:$F$4940,"АЗС")*'Цены|Скидки'!$B$33),'Цены|Скидки'!$C$33,IF(SUM($D$61:$D$62)>=(SUMIFS('Адресная программа'!$K$20:$K$4940,'Адресная программа'!$L$20:$L$4940,1,'Адресная программа'!$C$20:$C$4940,АЗС!B61,'Адресная программа'!$G$20:$G$4940,"<>Газпромнефть",'Адресная программа'!$F$20:$F$4940,"АЗС")*'Цены|Скидки'!$B$34),'Цены|Скидки'!$C$34,IF(SUM($D$61:$D$62)>=(SUMIFS('Адресная программа'!$K$20:$K$4940,'Адресная программа'!$L$20:$L$4940,1,'Адресная программа'!$C$20:$C$4940,АЗС!B61,'Адресная программа'!$G$20:$G$4940,"<>Газпромнефть",'Адресная программа'!$F$20:$F$4940,"АЗС")*'Цены|Скидки'!$B$36-1),'Цены|Скидки'!$C$36,0%))))) | H61: =D$12 | J61: =IF(D61=0,0,1-K61/F61) | K61: =F61*(1-G61)*(1-H61)*(1-IF($AC$2="РА",$AD$2,0))*(1-IF(OR($AC$3="Доп скидка",$AC$3="Сезонная скидка",$AC$3="Welcome скидка")=TRUE,$AD$3,0)) | L61: =K61+M61 | M61: =K61*0.2 | N61: =D61*L$7*1260 | O61: =IF(N61=0,0,(K61/N61*1000)/$D$7*10)
B62: Ростов-на-Дону | C62: Эксон Ойл | D62: =IF(C62="АЗС",SUMIFS('Адресная программа'!$O$20:$O$4940,'Адресная программа'!$L$20:$L$4940,1,'Адресная программа'!$C$20:$C$4940,АЗС!B62,'Адресная программа'!$F$20:$F$4940,"АЗС",'Адресная программа'!$G$20:$G$4940,"<>Газпромнефть"),SUMIFS('Адресная программа'!$O$20:$O$4940,'Адресная программа'!$L$20:$L$4940,1,'Адресная программа'!$C$20:$C$4940,АЗС!B62,'Адресная программа'!$G$20:$G$4940,АЗС!C62,'Адресная программа'!$F$20:$F$4940,"АЗС")) | E62: ='Цены|Скидки'!$F$11/15*$L$9 | F62: =E62*$L$7*D62 | G62: =IF(SUM($D$61:$D$62)=SUMIFS('Адресная программа'!$K$20:$K$4940,'Адресная программа'!$L$20:$L$4940,1,'Адресная программа'!$C$20:$C$4940,АЗС!B62,'Адресная программа'!$G$20:$G$4940,"<>Газпромнефть",'Адресная программа'!$F$20:$F$4940,"АЗС"),'Цены|Скидки'!$C$31,IF(SUM($D$61:$D$62)>=(SUMIFS('Адресная программа'!$K$20:$K$4940,'Адресная программа'!$L$20:$L$4940,1,'Адресная программа'!$C$20:$C$4940,АЗС!B62,'Адресная программа'!$G$20:$G$4940,"<>Газпромнефть",'Адресная программа'!$F$20:$F$4940,"АЗС")*'Цены|Скидки'!$B$32),'Цены|Скидки'!$C$32,IF(SUM($D$61:$D$62)>=(SUMIFS('Адресная программа'!$K$20:$K$4940,'Адресная программа'!$L$20:$L$4940,1,'Адресная программа'!$C$20:$C$4940,АЗС!B62,'Адресная программа'!$G$20:$G$4940,"<>Газпромнефть",'Адресная программа'!$F$20:$F$4940,"АЗС")*'Цены|Скидки'!$B$33),'Цены|Скидки'!$C$33,IF(SUM($D$61:$D$62)>=(SUMIFS('Адресная программа'!$K$20:$K$4940,'Адресная программа'!$L$20:$L$4940,1,'Адресная программа'!$C$20:$C$4940,АЗС!B62,'Адресная программа'!$G$20:$G$4940,"<>Газпромнефть",'Адресная программа'!$F$20:$F$4940,"АЗС")*'Цены|Скидки'!$B$34),'Цены|Скидки'!$C$34,IF(SUM($D$61:$D$62)>=(SUMIFS('Адресная программа'!$K$20:$K$4940,'Адресная программа'!$L$20:$L$4940,1,'Адресная программа'!$C$20:$C$4940,АЗС!B62,'Адресная программа'!$G$20:$G$4940,"<>Газпромнефть",'Адресная программа'!$F$20:$F$4940,"АЗС")*'Цены|Скидки'!$B$36-1),'Цены|Скидки'!$C$36,0%))))) | H62: =D$12 | J62: =IF(D62=0,0,1-K62/F62) | K62: =F62*(1-G62)*(1-H62)*(1-IF($AC$2="РА",$AD$2,0))*(1-IF(OR($AC$3="Доп скидка",$AC$3="Сезонная скидка",$AC$3="Welcome скидка")=TRUE,$AD$3,0)) | L62: =K62+M62 | M62: =K62*0.2 | N62: =D62*L$7*1260 | O62: =IF(N62=0,0,(K62/N62*1000)/$D$7*10)
B63: Рязань | C63: Роснефть | D63: =IF(C63="АЗС",SUMIFS('Адресная программа'!$O$20:$O$4940,'Адресная программа'!$L$20:$L$4940,1,'Адресная программа'!$C$20:$C$4940,АЗС!B63,'Адресная программа'!$F$20:$F$4940,"АЗС",'Адресная программа'!$G$20:$G$4940,"<>Газпромнефть"),SUMIFS('Адресная программа'!$O$20:$O$4940,'Адресная программа'!$L$20:$L$4940,1,'Адресная программа'!$C$20:$C$4940,АЗС!B63,'Адресная программа'!$G$20:$G$4940,АЗС!C63,'Адресная программа'!$F$20:$F$4940,"АЗС")) | E63: ='Цены|Скидки'!$F$11/15*$L$9 | F63: =E63*$L$7*D63 | G63: =IF(D63=SUMIFS('Адресная программа'!$K$20:$K$4940,'Адресная программа'!$L$20:$L$4940,1,'Адресная программа'!$C$20:$C$4940,АЗС!B63,'Адресная программа'!$G$20:$G$4940,"<>Газпромнефть",'Адресная программа'!$F$20:$F$4940,"АЗС"),'Цены|Скидки'!$C$31,IF(D63>=(SUMIFS('Адресная программа'!$K$20:$K$4940,'Адресная программа'!$L$20:$L$4940,1,'Адресная программа'!$C$20:$C$4940,АЗС!B63,'Адресная программа'!$G$20:$G$4940,"<>Газпромнефть",'Адресная программа'!$F$20:$F$4940,"АЗС")*'Цены|Скидки'!$B$32),'Цены|Скидки'!$C$32,IF(D63>=(SUMIFS('Адресная программа'!$K$20:$K$4940,'Адресная программа'!$L$20:$L$4940,1,'Адресная программа'!$C$20:$C$4940,АЗС!B63,'Адресная программа'!$G$20:$G$4940,"<>Газпромнефть",'Адресная программа'!$F$20:$F$4940,"АЗС")*'Цены|Скидки'!$B$33),'Цены|Скидки'!$C$33,IF(D63>=(SUMIFS('Адресная программа'!$K$20:$K$4940,'Адресная программа'!$L$20:$L$4940,1,'Адресная программа'!$C$20:$C$4940,АЗС!B63,'Адресная программа'!$G$20:$G$4940,"<>Газпромнефть",'Адресная программа'!$F$20:$F$4940,"АЗС")*'Цены|Скидки'!$B$34),'Цены|Скидки'!$C$34,0%)))) | H63: =D$12 | J63: =IF(D63=0,0,1-K63/F63) | K63: =F63*(1-G63)*(1-H63)*(1-IF($AC$2="РА",$AD$2,0))*(1-IF(OR($AC$3="Доп скидка",$AC$3="Сезонная скидка",$AC$3="Welcome скидка")=TRUE,$AD$3,0)) | L63: =K63+M63 | M63: =K63*0.2 | N63: =D63*$L$7*1210 | O63: =IF(N63=0,0,(K63/N63*1000)/$D$7*10)
B64: Самара | C64: АЗС | D64: =IF(C64="АЗС",SUMIFS('Адресная программа'!$O$20:$O$4940,'Адресная программа'!$L$20:$L$4940,1,'Адресная программа'!$C$20:$C$4940,АЗС!B64,'Адресная программа'!$F$20:$F$4940,"АЗС",'Адресная программа'!$G$20:$G$4940,"<>Газпромнефть"),SUMIFS('Адресная программа'!$O$20:$O$4940,'Адресная программа'!$L$20:$L$4940,1,'Адресная программа'!$C$20:$C$4940,АЗС!B64,'Адресная программа'!$G$20:$G$4940,АЗС!C64,'Адресная программа'!$F$20:$F$4940,"АЗС")) | E64: ='Цены|Скидки'!$F$11/15*$L$9 | F64: =E64*$L$7*D64 | G64: =IF(D64=SUMIFS('Адресная программа'!$K$20:$K$4940,'Адресная программа'!$L$20:$L$4940,1,'Адресная программа'!$C$20:$C$4940,АЗС!B64,'Адресная программа'!$G$20:$G$4940,"<>Газпромнефть",'Адресная программа'!$F$20:$F$4940,"АЗС"),'Цены|Скидки'!$C$31,IF(D64>=(SUMIFS('Адресная программа'!$K$20:$K$4940,'Адресная программа'!$L$20:$L$4940,1,'Адресная программа'!$C$20:$C$4940,АЗС!B64,'Адресная программа'!$G$20:$G$4940,"<>Газпромнефть",'Адресная программа'!$F$20:$F$4940,"АЗС")*'Цены|Скидки'!$B$32),'Цены|Скидки'!$C$32,IF(D64>=(SUMIFS('Адресная программа'!$K$20:$K$4940,'Адресная программа'!$L$20:$L$4940,1,'Адресная программа'!$C$20:$C$4940,АЗС!B64,'Адресная программа'!$G$20:$G$4940,"<>Газпромнефть",'Адресная программа'!$F$20:$F$4940,"АЗС")*'Цены|Скидки'!$B$33),'Цены|Скидки'!$C$33,IF(D64>=(SUMIFS('Адресная программа'!$K$20:$K$4940,'Адресная программа'!$L$20:$L$4940,1,'Адресная программа'!$C$20:$C$4940,АЗС!B64,'Адресная программа'!$G$20:$G$4940,"<>Газпромнефть",'Адресная программа'!$F$20:$F$4940,"АЗС")*'Цены|Скидки'!$B$34),'Цены|Скидки'!$C$34,0%)))) | H64: =D$12 | J64: =IF(D64=0,0,1-K64/F64) | K64: =F64*(1-G64)*(1-H64)*(1-IF($AC$2="РА",$AD$2,0))*(1-IF(OR($AC$3="Доп скидка",$AC$3="Сезонная скидка",$AC$3="Welcome скидка")=TRUE,$AD$3,0)) | L64: =K64+M64 | M64: =K64*0.2 | N64: =D64*L$7*1260 | O64: =IF(N64=0,0,(K64/N64*1000)/$D$7*10)
B65: Самара | C65: Роснефть | D65: =IF(C65="АЗС",SUMIFS('Адресная программа'!$O$20:$O$4940,'Адресная программа'!$L$20:$L$4940,1,'Адресная программа'!$C$20:$C$4940,АЗС!B65,'Адресная программа'!$F$20:$F$4940,"АЗС",'Адресная программа'!$G$20:$G$4940,"<>Газпромнефть"),SUMIFS('Адресная программа'!$O$20:$O$4940,'Адресная программа'!$L$20:$L$4940,1,'Адресная программа'!$C$20:$C$4940,АЗС!B65,'Адресная программа'!$G$20:$G$4940,АЗС!C65,'Адресная программа'!$F$20:$F$4940,"АЗС")) | E65: ='Цены|Скидки'!$F$11/15*$L$9 | F65: =E65*$L$7*D65 | G65: =IF(SUM($D$65:$D$66)=SUMIFS('Адресная программа'!$K$20:$K$4940,'Адресная программа'!$L$20:$L$4940,1,'Адресная программа'!$C$20:$C$4940,АЗС!B65,'Адресная программа'!$G$20:$G$4940,"<>Газпромнефть",'Адресная программа'!$F$20:$F$4940,"АЗС"),'Цены|Скидки'!$C$31,IF(SUM($D$65:$D$66)>=(SUMIFS('Адресная программа'!$K$20:$K$4940,'Адресная программа'!$L$20:$L$4940,1,'Адресная программа'!$C$20:$C$4940,АЗС!B65,'Адресная программа'!$G$20:$G$4940,"<>Газпромнефть",'Адресная программа'!$F$20:$F$4940,"АЗС")*'Цены|Скидки'!$B$32),'Цены|Скидки'!$C$32,IF(SUM($D$65:$D$66)>=(SUMIFS('Адресная программа'!$K$20:$K$4940,'Адресная программа'!$L$20:$L$4940,1,'Адресная программа'!$C$20:$C$4940,АЗС!B65,'Адресная программа'!$G$20:$G$4940,"<>Газпромнефть",'Адресная программа'!$F$20:$F$4940,"АЗС")*'Цены|Скидки'!$B$33),'Цены|Скидки'!$C$33,IF(SUM($D$65:$D$66)>=(SUMIFS('Адресная программа'!$K$20:$K$4940,'Адресная программа'!$L$20:$L$4940,1,'Адресная программа'!$C$20:$C$4940,АЗС!B65,'Адресная программа'!$G$20:$G$4940,"<>Газпромнефть",'Адресная программа'!$F$20:$F$4940,"АЗС")*'Цены|Скидки'!$B$34),'Цены|Скидки'!$C$34,IF(SUM($D$65:$D$66)>=(SUMIFS('Адресная программа'!$K$20:$K$4940,'Адресная программа'!$L$20:$L$4940,1,'Адресная программа'!$C$20:$C$4940,АЗС!B65,'Адресная программа'!$G$20:$G$4940,"<>Газпромнефть",'Адресная программа'!$F$20:$F$4940,"АЗС")*'Цены|Скидки'!$B$36-1),'Цены|Скидки'!$C$36,0%))))) | H65: =D$12 | J65: =IF(D65=0,0,1-K65/F65) | K65: =F65*(1-G65)*(1-H65)*(1-IF($AC$2="РА",$AD$2,0))*(1-IF(OR($AC$3="Доп скидка",$AC$3="Сезонная скидка",$AC$3="Welcome скидка")=TRUE,$AD$3,0)) | L65: =K65+M65 | M65: =K65*0.2 | N65: =D65*L$7*1260 | O65: =IF(N65=0,0,(K65/N65*1000)/$D$7*10)
B66: Самара | C66: Башнефть | D66: =IF(C66="АЗС",SUMIFS('Адресная программа'!$O$20:$O$4940,'Адресная программа'!$L$20:$L$4940,1,'Адресная программа'!$C$20:$C$4940,АЗС!B66,'Адресная программа'!$F$20:$F$4940,"АЗС",'Адресная программа'!$G$20:$G$4940,"<>Газпромнефть"),SUMIFS('Адресная программа'!$O$20:$O$4940,'Адресная программа'!$L$20:$L$4940,1,'Адресная программа'!$C$20:$C$4940,АЗС!B66,'Адресная программа'!$G$20:$G$4940,АЗС!C66,'Адресная программа'!$F$20:$F$4940,"АЗС")) | E66: ='Цены|Скидки'!$F$11/15*$L$9 | F66: =E66*$L$7*D66 | G66: =IF(SUM($D$65:$D$66)=SUMIFS('Адресная программа'!$K$20:$K$4940,'Адресная программа'!$L$20:$L$4940,1,'Адресная программа'!$C$20:$C$4940,АЗС!B66,'Адресная программа'!$G$20:$G$4940,"<>Газпромнефть",'Адресная программа'!$F$20:$F$4940,"АЗС"),'Цены|Скидки'!$C$31,IF(SUM($D$65:$D$66)>=(SUMIFS('Адресная программа'!$K$20:$K$4940,'Адресная программа'!$L$20:$L$4940,1,'Адресная программа'!$C$20:$C$4940,АЗС!B66,'Адресная программа'!$G$20:$G$4940,"<>Газпромнефть",'Адресная программа'!$F$20:$F$4940,"АЗС")*'Цены|Скидки'!$B$32),'Цены|Скидки'!$C$32,IF(SUM($D$65:$D$66)>=(SUMIFS('Адресная программа'!$K$20:$K$4940,'Адресная программа'!$L$20:$L$4940,1,'Адресная программа'!$C$20:$C$4940,АЗС!B66,'Адресная программа'!$G$20:$G$4940,"<>Газпромнефть",'Адресная программа'!$F$20:$F$4940,"АЗС")*'Цены|Скидки'!$B$33),'Цены|Скидки'!$C$33,IF(SUM($D$65:$D$66)>=(SUMIFS('Адресная программа'!$K$20:$K$4940,'Адресная программа'!$L$20:$L$4940,1,'Адресная программа'!$C$20:$C$4940,АЗС!B66,'Адресная программа'!$G$20:$G$4940,"<>Газпромнефть",'Адресная программа'!$F$20:$F$4940,"АЗС")*'Цены|Скидки'!$B$34),'Цены|Скидки'!$C$34,IF(SUM($D$65:$D$66)>=(SUMIFS('Адресная программа'!$K$20:$K$4940,'Адресная программа'!$L$20:$L$4940,1,'Адресная программа'!$C$20:$C$4940,АЗС!B66,'Адресная программа'!$G$20:$G$4940,"<>Газпромнефть",'Адресная программа'!$F$20:$F$4940,"АЗС")*'Цены|Скидки'!$B$36-1),'Цены|Скидки'!$C$36,0%))))) | H66: =D$12 | J66: =IF(D66=0,0,1-K66/F66) | K66: =F66*(1-G66)*(1-H66)*(1-IF($AC$2="РА",$AD$2,0))*(1-IF(OR($AC$3="Доп скидка",$AC$3="Сезонная скидка",$AC$3="Welcome скидка")=TRUE,$AD$3,0)) | L66: =K66+M66 | M66: =K66*0.2 | N66: =D66*L$7*1260 | O66: =IF(N66=0,0,(K66/N66*1000)/$D$7*10)
B67: Саратов | C67: Роснефть | D67: =IF(C67="АЗС",SUMIFS('Адресная программа'!$O$20:$O$4940,'Адресная программа'!$L$20:$L$4940,1,'Адресная программа'!$C$20:$C$4940,АЗС!B67,'Адресная программа'!$F$20:$F$4940,"АЗС",'Адресная программа'!$G$20:$G$4940,"<>Газпромнефть"),SUMIFS('Адресная программа'!$O$20:$O$4940,'Адресная программа'!$L$20:$L$4940,1,'Адресная программа'!$C$20:$C$4940,АЗС!B67,'Адресная программа'!$G$20:$G$4940,АЗС!C67,'Адресная программа'!$F$20:$F$4940,"АЗС")) | E67: ='Цены|Скидки'!$F$11/15*$L$9 | F67: =E67*$L$7*D67 | G67: =IF(D67=SUMIFS('Адресная программа'!$K$20:$K$4940,'Адресная программа'!$L$20:$L$4940,1,'Адресная программа'!$C$20:$C$4940,АЗС!B67,'Адресная программа'!$G$20:$G$4940,"<>Газпромнефть",'Адресная программа'!$F$20:$F$4940,"АЗС"),'Цены|Скидки'!$C$31,IF(D67>=(SUMIFS('Адресная программа'!$K$20:$K$4940,'Адресная программа'!$L$20:$L$4940,1,'Адресная программа'!$C$20:$C$4940,АЗС!B67,'Адресная программа'!$G$20:$G$4940,"<>Газпромнефть",'Адресная программа'!$F$20:$F$4940,"АЗС")*'Цены|Скидки'!$B$32),'Цены|Скидки'!$C$32,IF(D67>=(SUMIFS('Адресная программа'!$K$20:$K$4940,'Адресная программа'!$L$20:$L$4940,1,'Адресная программа'!$C$20:$C$4940,АЗС!B67,'Адресная программа'!$G$20:$G$4940,"<>Газпромнефть",'Адресная программа'!$F$20:$F$4940,"АЗС")*'Цены|Скидки'!$B$33),'Цены|Скидки'!$C$33,IF(D67>=(SUMIFS('Адресная программа'!$K$20:$K$4940,'Адресная программа'!$L$20:$L$4940,1,'Адресная программа'!$C$20:$C$4940,АЗС!B67,'Адресная программа'!$G$20:$G$4940,"<>Газпромнефть",'Адресная программа'!$F$20:$F$4940,"АЗС")*'Цены|Скидки'!$B$34),'Цены|Скидки'!$C$34,0%)))) | H67: =D$12 | J67: =IF(D67=0,0,1-K67/F67) | K67: =F67*(1-G67)*(1-H67)*(1-IF($AC$2="РА",$AD$2,0))*(1-IF(OR($AC$3="Доп скидка",$AC$3="Сезонная скидка",$AC$3="Welcome скидка")=TRUE,$AD$3,0)) | L67: =K67+M67 | M67: =K67*0.2 | N67: =D67*L$7*1045 | O67: =IF(N67=0,0,(K67/N67*1000)/$D$7*10)
B68: Смоленск | C68: Роснефть | D68: =IF(C68="АЗС",SUMIFS('Адресная программа'!$O$20:$O$4940,'Адресная программа'!$L$20:$L$4940,1,'Адресная программа'!$C$20:$C$4940,АЗС!B68,'Адресная программа'!$F$20:$F$4940,"АЗС",'Адресная программа'!$G$20:$G$4940,"<>Газпромнефть"),SUMIFS('Адресная программа'!$O$20:$O$4940,'Адресная программа'!$L$20:$L$4940,1,'Адресная программа'!$C$20:$C$4940,АЗС!B68,'Адресная программа'!$G$20:$G$4940,АЗС!C68,'Адресная программа'!$F$20:$F$4940,"АЗС")) | E68: ='Цены|Скидки'!$F$11/15*$L$9 | F68: =E68*$L$7*D68 | G68: =IF(D68=SUMIFS('Адресная программа'!$K$20:$K$4940,'Адресная программа'!$L$20:$L$4940,1,'Адресная программа'!$C$20:$C$4940,АЗС!B68,'Адресная программа'!$G$20:$G$4940,"<>Газпромнефть",'Адресная программа'!$F$20:$F$4940,"АЗС"),'Цены|Скидки'!$C$31,IF(D68>=(SUMIFS('Адресная программа'!$K$20:$K$4940,'Адресная программа'!$L$20:$L$4940,1,'Адресная программа'!$C$20:$C$4940,АЗС!B68,'Адресная программа'!$G$20:$G$4940,"<>Газпромнефть",'Адресная программа'!$F$20:$F$4940,"АЗС")*'Цены|Скидки'!$B$32),'Цены|Скидки'!$C$32,IF(D68>=(SUMIFS('Адресная программа'!$K$20:$K$4940,'Адресная программа'!$L$20:$L$4940,1,'Адресная программа'!$C$20:$C$4940,АЗС!B68,'Адресная программа'!$G$20:$G$4940,"<>Газпромнефть",'Адресная программа'!$F$20:$F$4940,"АЗС")*'Цены|Скидки'!$B$33),'Цены|Скидки'!$C$33,IF(D68>=(SUMIFS('Адресная программа'!$K$20:$K$4940,'Адресная программа'!$L$20:$L$4940,1,'Адресная программа'!$C$20:$C$4940,АЗС!B68,'Адресная программа'!$G$20:$G$4940,"<>Газпромнефть",'Адресная программа'!$F$20:$F$4940,"АЗС")*'Цены|Скидки'!$B$34),'Цены|Скидки'!$C$34,0%)))) | H68: =D$12 | J68: =IF(D68=0,0,1-K68/F68) | K68: =F68*(1-G68)*(1-H68)*(1-IF($AC$2="РА",$AD$2,0))*(1-IF(OR($AC$3="Доп скидка",$AC$3="Сезонная скидка",$AC$3="Welcome скидка")=TRUE,$AD$3,0)) | L68: =K68+M68 | M68: =K68*0.2 | N68: =D68*L$7*950 | O68: =IF(N68=0,0,(K68/N68*1000)/$D$7*10)
B69: Ставрополь | C69: Роснефть | D69: =IF(C69="АЗС",SUMIFS('Адресная программа'!$O$20:$O$4940,'Адресная программа'!$L$20:$L$4940,1,'Адресная программа'!$C$20:$C$4940,АЗС!B69,'Адресная программа'!$F$20:$F$4940,"АЗС",'Адресная программа'!$G$20:$G$4940,"<>Газпромнефть"),SUMIFS('Адресная программа'!$O$20:$O$4940,'Адресная программа'!$L$20:$L$4940,1,'Адресная программа'!$C$20:$C$4940,АЗС!B69,'Адресная программа'!$G$20:$G$4940,АЗС!C69,'Адресная программа'!$F$20:$F$4940,"АЗС")) | E69: ='Цены|Скидки'!$F$11/15*$L$9 | F69: =E69*$L$7*D69 | G69: =IF(D69=SUMIFS('Адресная программа'!$K$20:$K$4940,'Адресная программа'!$L$20:$L$4940,1,'Адресная программа'!$C$20:$C$4940,АЗС!B69,'Адресная программа'!$G$20:$G$4940,"<>Газпромнефть",'Адресная программа'!$F$20:$F$4940,"АЗС"),'Цены|Скидки'!$C$31,IF(D69>=(SUMIFS('Адресная программа'!$K$20:$K$4940,'Адресная программа'!$L$20:$L$4940,1,'Адресная программа'!$C$20:$C$4940,АЗС!B69,'Адресная программа'!$G$20:$G$4940,"<>Газпромнефть",'Адресная программа'!$F$20:$F$4940,"АЗС")*'Цены|Скидки'!$B$32),'Цены|Скидки'!$C$32,IF(D69>=(SUMIFS('Адресная программа'!$K$20:$K$4940,'Адресная программа'!$L$20:$L$4940,1,'Адресная программа'!$C$20:$C$4940,АЗС!B69,'Адресная программа'!$G$20:$G$4940,"<>Газпромнефть",'Адресная программа'!$F$20:$F$4940,"АЗС")*'Цены|Скидки'!$B$33),'Цены|Скидки'!$C$33,IF(D69>=(SUMIFS('Адресная программа'!$K$20:$K$4940,'Адресная программа'!$L$20:$L$4940,1,'Адресная программа'!$C$20:$C$4940,АЗС!B69,'Адресная программа'!$G$20:$G$4940,"<>Газпромнефть",'Адресная программа'!$F$20:$F$4940,"АЗС")*'Цены|Скидки'!$B$34),'Цены|Скидки'!$C$34,0%)))) | H69: =D$12 | J69: =IF(D69=0,0,1-K69/F69) | K69: =F69*(1-G69)*(1-H69)*(1-IF($AC$2="РА",$AD$2,0))*(1-IF(OR($AC$3="Доп скидка",$AC$3="Сезонная скидка",$AC$3="Welcome скидка")=TRUE,$AD$3,0)) | L69: =K69+M69 | M69: =K69*0.2 | N69: =D69*L$7*935 | O69: =IF(N69=0,0,(K69/N69*1000)/$D$7*10)
B70: Сургут | C70: Эталон | D70: =IF(C70="АЗС",SUMIFS('Адресная программа'!$O$20:$O$4940,'Адресная программа'!$L$20:$L$4940,1,'Адресная программа'!$C$20:$C$4940,АЗС!B70,'Адресная программа'!$F$20:$F$4940,"АЗС",'Адресная программа'!$G$20:$G$4940,"<>Газпромнефть"),SUMIFS('Адресная программа'!$O$20:$O$4940,'Адресная программа'!$L$20:$L$4940,1,'Адресная программа'!$C$20:$C$4940,АЗС!B70,'Адресная программа'!$G$20:$G$4940,АЗС!C70,'Адресная программа'!$F$20:$F$4940,"АЗС")) | E70: ='Цены|Скидки'!I11/15*$L$9 | F70: =E70*$L$7*D70 | G70: =IF(D70=SUMIFS('Адресная программа'!$K$20:$K$4940,'Адресная программа'!$L$20:$L$4940,1,'Адресная программа'!$C$20:$C$4940,АЗС!B70,'Адресная программа'!$G$20:$G$4940,"<>Газпромнефть",'Адресная программа'!$F$20:$F$4940,"АЗС"),'Цены|Скидки'!$C$31,IF(D70>=(SUMIFS('Адресная программа'!$K$20:$K$4940,'Адресная программа'!$L$20:$L$4940,1,'Адресная программа'!$C$20:$C$4940,АЗС!B70,'Адресная программа'!$G$20:$G$4940,"<>Газпромнефть",'Адресная программа'!$F$20:$F$4940,"АЗС")*'Цены|Скидки'!$B$32),'Цены|Скидки'!$C$32,IF(D70>=(SUMIFS('Адресная программа'!$K$20:$K$4940,'Адресная программа'!$L$20:$L$4940,1,'Адресная программа'!$C$20:$C$4940,АЗС!B70,'Адресная программа'!$G$20:$G$4940,"<>Газпромнефть",'Адресная программа'!$F$20:$F$4940,"АЗС")*'Цены|Скидки'!$B$33),'Цены|Скидки'!$C$33,IF(D70>=(SUMIFS('Адресная программа'!$K$20:$K$4940,'Адресная программа'!$L$20:$L$4940,1,'Адресная программа'!$C$20:$C$4940,АЗС!B70,'Адресная программа'!$G$20:$G$4940,"<>Газпромнефть",'Адресная программа'!$F$20:$F$4940,"АЗС")*'Цены|Скидки'!$B$34),'Цены|Скидки'!$C$34,0%)))) | H70: =D$12 | J70: =IF(D70=0,0,1-K70/F70) | K70: =F70*(1-G70)*(1-H70)*(1-IF($AC$2="РА",$AD$2,0))*(1-IF(OR($AC$3="Доп скидка",$AC$3="Сезонная скидка",$AC$3="Welcome скидка")=TRUE,$AD$3,0)) | L70: =K70+M70 | M70: =K70*0.2 | N70: =D70*L$7*1210 | O70: =IF(N70=0,0,(K70/N70*1000)/$D$7*10)
B71: Тамбов | C71: Роснефть | D71: =IF(C71="АЗС",SUMIFS('Адресная программа'!$O$20:$O$4940,'Адресная программа'!$L$20:$L$4940,1,'Адресная программа'!$C$20:$C$4940,АЗС!B71,'Адресная программа'!$F$20:$F$4940,"АЗС",'Адресная программа'!$G$20:$G$4940,"<>Газпромнефть"),SUMIFS('Адресная программа'!$O$20:$O$4940,'Адресная программа'!$L$20:$L$4940,1,'Адресная программа'!$C$20:$C$4940,АЗС!B71,'Адресная программа'!$G$20:$G$4940,АЗС!C71,'Адресная программа'!$F$20:$F$4940,"АЗС")) | E71: ='Цены|Скидки'!$F$11/15*$L$9 | F71: =E71*$L$7*D71 | G71: =IF(D71=SUMIFS('Адресная программа'!$K$20:$K$4940,'Адресная программа'!$L$20:$L$4940,1,'Адресная программа'!$C$20:$C$4940,АЗС!B71,'Адресная программа'!$G$20:$G$4940,"<>Газпромнефть",'Адресная программа'!$F$20:$F$4940,"АЗС"),'Цены|Скидки'!$C$31,IF(D71>=(SUMIFS('Адресная программа'!$K$20:$K$4940,'Адресная программа'!$L$20:$L$4940,1,'Адресная программа'!$C$20:$C$4940,АЗС!B71,'Адресная программа'!$G$20:$G$4940,"<>Газпромнефть",'Адресная программа'!$F$20:$F$4940,"АЗС")*'Цены|Скидки'!$B$32),'Цены|Скидки'!$C$32,IF(D71>=(SUMIFS('Адресная программа'!$K$20:$K$4940,'Адресная программа'!$L$20:$L$4940,1,'Адресная программа'!$C$20:$C$4940,АЗС!B71,'Адресная программа'!$G$20:$G$4940,"<>Газпромнефть",'Адресная программа'!$F$20:$F$4940,"АЗС")*'Цены|Скидки'!$B$33),'Цены|Скидки'!$C$33,IF(D71>=(SUMIFS('Адресная программа'!$K$20:$K$4940,'Адресная программа'!$L$20:$L$4940,1,'Адресная программа'!$C$20:$C$4940,АЗС!B71,'Адресная программа'!$G$20:$G$4940,"<>Газпромнефть",'Адресная программа'!$F$20:$F$4940,"АЗС")*'Цены|Скидки'!$B$34),'Цены|Скидки'!$C$34,0%)))) | H71: =D$12 | J71: =IF(D71=0,0,1-K71/F71) | K71: =F71*(1-G71)*(1-H71)*(1-IF($AC$2="РА",$AD$2,0))*(1-IF(OR($AC$3="Доп скидка",$AC$3="Сезонная скидка",$AC$3="Welcome скидка")=TRUE,$AD$3,0)) | L71: =K71+M71 | M71: =K71*0.2 | N71: =D71*L$7*1155 | O71: =IF(N71=0,0,(K71/N71*1000)/$D$7*10)
B72: Тверь | C72: Роснефть | D72: =IF(C72="АЗС",SUMIFS('Адресная программа'!$O$20:$O$4940,'Адресная программа'!$L$20:$L$4940,1,'Адресная программа'!$C$20:$C$4940,АЗС!B72,'Адресная программа'!$F$20:$F$4940,"АЗС",'Адресная программа'!$G$20:$G$4940,"<>Газпромнефть"),SUMIFS('Адресная программа'!$O$20:$O$4940,'Адресная программа'!$L$20:$L$4940,1,'Адресная программа'!$C$20:$C$4940,АЗС!B72,'Адресная программа'!$G$20:$G$4940,АЗС!C72,'Адресная программа'!$F$20:$F$4940,"АЗС")) | E72: ='Цены|Скидки'!$F$11/15*$L$9 | F72: =E72*$L$7*D72 | G72: =IF(D72=SUMIFS('Адресная программа'!$K$20:$K$4940,'Адресная программа'!$L$20:$L$4940,1,'Адресная программа'!$C$20:$C$4940,АЗС!B72,'Адресная программа'!$G$20:$G$4940,"<>Газпромнефть",'Адресная программа'!$F$20:$F$4940,"АЗС"),'Цены|Скидки'!$C$31,IF(D72>=(SUMIFS('Адресная программа'!$K$20:$K$4940,'Адресная программа'!$L$20:$L$4940,1,'Адресная программа'!$C$20:$C$4940,АЗС!B72,'Адресная программа'!$G$20:$G$4940,"<>Газпромнефть",'Адресная программа'!$F$20:$F$4940,"АЗС")*'Цены|Скидки'!$B$32),'Цены|Скидки'!$C$32,IF(D72>=(SUMIFS('Адресная программа'!$K$20:$K$4940,'Адресная программа'!$L$20:$L$4940,1,'Адресная программа'!$C$20:$C$4940,АЗС!B72,'Адресная программа'!$G$20:$G$4940,"<>Газпромнефть",'Адресная программа'!$F$20:$F$4940,"АЗС")*'Цены|Скидки'!$B$33),'Цены|Скидки'!$C$33,IF(D72>=(SUMIFS('Адресная программа'!$K$20:$K$4940,'Адресная программа'!$L$20:$L$4940,1,'Адресная программа'!$C$20:$C$4940,АЗС!B72,'Адресная программа'!$G$20:$G$4940,"<>Газпромнефть",'Адресная программа'!$F$20:$F$4940,"АЗС")*'Цены|Скидки'!$B$34),'Цены|Скидки'!$C$34,0%)))) | H72: =D$12 | J72: =IF(D72=0,0,1-K72/F72) | K72: =F72*(1-G72)*(1-H72)*(1-IF($AC$2="РА",$AD$2,0))*(1-IF(OR($AC$3="Доп скидка",$AC$3="Сезонная скидка",$AC$3="Welcome скидка")=TRUE,$AD$3,0)) | L72: =K72+M72 | M72: =K72*0.2 | N72: =D72*L$7*1320 | O72: =IF(N72=0,0,(K72/N72*1000)/$D$7*10)
B73: Тула | C73: Роснефть | D73: =IF(C73="АЗС",SUMIFS('Адресная программа'!$O$20:$O$4940,'Адресная программа'!$L$20:$L$4940,1,'Адресная программа'!$C$20:$C$4940,АЗС!B73,'Адресная программа'!$F$20:$F$4940,"АЗС",'Адресная программа'!$G$20:$G$4940,"<>Газпромнефть"),SUMIFS('Адресная программа'!$O$20:$O$4940,'Адресная программа'!$L$20:$L$4940,1,'Адресная программа'!$C$20:$C$4940,АЗС!B73,'Адресная программа'!$G$20:$G$4940,АЗС!C73,'Адресная программа'!$F$20:$F$4940,"АЗС")) | E73: ='Цены|Скидки'!$F$11/15*$L$9 | F73: =E73*$L$7*D73 | G73: =IF(D73=SUMIFS('Адресная программа'!$K$20:$K$4940,'Адресная программа'!$L$20:$L$4940,1,'Адресная программа'!$C$20:$C$4940,АЗС!B73,'Адресная программа'!$G$20:$G$4940,"<>Газпромнефть",'Адресная программа'!$F$20:$F$4940,"АЗС"),'Цены|Скидки'!$C$31,IF(D73>=(SUMIFS('Адресная программа'!$K$20:$K$4940,'Адресная программа'!$L$20:$L$4940,1,'Адресная программа'!$C$20:$C$4940,АЗС!B73,'Адресная программа'!$G$20:$G$4940,"<>Газпромнефть",'Адресная программа'!$F$20:$F$4940,"АЗС")*'Цены|Скидки'!$B$32),'Цены|Скидки'!$C$32,IF(D73>=(SUMIFS('Адресная программа'!$K$20:$K$4940,'Адресная программа'!$L$20:$L$4940,1,'Адресная программа'!$C$20:$C$4940,АЗС!B73,'Адресная программа'!$G$20:$G$4940,"<>Газпромнефть",'Адресная программа'!$F$20:$F$4940,"АЗС")*'Цены|Скидки'!$B$33),'Цены|Скидки'!$C$33,IF(D73>=(SUMIFS('Адресная программа'!$K$20:$K$4940,'Адресная программа'!$L$20:$L$4940,1,'Адресная программа'!$C$20:$C$4940,АЗС!B73,'Адресная программа'!$G$20:$G$4940,"<>Газпромнефть",'Адресная программа'!$F$20:$F$4940,"АЗС")*'Цены|Скидки'!$B$34),'Цены|Скидки'!$C$34,0%)))) | H73: =D$12 | J73: =IF(D73=0,0,1-K73/F73) | K73: =F73*(1-G73)*(1-H73)*(1-IF($AC$2="РА",$AD$2,0))*(1-IF(OR($AC$3="Доп скидка",$AC$3="Сезонная скидка",$AC$3="Welcome скидка")=TRUE,$AD$3,0)) | L73: =K73+M73 | M73: =K73*0.2 | N73: =D73*L$7*1100 | O73: =IF(N73=0,0,(K73/N73*1000)/$D$7*10)
B74: Томск | C74: Роснефть | D74: =IF(C74="АЗС",SUMIFS('Адресная программа'!$O$20:$O$4940,'Адресная программа'!$L$20:$L$4940,1,'Адресная программа'!$C$20:$C$4940,АЗС!B74,'Адресная программа'!$F$20:$F$4940,"АЗС",'Адресная программа'!$G$20:$G$4940,"<>Газпромнефть"),SUMIFS('Адресная программа'!$O$20:$O$4940,'Адресная программа'!$L$20:$L$4940,1,'Адресная программа'!$C$20:$C$4940,АЗС!B74,'Адресная программа'!$G$20:$G$4940,АЗС!C74,'Адресная программа'!$F$20:$F$4940,"АЗС")) | E74: ='Цены|Скидки'!$F$11/15*$L$9 | F74: =E74*$L$7*D74 | G74: =IF(D74=SUMIFS('Адресная программа'!$K$20:$K$4940,'Адресная программа'!$L$20:$L$4940,1,'Адресная программа'!$C$20:$C$4940,АЗС!B74,'Адресная программа'!$G$20:$G$4940,"<>Газпромнефть",'Адресная программа'!$F$20:$F$4940,"АЗС"),'Цены|Скидки'!$C$31,IF(D74>=(SUMIFS('Адресная программа'!$K$20:$K$4940,'Адресная программа'!$L$20:$L$4940,1,'Адресная программа'!$C$20:$C$4940,АЗС!B74,'Адресная программа'!$G$20:$G$4940,"<>Газпромнефть",'Адресная программа'!$F$20:$F$4940,"АЗС")*'Цены|Скидки'!$B$32),'Цены|Скидки'!$C$32,IF(D74>=(SUMIFS('Адресная программа'!$K$20:$K$4940,'Адресная программа'!$L$20:$L$4940,1,'Адресная программа'!$C$20:$C$4940,АЗС!B74,'Адресная программа'!$G$20:$G$4940,"<>Газпромнефть",'Адресная программа'!$F$20:$F$4940,"АЗС")*'Цены|Скидки'!$B$33),'Цены|Скидки'!$C$33,IF(D74>=(SUMIFS('Адресная программа'!$K$20:$K$4940,'Адресная программа'!$L$20:$L$4940,1,'Адресная программа'!$C$20:$C$4940,АЗС!B74,'Адресная программа'!$G$20:$G$4940,"<>Газпромнефть",'Адресная программа'!$F$20:$F$4940,"АЗС")*'Цены|Скидки'!$B$34),'Цены|Скидки'!$C$34,0%)))) | H74: =D$12 | J74: =IF(D74=0,0,1-K74/F74) | K74: =F74*(1-G74)*(1-H74)*(1-IF($AC$2="РА",$AD$2,0))*(1-IF(OR($AC$3="Доп скидка",$AC$3="Сезонная скидка",$AC$3="Welcome скидка")=TRUE,$AD$3,0)) | L74: =K74+M74 | M74: =K74*0.2 | N74: =D74*L$7*1045 | O74: =IF(N74=0,0,(K74/N74*1000)/$D$7*10)
B75: Тюмень | C75: Газпромнефть | D75: =IF(C75="АЗС",SUMIFS('Адресная программа'!$O$20:$O$4940,'Адресная программа'!$L$20:$L$4940,1,'Адресная программа'!$C$20:$C$4940,АЗС!B75,'Адресная программа'!$F$20:$F$4940,"АЗС",'Адресная программа'!$G$20:$G$4940,"<>Газпромнефть"),SUMIFS('Адресная программа'!$O$20:$O$4940,'Адресная программа'!$L$20:$L$4940,1,'Адресная программа'!$C$20:$C$4940,АЗС!B75,'Адресная программа'!$G$20:$G$4940,АЗС!C75,'Адресная программа'!$F$20:$F$4940,"АЗС")) | E75: ='Цены|Скидки'!$I$11/15*$L$9 | F75: =E75*$L$7*D75 | G75: =IF(D75=SUMIFS('Адресная программа'!$K$20:$K$4940,'Адресная программа'!$L$20:$L$4940,1,'Адресная программа'!$C$20:$C$4940,АЗС!B75,'Адресная программа'!$G$20:$G$4940,"=Газпромнефть",'Адресная программа'!$F$20:$F$4940,"АЗС"),'Цены|Скидки'!$C$43,IF(D75>=(SUMIFS('Адресная программа'!$K$20:$K$4940,'Адресная программа'!$L$20:$L$4940,1,'Адресная программа'!$C$20:$C$4940,АЗС!B75,'Адресная программа'!$G$20:$G$4940,"=Газпромнефть",'Адресная программа'!$F$20:$F$4940,"АЗС")*'Цены|Скидки'!$B$44),'Цены|Скидки'!$C$44,IF(D75>=(SUMIFS('Адресная программа'!$K$20:$K$4940,'Адресная программа'!$L$20:$L$4940,1,'Адресная программа'!$C$20:$C$4940,АЗС!B75,'Адресная программа'!$G$20:$G$4940,"=Газпромнефть",'Адресная программа'!$F$20:$F$4940,"АЗС")*'Цены|Скидки'!$B$45),'Цены|Скидки'!$C$45,IF(D75>=(SUMIFS('Адресная программа'!$K$20:$K$4940,'Адресная программа'!$L$20:$L$4940,1,'Адресная программа'!$C$20:$C$4940,АЗС!B75,'Адресная программа'!$G$20:$G$4940,"=Газпромнефть",'Адресная программа'!$F$20:$F$4940,"АЗС")*'Цены|Скидки'!$B$46),'Цены|Скидки'!$C$46,0%)))) | H75: =$D$12 | I75: ='Адресная программа'!Y19 | J75: =IF(D75=0,0,1-K75/F75) | K75: =F75*(1-G75)*(1-H75)*(1-IF($AC$2="РА",$AD$2,0))*(1-IF(OR($AC$3="Доп скидка",$AC$3="Сезонная скидка",$AC$3="Welcome скидка")=TRUE,$AD$3,0))*(1-'Адресная программа'!Y19) | L75: =K75+M75 | M75: =K75*0.2 | N75: =D75*$L$7*1045 | O75: =IF(N75=0,0,(K75/N75*1000)/$D$7*10)
B76: Улан-Удэ | C76: Роснефть | D76: =IF(C76="АЗС",SUMIFS('Адресная программа'!$O$20:$O$4940,'Адресная программа'!$L$20:$L$4940,1,'Адресная программа'!$C$20:$C$4940,АЗС!B76,'Адресная программа'!$F$20:$F$4940,"АЗС",'Адресная программа'!$G$20:$G$4940,"<>Газпромнефть"),SUMIFS('Адресная программа'!$O$20:$O$4940,'Адресная программа'!$L$20:$L$4940,1,'Адресная программа'!$C$20:$C$4940,АЗС!B76,'Адресная программа'!$G$20:$G$4940,АЗС!C76,'Адресная программа'!$F$20:$F$4940,"АЗС")) | E76: ='Цены|Скидки'!$F$11/15*$L$9 | F76: =E76*$L$7*D76 | G76: =IF(D76=SUMIFS('Адресная программа'!$K$20:$K$4940,'Адресная программа'!$L$20:$L$4940,1,'Адресная программа'!$C$20:$C$4940,АЗС!B76,'Адресная программа'!$G$20:$G$4940,"<>Газпромнефть",'Адресная программа'!$F$20:$F$4940,"АЗС"),'Цены|Скидки'!$C$31,IF(D76>=(SUMIFS('Адресная программа'!$K$20:$K$4940,'Адресная программа'!$L$20:$L$4940,1,'Адресная программа'!$C$20:$C$4940,АЗС!B76,'Адресная программа'!$G$20:$G$4940,"<>Газпромнефть",'Адресная программа'!$F$20:$F$4940,"АЗС")*'Цены|Скидки'!$B$32),'Цены|Скидки'!$C$32,IF(D76>=(SUMIFS('Адресная программа'!$K$20:$K$4940,'Адресная программа'!$L$20:$L$4940,1,'Адресная программа'!$C$20:$C$4940,АЗС!B76,'Адресная программа'!$G$20:$G$4940,"<>Газпромнефть",'Адресная программа'!$F$20:$F$4940,"АЗС")*'Цены|Скидки'!$B$33),'Цены|Скидки'!$C$33,IF(D76>=(SUMIFS('Адресная программа'!$K$20:$K$4940,'Адресная программа'!$L$20:$L$4940,1,'Адресная программа'!$C$20:$C$4940,АЗС!B76,'Адресная программа'!$G$20:$G$4940,"<>Газпромнефть",'Адресная программа'!$F$20:$F$4940,"АЗС")*'Цены|Скидки'!$B$34),'Цены|Скидки'!$C$34,0%)))) | H76: =D$12 | J76: =IF(D76=0,0,1-K76/F76) | K76: =F76*(1-G76)*(1-H76)*(1-IF($AC$2="РА",$AD$2,0))*(1-IF(OR($AC$3="Доп скидка",$AC$3="Сезонная скидка",$AC$3="Welcome скидка")=TRUE,$AD$3,0)) | L76: =K76+M76 | M76: =K76*0.2 | N76: =D76*L$7*1100 | O76: =IF(N76=0,0,(K76/N76*1000)/$D$7*10)
B77: Ульяновск | C77: АЗС | D77: =IF(C77="АЗС",SUMIFS('Адресная программа'!$O$20:$O$4940,'Адресная программа'!$L$20:$L$4940,1,'Адресная программа'!$C$20:$C$4940,АЗС!B77,'Адресная программа'!$F$20:$F$4940,"АЗС",'Адресная программа'!$G$20:$G$4940,"<>Газпромнефть"),SUMIFS('Адресная программа'!$O$20:$O$4940,'Адресная программа'!$L$20:$L$4940,1,'Адресная программа'!$C$20:$C$4940,АЗС!B77,'Адресная программа'!$G$20:$G$4940,АЗС!C77,'Адресная программа'!$F$20:$F$4940,"АЗС")) | E77: ='Цены|Скидки'!$F$11/15*$L$9 | F77: =E77*$L$7*D77 | G77: =IF(D77=SUMIFS('Адресная программа'!$K$20:$K$4940,'Адресная программа'!$L$20:$L$4940,1,'Адресная программа'!$C$20:$C$4940,АЗС!B77,'Адресная программа'!$G$20:$G$4940,"<>Газпромнефть",'Адресная программа'!$F$20:$F$4940,"АЗС"),'Цены|Скидки'!$C$31,IF(D77>=(SUMIFS('Адресная программа'!$K$20:$K$4940,'Адресная программа'!$L$20:$L$4940,1,'Адресная программа'!$C$20:$C$4940,АЗС!B77,'Адресная программа'!$G$20:$G$4940,"<>Газпромнефть",'Адресная программа'!$F$20:$F$4940,"АЗС")*'Цены|Скидки'!$B$32),'Цены|Скидки'!$C$32,IF(D77>=(SUMIFS('Адресная программа'!$K$20:$K$4940,'Адресная программа'!$L$20:$L$4940,1,'Адресная программа'!$C$20:$C$4940,АЗС!B77,'Адресная программа'!$G$20:$G$4940,"<>Газпромнефть",'Адресная программа'!$F$20:$F$4940,"АЗС")*'Цены|Скидки'!$B$33),'Цены|Скидки'!$C$33,IF(D77>=(SUMIFS('Адресная программа'!$K$20:$K$4940,'Адресная программа'!$L$20:$L$4940,1,'Адресная программа'!$C$20:$C$4940,АЗС!B77,'Адресная программа'!$G$20:$G$4940,"<>Газпромнефть",'Адресная программа'!$F$20:$F$4940,"АЗС")*'Цены|Скидки'!$B$34),'Цены|Скидки'!$C$34,0%)))) | H77: =D$12 | J77: =IF(D77=0,0,1-K77/F77) | K77: =F77*(1-G77)*(1-H77)*(1-IF($AC$2="РА",$AD$2,0))*(1-IF(OR($AC$3="Доп скидка",$AC$3="Сезонная скидка",$AC$3="Welcome скидка")=TRUE,$AD$3,0)) | L77: =K77+M77 | M77: =K77*0.2 | N77: =D77*L$7*1260 | O77: =IF(N77=0,0,(K77/N77*1000)/$D$7*10)
B78: Ульяновск | C78: Роснефть | D78: =IF(C78="АЗС",SUMIFS('Адресная программа'!$O$20:$O$4940,'Адресная программа'!$L$20:$L$4940,1,'Адресная программа'!$C$20:$C$4940,АЗС!B78,'Адресная программа'!$F$20:$F$4940,"АЗС",'Адресная программа'!$G$20:$G$4940,"<>Газпромнефть"),SUMIFS('Адресная программа'!$O$20:$O$4940,'Адресная программа'!$L$20:$L$4940,1,'Адресная программа'!$C$20:$C$4940,АЗС!B78,'Адресная программа'!$G$20:$G$4940,АЗС!C78,'Адресная программа'!$F$20:$F$4940,"АЗС")) | E78: ='Цены|Скидки'!$F$11/15*$L$9 | F78: =E78*$L$7*D78 | G78: =IF(SUM($D$78:$D$79)=SUMIFS('Адресная программа'!$K$20:$K$4940,'Адресная программа'!$L$20:$L$4940,1,'Адресная программа'!$C$20:$C$4940,АЗС!B78,'Адресная программа'!$G$20:$G$4940,"<>Газпромнефть",'Адресная программа'!$F$20:$F$4940,"АЗС"),'Цены|Скидки'!$C$31,IF(SUM($D$78:$D$79)>=(SUMIFS('Адресная программа'!$K$20:$K$4940,'Адресная программа'!$L$20:$L$4940,1,'Адресная программа'!$C$20:$C$4940,АЗС!B78,'Адресная программа'!$G$20:$G$4940,"<>Газпромнефть",'Адресная программа'!$F$20:$F$4940,"АЗС")*'Цены|Скидки'!$B$32),'Цены|Скидки'!$C$32,IF(SUM($D$78:$D$79)>=(SUMIFS('Адресная программа'!$K$20:$K$4940,'Адресная программа'!$L$20:$L$4940,1,'Адресная программа'!$C$20:$C$4940,АЗС!B78,'Адресная программа'!$G$20:$G$4940,"<>Газпромнефть",'Адресная программа'!$F$20:$F$4940,"АЗС")*'Цены|Скидки'!$B$33),'Цены|Скидки'!$C$33,IF(SUM($D$78:$D$79)>=(SUMIFS('Адресная программа'!$K$20:$K$4940,'Адресная программа'!$L$20:$L$4940,1,'Адресная программа'!$C$20:$C$4940,АЗС!B78,'Адресная программа'!$G$20:$G$4940,"<>Газпромнефть",'Адресная программа'!$F$20:$F$4940,"АЗС")*'Цены|Скидки'!$B$34),'Цены|Скидки'!$C$34,IF(SUM($D$78:$D$79)>=(SUMIFS('Адресная программа'!$K$20:$K$4940,'Адресная программа'!$L$20:$L$4940,1,'Адресная программа'!$C$20:$C$4940,АЗС!B78,'Адресная программа'!$G$20:$G$4940,"<>Газпромнефть",'Адресная программа'!$F$20:$F$4940,"АЗС")*'Цены|Скидки'!$B$36-1),'Цены|Скидки'!$C$36,0%))))) | H78: =D$12 | J78: =IF(D78=0,0,1-K78/F78) | K78: =F78*(1-G78)*(1-H78)*(1-IF($AC$2="РА",$AD$2,0))*(1-IF(OR($AC$3="Доп скидка",$AC$3="Сезонная скидка",$AC$3="Welcome скидка")=TRUE,$AD$3,0)) | L78: =K78+M78 | M78: =K78*0.2 | N78: =D78*L$7*1260 | O78: =IF(N78=0,0,(K78/N78*1000)/$D$7*10)
B79: Ульяновск | C79: Башнефть | D79: =IF(C79="АЗС",SUMIFS('Адресная программа'!$O$20:$O$4940,'Адресная программа'!$L$20:$L$4940,1,'Адресная программа'!$C$20:$C$4940,АЗС!B79,'Адресная программа'!$F$20:$F$4940,"АЗС",'Адресная программа'!$G$20:$G$4940,"<>Газпромнефть"),SUMIFS('Адресная программа'!$O$20:$O$4940,'Адресная программа'!$L$20:$L$4940,1,'Адресная программа'!$C$20:$C$4940,АЗС!B79,'Адресная программа'!$G$20:$G$4940,АЗС!C79,'Адресная программа'!$F$20:$F$4940,"АЗС")) | E79: ='Цены|Скидки'!$F$11/15*$L$9 | F79: =E79*$L$7*D79 | G79: =IF(SUM($D$78:$D$79)=SUMIFS('Адресная программа'!$K$20:$K$4940,'Адресная программа'!$L$20:$L$4940,1,'Адресная программа'!$C$20:$C$4940,АЗС!B79,'Адресная программа'!$G$20:$G$4940,"<>Газпромнефть",'Адресная программа'!$F$20:$F$4940,"АЗС"),'Цены|Скидки'!$C$31,IF(SUM($D$78:$D$79)>=(SUMIFS('Адресная программа'!$K$20:$K$4940,'Адресная программа'!$L$20:$L$4940,1,'Адресная программа'!$C$20:$C$4940,АЗС!B79,'Адресная программа'!$G$20:$G$4940,"<>Газпромнефть",'Адресная программа'!$F$20:$F$4940,"АЗС")*'Цены|Скидки'!$B$32),'Цены|Скидки'!$C$32,IF(SUM($D$78:$D$79)>=(SUMIFS('Адресная программа'!$K$20:$K$4940,'Адресная программа'!$L$20:$L$4940,1,'Адресная программа'!$C$20:$C$4940,АЗС!B79,'Адресная программа'!$G$20:$G$4940,"<>Газпромнефть",'Адресная программа'!$F$20:$F$4940,"АЗС")*'Цены|Скидки'!$B$33),'Цены|Скидки'!$C$33,IF(SUM($D$78:$D$79)>=(SUMIFS('Адресная программа'!$K$20:$K$4940,'Адресная программа'!$L$20:$L$4940,1,'Адресная программа'!$C$20:$C$4940,АЗС!B79,'Адресная программа'!$G$20:$G$4940,"<>Газпромнефть",'Адресная программа'!$F$20:$F$4940,"АЗС")*'Цены|Скидки'!$B$34),'Цены|Скидки'!$C$34,IF(SUM($D$78:$D$79)>=(SUMIFS('Адресная программа'!$K$20:$K$4940,'Адресная программа'!$L$20:$L$4940,1,'Адресная программа'!$C$20:$C$4940,АЗС!B79,'Адресная программа'!$G$20:$G$4940,"<>Газпромнефть",'Адресная программа'!$F$20:$F$4940,"АЗС")*'Цены|Скидки'!$B$36-1),'Цены|Скидки'!$C$36,0%))))) | H79: =D$12 | J79: =IF(D79=0,0,1-K79/F79) | K79: =F79*(1-G79)*(1-H79)*(1-IF($AC$2="РА",$AD$2,0))*(1-IF(OR($AC$3="Доп скидка",$AC$3="Сезонная скидка",$AC$3="Welcome скидка")=TRUE,$AD$3,0)) | L79: =K79+M79 | M79: =K79*0.2 | N79: =D79*L$7*1260 | O79: =IF(N79=0,0,(K79/N79*1000)/$D$7*10)
B80: Уфа | C80: Башнефть | D80: =IF(C80="АЗС",SUMIFS('Адресная программа'!$O$20:$O$4940,'Адресная программа'!$L$20:$L$4940,1,'Адресная программа'!$C$20:$C$4940,АЗС!B80,'Адресная программа'!$F$20:$F$4940,"АЗС",'Адресная программа'!$G$20:$G$4940,"<>Газпромнефть"),SUMIFS('Адресная программа'!$O$20:$O$4940,'Адресная программа'!$L$20:$L$4940,1,'Адресная программа'!$C$20:$C$4940,АЗС!B80,'Адресная программа'!$G$20:$G$4940,АЗС!C80,'Адресная программа'!$F$20:$F$4940,"АЗС")) | E80: ='Цены|Скидки'!$F$11/15*$L$9 | F80: =E80*$L$7*D80 | G80: =IF(D80=SUMIFS('Адресная программа'!$K$20:$K$4940,'Адресная программа'!$L$20:$L$4940,1,'Адресная программа'!$C$20:$C$4940,АЗС!B80,'Адресная программа'!$G$20:$G$4940,"<>Газпромнефть",'Адресная программа'!$F$20:$F$4940,"АЗС"),'Цены|Скидки'!$C$31,IF(D80>=(SUMIFS('Адресная программа'!$K$20:$K$4940,'Адресная программа'!$L$20:$L$4940,1,'Адресная программа'!$C$20:$C$4940,АЗС!B80,'Адресная программа'!$G$20:$G$4940,"<>Газпромнефть",'Адресная программа'!$F$20:$F$4940,"АЗС")*'Цены|Скидки'!$B$32),'Цены|Скидки'!$C$32,IF(D80>=(SUMIFS('Адресная программа'!$K$20:$K$4940,'Адресная программа'!$L$20:$L$4940,1,'Адресная программа'!$C$20:$C$4940,АЗС!B80,'Адресная программа'!$G$20:$G$4940,"<>Газпромнефть",'Адресная программа'!$F$20:$F$4940,"АЗС")*'Цены|Скидки'!$B$33),'Цены|Скидки'!$C$33,IF(D80>=(SUMIFS('Адресная программа'!$K$20:$K$4940,'Адресная программа'!$L$20:$L$4940,1,'Адресная программа'!$C$20:$C$4940,АЗС!B80,'Адресная программа'!$G$20:$G$4940,"<>Газпромнефть",'Адресная программа'!$F$20:$F$4940,"АЗС")*'Цены|Скидки'!$B$34),'Цены|Скидки'!$C$34,0%)))) | H80: =D$12 | J80: =IF(D80=0,0,1-K80/F80) | K80: =F80*(1-G80)*(1-H80)*(1-IF($AC$2="РА",$AD$2,0))*(1-IF(OR($AC$3="Доп скидка",$AC$3="Сезонная скидка",$AC$3="Welcome скидка")=TRUE,$AD$3,0)) | L80: =K80+M80 | M80: =K80*0.2 | N80: =D80*L$7*1375 | O80: =IF(N80=0,0,(K80/N80*1000)/$D$7*10)
B81: Хакасия | C81: Роснефть | D81: =IF(C81="АЗС",SUMIFS('Адресная программа'!$O$20:$O$4940,'Адресная программа'!$L$20:$L$4940,1,'Адресная программа'!$C$20:$C$4940,АЗС!B81,'Адресная программа'!$F$20:$F$4940,"АЗС",'Адресная программа'!$G$20:$G$4940,"<>Газпромнефть"),SUMIFS('Адресная программа'!$O$20:$O$4940,'Адресная программа'!$L$20:$L$4940,1,'Адресная программа'!$C$20:$C$4940,АЗС!B81,'Адресная программа'!$G$20:$G$4940,АЗС!C81,'Адресная программа'!$F$20:$F$4940,"АЗС")) | E81: ='Цены|Скидки'!$F$11/15*$L$9 | F81: =E81*$L$7*D81 | G81: =IF(D81=SUMIFS('Адресная программа'!$K$20:$K$4940,'Адресная программа'!$L$20:$L$4940,1,'Адресная программа'!$C$20:$C$4940,АЗС!B81,'Адресная программа'!$G$20:$G$4940,"<>Газпромнефть",'Адресная программа'!$F$20:$F$4940,"АЗС"),'Цены|Скидки'!$C$31,IF(D81>=(SUMIFS('Адресная программа'!$K$20:$K$4940,'Адресная программа'!$L$20:$L$4940,1,'Адресная программа'!$C$20:$C$4940,АЗС!B81,'Адресная программа'!$G$20:$G$4940,"<>Газпромнефть",'Адресная программа'!$F$20:$F$4940,"АЗС")*'Цены|Скидки'!$B$32),'Цены|Скидки'!$C$32,IF(D81>=(SUMIFS('Адресная программа'!$K$20:$K$4940,'Адресная программа'!$L$20:$L$4940,1,'Адресная программа'!$C$20:$C$4940,АЗС!B81,'Адресная программа'!$G$20:$G$4940,"<>Газпромнефть",'Адресная программа'!$F$20:$F$4940,"АЗС")*'Цены|Скидки'!$B$33),'Цены|Скидки'!$C$33,IF(D81>=(SUMIFS('Адресная программа'!$K$20:$K$4940,'Адресная программа'!$L$20:$L$4940,1,'Адресная программа'!$C$20:$C$4940,АЗС!B81,'Адресная программа'!$G$20:$G$4940,"<>Газпромнефть",'Адресная программа'!$F$20:$F$4940,"АЗС")*'Цены|Скидки'!$B$34),'Цены|Скидки'!$C$34,0%)))) | H81: =D$12 | J81: =IF(D81=0,0,1-K81/F81) | K81: =F81*(1-G81)*(1-H81)*(1-IF($AC$2="РА",$AD$2,0))*(1-IF(OR($AC$3="Доп скидка",$AC$3="Сезонная скидка",$AC$3="Welcome скидка")=TRUE,$AD$3,0)) | L81: =K81+M81 | M81: =K81*0.2 | N81: =D81*L$7*805 | O81: =IF(N81=0,0,(K81/N81*1000)/$D$7*10)
B82: Челябинск | C82: Башнефть | D82: =IF(C82="АЗС",SUMIFS('Адресная программа'!$O$20:$O$4940,'Адресная программа'!$L$20:$L$4940,1,'Адресная программа'!$C$20:$C$4940,АЗС!B82,'Адресная программа'!$F$20:$F$4940,"АЗС",'Адресная программа'!$G$20:$G$4940,"<>Газпромнефть"),SUMIFS('Адресная программа'!$O$20:$O$4940,'Адресная программа'!$L$20:$L$4940,1,'Адресная программа'!$C$20:$C$4940,АЗС!B82,'Адресная программа'!$G$20:$G$4940,АЗС!C82,'Адресная программа'!$F$20:$F$4940,"АЗС")) | E82: ='Цены|Скидки'!$F$11/15*$L$9 | F82: =E82*$L$7*D82 | G82: =IF(D82=SUMIFS('Адресная программа'!$K$20:$K$4940,'Адресная программа'!$L$20:$L$4940,1,'Адресная программа'!$C$20:$C$4940,АЗС!B82,'Адресная программа'!$G$20:$G$4940,"<>Газпромнефть",'Адресная программа'!$F$20:$F$4940,"АЗС"),'Цены|Скидки'!$C$31,IF(D82>=(SUMIFS('Адресная программа'!$K$20:$K$4940,'Адресная программа'!$L$20:$L$4940,1,'Адресная программа'!$C$20:$C$4940,АЗС!B82,'Адресная программа'!$G$20:$G$4940,"<>Газпромнефть",'Адресная программа'!$F$20:$F$4940,"АЗС")*'Цены|Скидки'!$B$32),'Цены|Скидки'!$C$32,IF(D82>=(SUMIFS('Адресная программа'!$K$20:$K$4940,'Адресная программа'!$L$20:$L$4940,1,'Адресная программа'!$C$20:$C$4940,АЗС!B82,'Адресная программа'!$G$20:$G$4940,"<>Газпромнефть",'Адресная программа'!$F$20:$F$4940,"АЗС")*'Цены|Скидки'!$B$33),'Цены|Скидки'!$C$33,IF(D82>=(SUMIFS('Адресная программа'!$K$20:$K$4940,'Адресная программа'!$L$20:$L$4940,1,'Адресная программа'!$C$20:$C$4940,АЗС!B82,'Адресная программа'!$G$20:$G$4940,"<>Газпромнефть",'Адресная программа'!$F$20:$F$4940,"АЗС")*'Цены|Скидки'!$B$34),'Цены|Скидки'!$C$34,0%)))) | H82: =D$12 | J82: =IF(D82=0,0,1-K82/F82) | K82: =F82*(1-G82)*(1-H82)*(1-IF($AC$2="РА",$AD$2,0))*(1-IF(OR($AC$3="Доп скидка",$AC$3="Сезонная скидка",$AC$3="Welcome скидка")=TRUE,$AD$3,0)) | L82: =K82+M82 | M82: =K82*0.2 | N82: =D82*L$7*1045 | O82: =IF(N82=0,0,(K82/N82*1000)/$D$7*10)
B83: Челябинск | C83: Газпромнефть | D83: =IF(C83="АЗС",SUMIFS('Адресная программа'!$O$20:$O$4940,'Адресная программа'!$L$20:$L$4940,1,'Адресная программа'!$C$20:$C$4940,АЗС!B83,'Адресная программа'!$F$20:$F$4940,"АЗС",'Адресная программа'!$G$20:$G$4940,"<>Газпромнефть"),SUMIFS('Адресная программа'!$O$20:$O$4940,'Адресная программа'!$L$20:$L$4940,1,'Адресная программа'!$C$20:$C$4940,АЗС!B83,'Адресная программа'!$G$20:$G$4940,АЗС!C83,'Адресная программа'!$F$20:$F$4940,"АЗС")) | E83: ='Цены|Скидки'!$I$11/15*$L$9 | F83: =E83*$L$7*D83 | G83: =IF(D83=SUMIFS('Адресная программа'!$K$20:$K$4940,'Адресная программа'!$L$20:$L$4940,1,'Адресная программа'!$C$20:$C$4940,АЗС!B83,'Адресная программа'!$G$20:$G$4940,"=Газпромнефть",'Адресная программа'!$F$20:$F$4940,"АЗС"),'Цены|Скидки'!$C$43,IF(D83>=(SUMIFS('Адресная программа'!$K$20:$K$4940,'Адресная программа'!$L$20:$L$4940,1,'Адресная программа'!$C$20:$C$4940,АЗС!B83,'Адресная программа'!$G$20:$G$4940,"=Газпромнефть",'Адресная программа'!$F$20:$F$4940,"АЗС")*'Цены|Скидки'!$B$44),'Цены|Скидки'!$C$44,IF(D83>=(SUMIFS('Адресная программа'!$K$20:$K$4940,'Адресная программа'!$L$20:$L$4940,1,'Адресная программа'!$C$20:$C$4940,АЗС!B83,'Адресная программа'!$G$20:$G$4940,"=Газпромнефть",'Адресная программа'!$F$20:$F$4940,"АЗС")*'Цены|Скидки'!$B$45),'Цены|Скидки'!$C$45,IF(D83>=(SUMIFS('Адресная программа'!$K$20:$K$4940,'Адресная программа'!$L$20:$L$4940,1,'Адресная программа'!$C$20:$C$4940,АЗС!B83,'Адресная программа'!$G$20:$G$4940,"=Газпромнефть",'Адресная программа'!$F$20:$F$4940,"АЗС")*'Цены|Скидки'!$B$46),'Цены|Скидки'!$C$46,0%)))) | H83: =$D$12 | I83: ='Адресная программа'!Y19 | J83: =IF(D83=0,0,1-K83/F83) | K83: =F83*(1-G83)*(1-H83)*(1-IF($AC$2="РА",$AD$2,0))*(1-IF(OR($AC$3="Доп скидка",$AC$3="Сезонная скидка",$AC$3="Welcome скидка")=TRUE,$AD$3,0))*(1-'Адресная программа'!Y19) | L83: =K83+M83 | M83: =K83*0.2 | N83: =D83*$L$7*1210 | O83: =IF(N83=0,0,(K83/N83*1000)/$D$7*10)
B84: Ярославль | C84: Газпромнефть | D84: =IF(C84="АЗС",SUMIFS('Адресная программа'!$O$20:$O$4940,'Адресная программа'!$L$20:$L$4940,1,'Адресная программа'!$C$20:$C$4940,АЗС!B84,'Адресная программа'!$F$20:$F$4940,"АЗС",'Адресная программа'!$G$20:$G$4940,"<>Газпромнефть"),SUMIFS('Адресная программа'!$O$20:$O$4940,'Адресная программа'!$L$20:$L$4940,1,'Адресная программа'!$C$20:$C$4940,АЗС!B84,'Адресная программа'!$G$20:$G$4940,АЗС!C84,'Адресная программа'!$F$20:$F$4940,"АЗС")) | E84: ='Цены|Скидки'!$I$11/15*$L$9 | F84: =E84*$L$7*D84 | G84: =IF(D84=SUMIFS('Адресная программа'!$K$20:$K$4940,'Адресная программа'!$L$20:$L$4940,1,'Адресная программа'!$C$20:$C$4940,АЗС!B84,'Адресная программа'!$G$20:$G$4940,"=Газпромнефть",'Адресная программа'!$F$20:$F$4940,"АЗС"),'Цены|Скидки'!$C$43,IF(D84>=(SUMIFS('Адресная программа'!$K$20:$K$4940,'Адресная программа'!$L$20:$L$4940,1,'Адресная программа'!$C$20:$C$4940,АЗС!B84,'Адресная программа'!$G$20:$G$4940,"=Газпромнефть",'Адресная программа'!$F$20:$F$4940,"АЗС")*'Цены|Скидки'!$B$44),'Цены|Скидки'!$C$44,IF(D84>=(SUMIFS('Адресная программа'!$K$20:$K$4940,'Адресная программа'!$L$20:$L$4940,1,'Адресная программа'!$C$20:$C$4940,АЗС!B84,'Адресная программа'!$G$20:$G$4940,"=Газпромнефть",'Адресная программа'!$F$20:$F$4940,"АЗС")*'Цены|Скидки'!$B$45),'Цены|Скидки'!$C$45,IF(D84>=(SUMIFS('Адресная программа'!$K$20:$K$4940,'Адресная программа'!$L$20:$L$4940,1,'Адресная программа'!$C$20:$C$4940,АЗС!B84,'Адресная программа'!$G$20:$G$4940,"=Газпромнефть",'Адресная программа'!$F$20:$F$4940,"АЗС")*'Цены|Скидки'!$B$46),'Цены|Скидки'!$C$46,0%)))) | H84: =$D$12 | I84: ='Адресная программа'!Y19 | J84: =IF(D84=0,0,1-K84/F84) | K84: =F84*(1-G84)*(1-H84)*(1-IF($AC$2="РА",$AD$2,0))*(1-IF(OR($AC$3="Доп скидка",$AC$3="Сезонная скидка",$AC$3="Welcome скидка")=TRUE,$AD$3,0))*(1-'Адресная программа'!Y19) | L84: =K84+M84 | M84: =K84*0.2 | N84: =D84*$L$7*1210 | O84: =IF(N84=0,0,(K84/N84*1000)/$D$7*10)
B85: Ярославль | C85: Роснефть | D85: =IF(C85="АЗС",SUMIFS('Адресная программа'!$O$20:$O$4940,'Адресная программа'!$L$20:$L$4940,1,'Адресная программа'!$C$20:$C$4940,АЗС!B85,'Адресная программа'!$F$20:$F$4940,"АЗС",'Адресная программа'!$G$20:$G$4940,"<>Газпромнефть"),SUMIFS('Адресная программа'!$O$20:$O$4940,'Адресная программа'!$L$20:$L$4940,1,'Адресная программа'!$C$20:$C$4940,АЗС!B85,'Адресная программа'!$G$20:$G$4940,АЗС!C85,'Адресная программа'!$F$20:$F$4940,"АЗС")) | E85: ='Цены|Скидки'!$F$11/15*$L$9 | F85: =E85*$L$7*D85 | G85: =IF(D85=SUMIFS('Адресная программа'!$K$20:$K$4940,'Адресная программа'!$L$20:$L$4940,1,'Адресная программа'!$C$20:$C$4940,АЗС!B85,'Адресная программа'!$G$20:$G$4940,"<>Газпромнефть",'Адресная программа'!$F$20:$F$4940,"АЗС"),'Цены|Скидки'!$C$31,IF(D85>=(SUMIFS('Адресная программа'!$K$20:$K$4940,'Адресная программа'!$L$20:$L$4940,1,'Адресная программа'!$C$20:$C$4940,АЗС!B85,'Адресная программа'!$G$20:$G$4940,"<>Газпромнефть",'Адресная программа'!$F$20:$F$4940,"АЗС")*'Цены|Скидки'!$B$32),'Цены|Скидки'!$C$32,IF(D85>=(SUMIFS('Адресная программа'!$K$20:$K$4940,'Адресная программа'!$L$20:$L$4940,1,'Адресная программа'!$C$20:$C$4940,АЗС!B85,'Адресная программа'!$G$20:$G$4940,"<>Газпромнефть",'Адресная программа'!$F$20:$F$4940,"АЗС")*'Цены|Скидки'!$B$33),'Цены|Скидки'!$C$33,IF(D85>=(SUMIFS('Адресная программа'!$K$20:$K$4940,'Адресная программа'!$L$20:$L$4940,1,'Адресная программа'!$C$20:$C$4940,АЗС!B85,'Адресная программа'!$G$20:$G$4940,"<>Газпромнефть",'Адресная программа'!$F$20:$F$4940,"АЗС")*'Цены|Скидки'!$B$34),'Цены|Скидки'!$C$34,0%)))) | H85: =$D$12 | J85: =IF(D85=0,0,1-K85/F85) | K85: =F85*(1-G85)*(1-H85)*(1-IF($AC$2="РА",$AD$2,0))*(1-IF(OR($AC$3="Доп скидка",$AC$3="Сезонная скидка",$AC$3="Welcome скидка")=TRUE,$AD$3,0))*(1-'Адресная программа'!Y20) | L85: =K85+M85 | M85: =K85*0.2 | N85: =D85*$L$7*1210 | O85: =IF(N85=0,0,(K85/N85*1000)/$D$7*10)
C88: Итого: | D88: =SUMIF(C22:C85,"<>АЗС",D22:D85) | F88: =SUMIF(C22:C85,"<>АЗС",F22:F85) | K88: =SUMIF($C$22:$C$85,"<>АЗС",K22:K85) | L88: =SUMIF($C$22:$C$85,"<>АЗС",L22:L85) | M88: =SUMIF($C$22:$C$85,"<>АЗС",M22:M85) | N88: =SUMIF($C$22:$C$85,"<>АЗС",N22:N85) | O88: =SUM((K88/N88*1000)/$D$7*10)
C91: https://www.google.com/maps/d/u/0/viewer?mid=1p-oh9gcbPgDD4ydYuAcHc5N8OzuMUcrE&ll=52.95040983734168%2C55.487263296150196&z=3
B94: * CPT за 10 секундный ролик
B95: * В ходе рекламной кампании, по независящим от оператора причинам, без предварительного уведомления могут происходить изменения в адресной программе размещения (закрытие АЗС по техническим причинам, или на реконструкцию). В подобной ситуации оператор оставляет за собой право компенсировать рекламодателю не размещенные объемы путем предоставления аналогичных замен, дополнительных выходов, увеличения сроков размещения (что из этого возможно).

Sheet Азбука вкуса
AN1: ПК | AO1: 0
B2: Супермаркеты «Азбука вкуса» | AC2: РА | AD2: 0.1 | AN2: РА | AO2: 0.05 | AP2: Доп скидка
B3: Клиент: | D3: Sminex | I3: Всего экранов: | K3: =D26 | AO3: 0.1 | AP3: Welcome скидка
B4: Бренд: | D4: Sminex | I4: Часов работы одного экрана в сутки: | K4: 24 | AO4: 0.15 | AP4: Сезонная скидка
B5: Начало РК: | D5: 45748 | I5: Продолжительность блока в минутах: | K5: 3 | AO5: 0.2
B6: Окончание РК: | D6: 45838 | I6: Блоков в сутки на одном экране: | K6: =K4*60/K5 | AO6: 0.25
B7: Ролик1, сек: | D7: 15 | I7: Кол-во дней размещения: | K7: =D6-D5+1
I8: Кол-во роликов в блоке: | K8: =COUNT(D$7,D$8,D$9)
B9: КАРТА ОХВАТА | D9: фото Азбука вкуса | I9: Итого секунд в блоке: | K9: =SUM(D7:D9) | AO9: 0
B10: Применяемые скидки (последовательно) | I10: Показов в день на одном экране: | K10: =K6*K8 | AO10: 0.05
B11: За кол-во экранов(средн): | D11: =SUBTOTAL(1,G22:G25) | I11: Минут в день на одном экране: | K11: =K6*K9/60 | AO11: 0.1
B12: За период: | D12: =IF(K7>69,'Цены|Скидки'!$C$100,IF(K7>39,'Цены|Скидки'!$C$99,0%)) | I12: Показов на всех экранах за период: | K12: =K10*K7*K3 | AO12: 0.15
B13: =IF(AC2="РА","Скидка для РА:"," ") | D13: =IF(AC2="РА",AD2," ") | I13: OTS: | K13: =M26 | AO13: 0.2
B14: =IF(AC3=0," ",AC3) | D14: =IF(OR(AC3="Доп скидка",AC3="Сезонная скидка",AC3="Welcome скидка")=TRUE,AD3," ") | I14: CPT: | K14: =N26 | AO14: 0.25
B15: Стоимость размещения
B16: Всего, руб. NET: | D16: =J26 | I16: Предоставление ролика до: | K16: =D5-3 | AW16: 16
B17: Всего, руб. GROSS: | D17: =K26 | I17: Оплата до: | K17: =D5-5 | AN17: Автобренд | AW17: 1
AW18: 17
B19: Расчет стоимости кампании в «Азбука вкуса»
B20: Регион | C20: Сеть | D20: Количество экранов | E20: Стоимость размещения в сутки на 1 экране, без НДС | F20: Стоимость размещения по выбранной АП за период, без НДС | G20: Скидка за кол-во экранов | H20: Скидка за период | I20: Итоговая скидка | J20: Стоимость c учетом всех скидок, без НДС | K20: Стоимость c учетом всех скидок, вкл. НДС | L20: Сумма НДС (20%) | M20: OTS | N20: CPT
B22: Москва | C22: Азбука Вкуса | D22: =SUMIFS('Адресная программа'!$O$388:$O$4169,'Адресная программа'!$C$388:$C$4169,'Азбука вкуса'!B22,'Адресная программа'!$G$388:$G$4169,'Азбука вкуса'!C22) | E22: =F22/$K$7/D22 | F22: =SUMIFS('Адресная программа'!$T$20:$T$4940,'Адресная программа'!$C$20:$C$4940,'Азбука вкуса'!B22,'Адресная программа'!$G$20:$G$4940,'Азбука вкуса'!C22,'Адресная программа'!$N$20:$N$4940,1)*$K$7*60/$K$5*$K$9*'Цены|Скидки'!D11/15/480 | G22: =IF(D22=SUMIFS('Адресная программа'!$K$20:$K$4940,'Адресная программа'!$G$20:$G$4940,'Азбука вкуса'!C22,'Адресная программа'!$C$20:$C$4940,'Азбука вкуса'!B22,'Адресная программа'!$L$20:$L$4940,1),'Цены|Скидки'!$C$31,IF(D22>(SUMIFS('Адресная программа'!$K$20:$K$4940,'Адресная программа'!$G$20:$G$4940,'Азбука вкуса'!C22,'Адресная программа'!$C$20:$C$4940,'Азбука вкуса'!B22,'Адресная программа'!$L$20:$L$4940,1)*'Цены|Скидки'!$B$32-1),'Цены|Скидки'!$C$32,IF(D22>(SUMIFS('Адресная программа'!$K$20:$K$4940,'Адресная программа'!$G$20:$G$4940,'Азбука вкуса'!C22,'Адресная программа'!$C$20:$C$4940,'Азбука вкуса'!B22,'Адресная программа'!$L$20:$L$4940,1)*'Цены|Скидки'!$B$33-1),'Цены|Скидки'!$C$33,IF(D22>(SUMIFS('Адресная программа'!$K$20:$K$4940,'Адресная программа'!$G$20:$G$4940,'Азбука вкуса'!C22,'Адресная программа'!$C$20:$C$4940,'Азбука вкуса'!B22,'Адресная программа'!$L$20:$L$4940,1)*'Цены|Скидки'!$B$34-1),'Цены|Скидки'!$C$34,IF(D22>(SUMIFS('Адресная программа'!$K$20:$K$4940,'Адресная программа'!$G$20:$G$4940,'Азбука вкуса'!C22,'Адресная программа'!$C$20:$C$4940,'Азбука вкуса'!B22,'Адресная программа'!$L$20:$L$4940,1)*'Цены|Скидки'!$B$35-1),'Цены|Скидки'!$C$35,IF(D22>(SUMIFS('Адресная программа'!$K$20:$K$4940,'Адресная программа'!$G$20:$G$4940,'Азбука вкуса'!C22,'Адресная программа'!$C$20:$C$4940,'Азбука вкуса'!B22,'Адресная программа'!$L$20:$L$4940,1)*'Цены|Скидки'!$B$36-1),'Цены|Скидки'!$C$36,0%)))))) | H22: =$D$12 | I22: =IF(F22=0,0,1-J22/F22) | J22: =F22*(1-G22)*(1-H22)*(1-IF(AC$2="РА",AD$2,0))*(1-IF(OR(AC$3="Доп скидка",AC$3="Сезонная скидка",AC$3="Welcome скидка")=TRUE,AD$3,0)) | K22: =J22+L22 | L22: =J22*0.2 | M22: =D22*K$7*1000 | N22: =J22/M22*1000
B23: Москва | C23: Энотека АВ | D23: =SUMIFS('Адресная программа'!$O$388:$O$4169,'Адресная программа'!$C$388:$C$4169,'Азбука вкуса'!B23,'Адресная программа'!$G$388:$G$4169,'Азбука вкуса'!C23) | E23: =F23/$K$7/D23 | F23: =SUMIFS('Адресная программа'!$T$20:$T$4940,'Адресная программа'!$C$20:$C$4940,'Азбука вкуса'!B23,'Адресная программа'!$G$20:$G$4940,'Азбука вкуса'!C23,'Адресная программа'!$N$20:$N$4940,1)*$K$7*60/$K$5*$K$9*'Цены|Скидки'!D11/15/480 | G23: =IF(D23=SUMIFS('Адресная программа'!$K$20:$K$4940,'Адресная программа'!$G$20:$G$4940,'Азбука вкуса'!C23,'Адресная программа'!$C$20:$C$4940,'Азбука вкуса'!B23,'Адресная программа'!$L$20:$L$4940,1),'Цены|Скидки'!$C$31,IF(D23>(SUMIFS('Адресная программа'!$K$20:$K$4940,'Адресная программа'!$G$20:$G$4940,'Азбука вкуса'!C23,'Адресная программа'!$C$20:$C$4940,'Азбука вкуса'!B23,'Адресная программа'!$L$20:$L$4940,1)*'Цены|Скидки'!$B$32-1),'Цены|Скидки'!$C$32,IF(D23>(SUMIFS('Адресная программа'!$K$20:$K$4940,'Адресная программа'!$G$20:$G$4940,'Азбука вкуса'!C23,'Адресная программа'!$C$20:$C$4940,'Азбука вкуса'!B23,'Адресная программа'!$L$20:$L$4940,1)*'Цены|Скидки'!$B$33-1),'Цены|Скидки'!$C$33,IF(D23>(SUMIFS('Адресная программа'!$K$20:$K$4940,'Адресная программа'!$G$20:$G$4940,'Азбука вкуса'!C23,'Адресная программа'!$C$20:$C$4940,'Азбука вкуса'!B23,'Адресная программа'!$L$20:$L$4940,1)*'Цены|Скидки'!$B$34-1),'Цены|Скидки'!$C$34,IF(D23>(SUMIFS('Адресная программа'!$K$20:$K$4940,'Адресная программа'!$G$20:$G$4940,'Азбука вкуса'!C23,'Адресная программа'!$C$20:$C$4940,'Азбука вкуса'!B23,'Адресная программа'!$L$20:$L$4940,1)*'Цены|Скидки'!$B$35-1),'Цены|Скидки'!$C$35,IF(D23>(SUMIFS('Адресная программа'!$K$20:$K$4940,'Адресная программа'!$G$20:$G$4940,'Азбука вкуса'!C23,'Адресная программа'!$C$20:$C$4940,'Азбука вкуса'!B23,'Адресная программа'!$L$20:$L$4940,1)*'Цены|Скидки'!$B$36-1),'Цены|Скидки'!$C$36,0%)))))) | H23: =$D$12 | I23: =IF(F23=0,0,1-J23/F23) | J23: =F23*(1-G23)*(1-H23)*(1-IF(AC$2="РА",AD$2,0))*(1-IF(OR(AC$3="Доп скидка",AC$3="Сезонная скидка",AC$3="Welcome скидка")=TRUE,AD$3,0)) | K23: =J23+L23 | L23: =J23*0.2 | M23: =D23*K$7*1000 | N23: =J23/M23*1000
B24: Санкт-Петербург | C24: Азбука Вкуса | D24: =SUMIFS('Адресная программа'!$O$388:$O$4169,'Адресная программа'!$C$388:$C$4169,'Азбука вкуса'!B24,'Адресная программа'!$G$388:$G$4169,'Азбука вкуса'!C24) | E24: =F24/$K$7/D24 | F24: =SUMIFS('Адресная программа'!$T$20:$T$4940,'Адресная программа'!$C$20:$C$4940,'Азбука вкуса'!B24,'Адресная программа'!$G$20:$G$4940,'Азбука вкуса'!C24,'Адресная программа'!$N$20:$N$4940,1)*$K$7*60/$K$5*$K$9*'Цены|Скидки'!E11/15/480 | I24: =IF(F24=0,0,1-J24/F24) | J24: =F24*(1-G24)*(1-H24)*(1-IF(AC$2="РА",AD$2,0))*(1-IF(OR(AC$3="Доп скидка",AC$3="Сезонная скидка",AC$3="Welcome скидка")=TRUE,AD$3,0)) | K24: =J24+L24 | L24: =J24*0.2 | M24: =D24*K$7*1000 | N24: =J24/M24*1000
B25: Санкт-Петербург | C25: Энотека АВ | D25: =SUMIFS('Адресная программа'!$O$388:$O$4169,'Адресная программа'!$C$388:$C$4169,'Азбука вкуса'!B25,'Адресная программа'!$G$388:$G$4169,'Азбука вкуса'!C25) | E25: =F25/$K$7/D25 | F25: =SUMIFS('Адресная программа'!$T$20:$T$4940,'Адресная программа'!$C$20:$C$4940,'Азбука вкуса'!B25,'Адресная программа'!$G$20:$G$4940,'Азбука вкуса'!C25,'Адресная программа'!$N$20:$N$4940,1)*$K$7*60/$K$5*$K$9*'Цены|Скидки'!E11/15/480 | I25: =IF(F25=0,0,1-J25/F25) | J25: =F25*(1-G25)*(1-H25)*(1-IF(AC$2="РА",AD$2,0))*(1-IF(OR(AC$3="Доп скидка",AC$3="Сезонная скидка",AC$3="Welcome скидка")=TRUE,AD$3,0)) | K25: =J25+L25 | L25: =J25*0.2 | M25: =D25*K$7*1000 | N25: =J25/M25*1000
D26: =SUM(D22:D25) | F26: =SUM(F22:F25) | J26: =SUM(J22:J25) | K26: =SUM(K22:K25) | L26: =SUM(L22:L25) | M26: =SUM(M22:M25) | N26: =J26/M26*1000

Sheet MetroCC
B2: Торговые центры Metro C&C | AB2: НЕ Поставщик | AD2: 0.15 | AI2: ПК | AJ2: 0 | AK2: НЕ Поставщик | AM2: Применяемые скидки (последовательно)
B3: Клиент: | G3: Всего ТЦ: | I3: =C40 | AD3: 0 | AI3: РА | AJ3: 0.05 | AK3: Поставщик | AL3: Доп скидка | AM3: За кол-во экранов(средн): | AO3: =IF(SUM($C$22:$C$38)=SUMIFS('Адресная программа'!$L$20:$L$4931,'Адресная программа'!$G$20:$G$4931,"Metro C&C",'Адресная программа'!$L$20:$L$4931,1),'Цены|Скидки'!C93,IF(SUM($C$22:$C$38)>(SUMIFS('Адресная программа'!$L$20:$L$4931,'Адресная программа'!$G$20:$G$4931,"Metro C&C",'Адресная программа'!$L$20:$L$4931,1)*'Цены|Скидки'!B94-1),'Цены|Скидки'!C94,IF(SUM($C$22:$C$38)>(SUMIFS('Адресная программа'!$L$20:$L$4931,'Адресная программа'!$G$20:$G$4931,"Metro C&C",'Адресная программа'!$L$20:$L$4931,1)*'Цены|Скидки'!B95-1),'Цены|Скидки'!C95,IF(SUM($C$22:$C$38)>(SUMIFS('Адресная программа'!$L$20:$L$4931,'Адресная программа'!$G$20:$G$4931,"Metro C&C",'Адресная программа'!$L$20:$L$4931,1)*'Цены|Скидки'!B96-1),'Цены|Скидки'!C96,0))))
B4: Бренд: | G4: Всего экранов: | I4: =D40 | AJ4: 0.1 | AL4: Welcome скидка | AM4: За период: | AO4: =IF(I7>69,'Цены|Скидки'!$C$100,IF(I7>39,'Цены|Скидки'!$C$99,0%))
B5: Начало РК: | D5: =Общий!D5 | G5: Продолжительность блока в минутах: | I5: 3 | AJ5: 0.15 | AL5: Сезонная скидка | AM5: Итоговая скидка: | AO5: =IF(SUM($C$22:$C$38)=0,0,1-SUM($G$22:$G$38)/SUM($F$22:$F$38))
B6: Окончание РК: | D6: =Общий!D6 | G6: Блоков в сутки на одном экране: | I6: =17*60/I5 | AJ6: 0.2
B7: Ролик1, сек: | D7: =Общий!D7 | G7: Кол-во дней размещения: | I7: =D6-D5+1 | AJ7: 0.25
B8: Ролик2, сек: | G8: Кол-во роликов в блоке: | I8: =COUNT(D$7,D$8)
B9: =IF(AB2=AK2,AM2,IF(AC2=AI3,AM2,"")) | G9: Итого секунд в блоке: | I9: =SUM(D7:D8) | AJ9: 0
B10: =IF(AB2=AK2,AM3,"") | D10: =IF(AB2=AK2,AO3,"") | G10: Показов в день на одном экране: | I10: =I6*I8 | AJ10: 0.05
B11: =IF(AB2=AK2,AM4,"") | D11: =IF(AB2=AK2,AO4,"") | G11: Минут в день на одном экране: | I11: =I6*I9/60 | AJ11: 0.1
B12: =IF(AC2="РА","Скидка для РА:"," ") | D12: =IF(AC2="РА",AD2," ") | AJ12: 0.15
B13: =IF(AC3=0," ",AC3) | D13: =IF(OR(AC3="Доп скидка",AC3="Сезонная скидка",AC3="Welcome скидка")=TRUE,AD3," ") | H13: OTS: | I13: =J40 | AJ13: 0.2
B14: =IF(AB2=AK2,AM5,IF(AC2=AI3,AM5,"")) | D14: =IF(AB2=AK2,AO5,IF(AC2=AI3,AO5,"")) | G14: Показов на всех экранах за период: | I14: =I10*I7*I4 | AJ14: 0.25
B15: Стоимость размещения
B16: Всего, руб. NET: | D16: =G40 | G16: Предоставление ролика до: | I16: =D5-3
B17: Всего, руб. GROSS: | D17: =H40 | G17: Оплата до: | I17: =D5-5
AI18: Автобренд
B19: Расчет стоимости кампании
B21: Регион | C21: Количество магазинов | D21: Количество экранов | E21: Стоимость размещения в сутки в одном ТЦ, без НДС | F21: Стоимость размещения по выбранной АП за период, без НДС | G21: Стоимость c учетом всех скидок, без НДС | H21: Стоимость c учетом всех скидок, вкл. НДС | I21: Сумма НДС (20%) | J21: OTS | K21: CPT*
B22: Москва | C22: =COUNTIFS('Адресная программа'!$V$20:$V$4169,B22,'Адресная программа'!$G$20:$G$4169,"Metro C&C") | D22: =SUMIFS('Адресная программа'!$O$20:$O$4169,'Адресная программа'!$V$20:$V$4169,B22,'Адресная программа'!$G$20:$G$4169,"Metro C&C") | E22: =IF(C22=0,0,AVERAGEIFS('Адресная программа'!$T$20:$T$4169,'Адресная программа'!$V$20:$V$4169,B22,'Адресная программа'!$G$20:$G$4169,"Metro C&C"))/15*$I$9 | F22: =E22*$I$7*C22 | G22: =IF($D$10="",IF($AC$2="РА",F22*(1-$AD$2),F22),F22*(1-$AO$3)*(1-$AO$4)*(1-IF($AC$2="РА",$AD$2,0))*(1-IF(OR($AC$3="Доп скидка",$AC$3="Сезонная скидка",$AC$3="Welcome скидка")=TRUE,$AD$3,0))) | H22: =G22+I22 | I22: =G22*0.2 | J22: =SUMIFS('Адресная программа'!$U$3366:$U$4209,'Адресная программа'!$V$3366:$V$4209,B22,'Адресная программа'!$G$3366:$G$4209,"Metro C&C")/30*$I$7 | K22: =IF(J22=0,0,(G22/J22*1000)/$D$7*10)
B23: Санкт-Петербург | C23: =COUNTIFS('Адресная программа'!$V$20:$V$4169,B23,'Адресная программа'!$G$20:$G$4169,"Metro C&C") | D23: =SUMIFS('Адресная программа'!$O$20:$O$4169,'Адресная программа'!$V$20:$V$4169,B23,'Адресная программа'!$G$20:$G$4169,"Metro C&C") | E23: =IF(C23=0,0,AVERAGEIFS('Адресная программа'!$T$20:$T$4169,'Адресная программа'!$V$20:$V$4169,B23,'Адресная программа'!$G$20:$G$4169,"Metro C&C"))/15*$I$9 | F23: =E23*$I$7*C23 | G23: =IF($D$10="",IF($AC$2="РА",F23*(1-$AD$2),F23),F23*(1-$AO$3)*(1-$AO$4)*(1-IF($AC$2="РА",$AD$2,0))*(1-IF(OR($AC$3="Доп скидка",$AC$3="Сезонная скидка",$AC$3="Welcome скидка")=TRUE,$AD$3,0))) | H23: =G23+I23 | I23: =G23*0.2 | J23: =SUMIFS('Адресная программа'!$U$3366:$U$4209,'Адресная программа'!$V$3366:$V$4209,B23,'Адресная программа'!$G$3366:$G$4209,"Metro C&C")/30*$I$7 | K23: =IF(J23=0,0,(G23/J23*1000)/$D$7*10)
B24: Волгоград | C24: =COUNTIFS('Адресная программа'!$V$20:$V$4169,B24,'Адресная программа'!$G$20:$G$4169,"Metro C&C") | D24: =SUMIFS('Адресная программа'!$O$20:$O$4169,'Адресная программа'!$V$20:$V$4169,B24,'Адресная программа'!$G$20:$G$4169,"Metro C&C") | E24: =IF(C24=0,0,AVERAGEIFS('Адресная программа'!$T$20:$T$4169,'Адресная программа'!$V$20:$V$4169,B24,'Адресная программа'!$G$20:$G$4169,"Metro C&C"))/15*$I$9 | F24: =E24*$I$7*C24 | G24: =IF($D$10="",IF($AC$2="РА",F24*(1-$AD$2),F24),F24*(1-$AO$3)*(1-$AO$4)*(1-IF($AC$2="РА",$AD$2,0))*(1-IF(OR($AC$3="Доп скидка",$AC$3="Сезонная скидка",$AC$3="Welcome скидка")=TRUE,$AD$3,0))) | H24: =G24+I24 | I24: =G24*0.2 | J24: =SUMIFS('Адресная программа'!$U$3366:$U$4209,'Адресная программа'!$V$3366:$V$4209,B24,'Адресная программа'!$G$3366:$G$4209,"Metro C&C")/30*$I$7 | K24: =IF(J24=0,0,(G24/J24*1000)/$D$7*10)
B25: Воронеж | C25: =COUNTIFS('Адресная программа'!$V$20:$V$4169,B25,'Адресная программа'!$G$20:$G$4169,"Metro C&C") | D25: =SUMIFS('Адресная программа'!$O$20:$O$4169,'Адресная программа'!$V$20:$V$4169,B25,'Адресная программа'!$G$20:$G$4169,"Metro C&C") | E25: =IF(C25=0,0,AVERAGEIFS('Адресная программа'!$T$20:$T$4169,'Адресная программа'!$V$20:$V$4169,B25,'Адресная программа'!$G$20:$G$4169,"Metro C&C"))/15*$I$9 | F25: =E25*$I$7*C25 | G25: =IF($D$10="",IF($AC$2="РА",F25*(1-$AD$2),F25),F25*(1-$AO$3)*(1-$AO$4)*(1-IF($AC$2="РА",$AD$2,0))*(1-IF(OR($AC$3="Доп скидка",$AC$3="Сезонная скидка",$AC$3="Welcome скидка")=TRUE,$AD$3,0))) | H25: =G25+I25 | I25: =G25*0.2 | J25: =SUMIFS('Адресная программа'!$U$3366:$U$4209,'Адресная программа'!$V$3366:$V$4209,B25,'Адресная программа'!$G$3366:$G$4209,"Metro C&C")/30*$I$7 | K25: =IF(J25=0,0,(G25/J25*1000)/$D$7*10)
B26: Екатеринбург | C26: =COUNTIFS('Адресная программа'!$V$20:$V$4169,B26,'Адресная программа'!$G$20:$G$4169,"Metro C&C") | D26: =SUMIFS('Адресная программа'!$O$20:$O$4169,'Адресная программа'!$V$20:$V$4169,B26,'Адресная программа'!$G$20:$G$4169,"Metro C&C") | E26: =IF(C26=0,0,AVERAGEIFS('Адресная программа'!$T$20:$T$4169,'Адресная программа'!$V$20:$V$4169,B26,'Адресная программа'!$G$20:$G$4169,"Metro C&C"))/15*$I$9 | F26: =E26*$I$7*C26 | G26: =IF($D$10="",IF($AC$2="РА",F26*(1-$AD$2),F26),F26*(1-$AO$3)*(1-$AO$4)*(1-IF($AC$2="РА",$AD$2,0))*(1-IF(OR($AC$3="Доп скидка",$AC$3="Сезонная скидка",$AC$3="Welcome скидка")=TRUE,$AD$3,0))) | H26: =G26+I26 | I26: =G26*0.2 | J26: =SUMIFS('Адресная программа'!$U$3366:$U$4209,'Адресная программа'!$V$3366:$V$4209,B26,'Адресная программа'!$G$3366:$G$4209,"Metro C&C")/30*$I$7 | K26: =IF(J26=0,0,(G26/J26*1000)/$D$7*10)
B27: Татарстан | C27: =COUNTIFS('Адресная программа'!$V$20:$V$4169,B27,'Адресная программа'!$G$20:$G$4169,"Metro C&C") | D27: =SUMIFS('Адресная программа'!$O$20:$O$4169,'Адресная программа'!$V$20:$V$4169,B27,'Адресная программа'!$G$20:$G$4169,"Metro C&C") | E27: =IF(C27=0,0,AVERAGEIFS('Адресная программа'!$T$20:$T$4169,'Адресная программа'!$V$20:$V$4169,B27,'Адресная программа'!$G$20:$G$4169,"Metro C&C"))/15*$I$9 | F27: =E27*$I$7*C27 | G27: =IF($D$10="",IF($AC$2="РА",F27*(1-$AD$2),F27),F27*(1-$AO$3)*(1-$AO$4)*(1-IF($AC$2="РА",$AD$2,0))*(1-IF(OR($AC$3="Доп скидка",$AC$3="Сезонная скидка",$AC$3="Welcome скидка")=TRUE,$AD$3,0))) | H27: =G27+I27 | I27: =G27*0.2 | J27: =SUMIFS('Адресная программа'!$U$3366:$U$4209,'Адресная программа'!$V$3366:$V$4209,B27,'Адресная программа'!$G$3366:$G$4209,"Metro C&C")/30*$I$7 | K27: =IF(J27=0,0,(G27/J27*1000)/$D$7*10)
B28: Краснодар | C28: =COUNTIFS('Адресная программа'!$V$20:$V$4169,B28,'Адресная программа'!$G$20:$G$4169,"Metro C&C") | D28: =SUMIFS('Адресная программа'!$O$20:$O$4169,'Адресная программа'!$V$20:$V$4169,B28,'Адресная программа'!$G$20:$G$4169,"Metro C&C") | E28: =IF(C28=0,0,AVERAGEIFS('Адресная программа'!$T$20:$T$4169,'Адресная программа'!$V$20:$V$4169,B28,'Адресная программа'!$G$20:$G$4169,"Metro C&C"))/15*$I$9 | F28: =E28*$I$7*C28 | G28: =IF($D$10="",IF($AC$2="РА",F28*(1-$AD$2),F28),F28*(1-$AO$3)*(1-$AO$4)*(1-IF($AC$2="РА",$AD$2,0))*(1-IF(OR($AC$3="Доп скидка",$AC$3="Сезонная скидка",$AC$3="Welcome скидка")=TRUE,$AD$3,0))) | H28: =G28+I28 | I28: =G28*0.2 | J28: =SUMIFS('Адресная программа'!$U$3366:$U$4209,'Адресная программа'!$V$3366:$V$4209,B28,'Адресная программа'!$G$3366:$G$4209,"Metro C&C")/30*$I$7 | K28: =IF(J28=0,0,(G28/J28*1000)/$D$7*10)
B29: Красноярск | C29: =COUNTIFS('Адресная программа'!$V$20:$V$4169,B29,'Адресная программа'!$G$20:$G$4169,"Metro C&C") | D29: =SUMIFS('Адресная программа'!$O$20:$O$4169,'Адресная программа'!$V$20:$V$4169,B29,'Адресная программа'!$G$20:$G$4169,"Metro C&C") | E29: =IF(C29=0,0,AVERAGEIFS('Адресная программа'!$T$20:$T$4169,'Адресная программа'!$V$20:$V$4169,B29,'Адресная программа'!$G$20:$G$4169,"Metro C&C"))/15*$I$9 | F29: =E29*$I$7*C29 | G29: =IF($D$10="",IF($AC$2="РА",F29*(1-$AD$2),F29),F29*(1-$AO$3)*(1-$AO$4)*(1-IF($AC$2="РА",$AD$2,0))*(1-IF(OR($AC$3="Доп скидка",$AC$3="Сезонная скидка",$AC$3="Welcome скидка")=TRUE,$AD$3,0))) | H29: =G29+I29 | I29: =G29*0.2 | J29: =SUMIFS('Адресная программа'!$U$3366:$U$4209,'Адресная программа'!$V$3366:$V$4209,B29,'Адресная программа'!$G$3366:$G$4209,"Metro C&C")/30*$I$7 | K29: =IF(J29=0,0,(G29/J29*1000)/$D$7*10)
B30: Нижний Новгород | C30: =COUNTIFS('Адресная программа'!$V$20:$V$4169,B30,'Адресная программа'!$G$20:$G$4169,"Metro C&C") | D30: =SUMIFS('Адресная программа'!$O$20:$O$4169,'Адресная программа'!$V$20:$V$4169,B30,'Адресная программа'!$G$20:$G$4169,"Metro C&C") | E30: =IF(C30=0,0,AVERAGEIFS('Адресная программа'!$T$20:$T$4169,'Адресная программа'!$V$20:$V$4169,B30,'Адресная программа'!$G$20:$G$4169,"Metro C&C"))/15*$I$9 | F30: =E30*$I$7*C30 | G30: =IF($D$10="",IF($AC$2="РА",F30*(1-$AD$2),F30),F30*(1-$AO$3)*(1-$AO$4)*(1-IF($AC$2="РА",$AD$2,0))*(1-IF(OR($AC$3="Доп скидка",$AC$3="Сезонная скидка",$AC$3="Welcome скидка")=TRUE,$AD$3,0))) | H30: =G30+I30 | I30: =G30*0.2 | J30: =SUMIFS('Адресная программа'!$U$3366:$U$4209,'Адресная программа'!$V$3366:$V$4209,B30,'Адресная программа'!$G$3366:$G$4209,"Metro C&C")/30*$I$7 | K30: =IF(J30=0,0,(G30/J30*1000)/$D$7*10)
B31: Новосибирск | C31: =COUNTIFS('Адресная программа'!$V$20:$V$4169,B31,'Адресная программа'!$G$20:$G$4169,"Metro C&C") | D31: =SUMIFS('Адресная программа'!$O$20:$O$4169,'Адресная программа'!$V$20:$V$4169,B31,'Адресная программа'!$G$20:$G$4169,"Metro C&C") | E31: =IF(C31=0,0,AVERAGEIFS('Адресная программа'!$T$20:$T$4169,'Адресная программа'!$V$20:$V$4169,B31,'Адресная программа'!$G$20:$G$4169,"Metro C&C"))/15*$I$9 | F31: =E31*$I$7*C31 | G31: =IF($D$10="",IF($AC$2="РА",F31*(1-$AD$2),F31),F31*(1-$AO$3)*(1-$AO$4)*(1-IF($AC$2="РА",$AD$2,0))*(1-IF(OR($AC$3="Доп скидка",$AC$3="Сезонная скидка",$AC$3="Welcome скидка")=TRUE,$AD$3,0))) | H31: =G31+I31 | I31: =G31*0.2 | J31: =SUMIFS('Адресная программа'!$U$3366:$U$4209,'Адресная программа'!$V$3366:$V$4209,B31,'Адресная программа'!$G$3366:$G$4209,"Metro C&C")/30*$I$7 | K31: =IF(J31=0,0,(G31/J31*1000)/$D$7*10)
B32: Омск | C32: =COUNTIFS('Адресная программа'!$V$20:$V$4169,B32,'Адресная программа'!$G$20:$G$4169,"Metro C&C") | D32: =SUMIFS('Адресная программа'!$O$20:$O$4169,'Адресная программа'!$V$20:$V$4169,B32,'Адресная программа'!$G$20:$G$4169,"Metro C&C") | E32: =IF(C32=0,0,AVERAGEIFS('Адресная программа'!$T$20:$T$4169,'Адресная программа'!$V$20:$V$4169,B32,'Адресная программа'!$G$20:$G$4169,"Metro C&C"))/15*$I$9 | F32: =E32*$I$7*C32 | G32: =IF($D$10="",IF($AC$2="РА",F32*(1-$AD$2),F32),F32*(1-$AO$3)*(1-$AO$4)*(1-IF($AC$2="РА",$AD$2,0))*(1-IF(OR($AC$3="Доп скидка",$AC$3="Сезонная скидка",$AC$3="Welcome скидка")=TRUE,$AD$3,0))) | H32: =G32+I32 | I32: =G32*0.2 | J32: =SUMIFS('Адресная программа'!$U$3366:$U$4209,'Адресная программа'!$V$3366:$V$4209,B32,'Адресная программа'!$G$3366:$G$4209,"Metro C&C")/30*$I$7 | K32: =IF(J32=0,0,(G32/J32*1000)/$D$7*10)
B33: Пермь | C33: =COUNTIFS('Адресная программа'!$V$20:$V$4169,B33,'Адресная программа'!$G$20:$G$4169,"Metro C&C") | D33: =SUMIFS('Адресная программа'!$O$20:$O$4169,'Адресная программа'!$V$20:$V$4169,B33,'Адресная программа'!$G$20:$G$4169,"Metro C&C") | E33: =IF(C33=0,0,AVERAGEIFS('Адресная программа'!$T$20:$T$4169,'Адресная программа'!$V$20:$V$4169,B33,'Адресная программа'!$G$20:$G$4169,"Metro C&C"))/15*$I$9 | F33: =E33*$I$7*C33 | G33: =IF($D$10="",IF($AC$2="РА",F33*(1-$AD$2),F33),F33*(1-$AO$3)*(1-$AO$4)*(1-IF($AC$2="РА",$AD$2,0))*(1-IF(OR($AC$3="Доп скидка",$AC$3="Сезонная скидка",$AC$3="Welcome скидка")=TRUE,$AD$3,0))) | H33: =G33+I33 | I33: =G33*0.2 | J33: =SUMIFS('Адресная программа'!$U$3366:$U$4209,'Адресная программа'!$V$3366:$V$4209,B33,'Адресная программа'!$G$3366:$G$4209,"Metro C&C")/30*$I$7 | K33: =IF(J33=0,0,(G33/J33*1000)/$D$7*10)
... B38: Челябинск | C38: =COUNTIFS('Адресная программа'!$V$20:$V$4169,B38,'Адресная программа'!$G$20:$G$4169,"Metro C&C") | D38: =SUMIFS('Адресная программа'!$O$20:$O$4169,'Адресная программа'!$V$20:$V$4169,B38,'Адресная программа'!$G$20:$G$4169,"Metro C&C") | E38: =IF(C38=0,0,AVERAGEIFS('Адресная программа'!$T$20:$T$4169,'Адресная программа'!$V$20:$V$4169,B38,'Адресная программа'!$G$20:$G$4169,"Metro C&C"))/15*$I$9 | F38: =E38*$I$7*C38 | G38: =IF($D$10="",IF($AC$2="РА",F38*(1-$AD$2),F38),F38*(1-$AO$3)*(1-$AO$4)*(1-IF($AC$2="РА",$AD$2,0))*(1-IF(OR($AC$3="Доп скидка",$AC$3="Сезонная скидка",$AC$3="Welcome скидка")=TRUE,$AD$3,0))) | H38: =G38+I38 | I38: =G38*0.2 | J38: =SUMIFS('Адресная программа'!$U$3366:$U$4209,'Адресная программа'!$V$3366:$V$4209,B38,'Адресная программа'!$G$3366:$G$4209,"Metro C&C")/30*$I$7 | K38: =IF(J38=0,0,(G38/J38*1000)/$D$7*10)
B40: Итого: | C40: =SUBTOTAL(9,C22:C38) | D40: =SUBTOTAL(9,D22:D38) | F40: =SUBTOTAL(9,F22:F38) | G40: =SUBTOTAL(9,G22:G38) | H40: =SUBTOTAL(9,H22:H38) | I40: =SUBTOTAL(9,I22:I38) | J40: =SUBTOTAL(9,J22:J38) | K40: =IF(J40=0,0,(G40/J40*1000)/$D$7*10)
B43: *CPT за 10 секундный ролик

Sheet Фитнес
B2: Сеть фитнес центров | AC2: РА | AD2: 0.1 | AN2: ПК | AO2: 0
B3: Клиент: | D3: Sminex | I3: Всего экранов: | K3: =D38 | AN3: РА | AO3: 0.05 | AP3: Доп скидка
B4: Бренд: | D4: Sminex | I4: Часов работы одного экрана в сутки: | K4: 16 | AO4: 0.1 | AP4: Welcome скидка
B5: Начало РК: | D5: 45748 | I5: Продолжительность блока в минутах: | K5: 2 | AO5: 0.15 | AP5: Сезонная скидка
B6: Окончание РК: | D6: 45838 | I6: Блоков в сутки на одном экране: | K6: =K4*60/K5 | AO6: 0.2
B7: Ролик1, сек: | D7: 15 | I7: Кол-во дней размещения: | K7: =D6-D5+1 | AO7: 0.25
I8: Кол-во роликов в блоке: | K8: =COUNT(D$7,D$8,D$9)
I9: Итого секунд в блоке: | K9: =SUM(D7:D9)
B10: Применяемые скидки (последовательно) | I10: Показов в день на одном экране: | K10: =K6*K8 | AO10: 0
B11: За кол-во экранов(средн): | D11: =IF(SUMIFS('Адресная программа'!$O$20:$O$4940,'Адресная программа'!$F$20:$F$4940,"Фитнес",'Адресная программа'!$L$20:$L$4940,1)>=SUMIFS('Адресная программа'!$K$20:$K$4940,'Адресная программа'!$F$20:$F$4940,"Фитнес",'Адресная программа'!$L$20:$L$4940,1),'Цены|Скидки'!C52,IF(SUMIFS('Адресная программа'!$O$20:$O$4940,'Адресная программа'!$F$20:$F$4940,"Фитнес",'Адресная программа'!$L$20:$L$4940,1)>(SUMIFS('Адресная программа'!$K$20:$K$4940,'Адресная программа'!$F$20:$F$4940,"Фитнес",'Адресная программа'!$L$20:$L$4940,1)*'Цены|Скидки'!B53-1),'Цены|Скидки'!C53,IF(SUMIFS('Адресная программа'!$O$20:$O$4940,'Адресная программа'!$F$20:$F$4940,"Фитнес",'Адресная программа'!$L$20:$L$4940,1)>(SUMIFS('Адресная программа'!$K$20:$K$4940,'Адресная программа'!$F$20:$F$4940,"Фитнес",'Адресная программа'!$L$20:$L$4940,1)*'Цены|Скидки'!B54-1),'Цены|Скидки'!C54,IF(SUMIFS('Адресная программа'!$O$20:$O$4940,'Адресная программа'!$F$20:$F$4940,"Фитнес",'Адресная программа'!$L$20:$L$4940,1)>(SUMIFS('Адресная программа'!$K$20:$K$4940,'Адресная программа'!$F$20:$F$4940,"Фитнес",'Адресная программа'!$L$20:$L$4940,1)*'Цены|Скидки'!B55-1),'Цены|Скидки'!C55,0%)))) | I11: Минут в день на одном экране: | K11: =K6*K9/60 | AO11: 0.05
B12: За период: | D12: =IF(K7>69,'Цены|Скидки'!$C$100,IF(K7>39,'Цены|Скидки'!$C$99,0%)) | I12: Показов на всех экранах за период: | K12: =K10*K7*K3 | AO12: 0.1
B13: =IF(AC2="РА","Скидка для РА:"," ") | D13: =IF(AC2="РА",AD2," ") | I13: OTS: | K13: =M38 | AO13: 0.15
B14: =IF(AC3=0," ",AC3) | D14: =IF(OR(AC3="Доп скидка",AC3="Сезонная скидка",AC3="Welcome скидка")=TRUE,AD3," ") | I14: CPT: | K14: =N38 | AO14: 0.2
B15: Стоимость размещения | AO15: 0.25
B16: Всего, руб. NET: | D16: =J38 | I16: Предоставление ролика до: | K16: =D5-3
B17: Всего, руб. GROSS: | D17: =K38 | I17: Оплата до: | K17: =D5-5
AN18: Автобренд
B20: Расчет стоимости кампании в фитнес центрах
B21: Регион | C21: Сеть | D21: Количество экранов | E21: Стоимость размещения в сутки на 1 экране, без НДС | F21: Стоимость размещения по выбранной АП за период, без НДС | G21: Скидка за кол-во экранов | H21: Скидка за период | I21: Итоговая скидка | J21: Стоимость c учетом всех скидок, без НДС | K21: Стоимость c учетом всех скидок, вкл. НДС | L21: Сумма НДС (20%) | M21: OTS | N21: CPT
B22: Москва | C22: World Class | D22: =SUMIFS('Адресная программа'!$O$20:$O$4021,'Адресная программа'!$G$20:$G$4021,C22,'Адресная программа'!$C$20:$C$4021,B22) | E22: =IF(D22=0,0,AVERAGEIFS('Адресная программа'!$S$20:$S$4028,'Адресная программа'!$C$20:$C$4028,Фитнес!B22,'Адресная программа'!$N$20:$N$4028,1,'Адресная программа'!$G$20:$G$4028,Фитнес!C22))/15*$K$9 | F22: =SUMIFS('Адресная программа'!$T$20:$T$4028,'Адресная программа'!$G$20:$G$4028,Фитнес!C22,'Адресная программа'!$C$20:$C$4028,Фитнес!B22)*$K$7/15*$K$9 | G22: =$D$11 | H22: =D$12 | I22: =IF(D22=0,0,1-J22/F22) | J22: =F22*(1-G22)*(1-H22)*(1-IF($AC$2="РА",$AD$2,0))*(1-IF(OR($AC$3="Доп скидка",$AC$3="Сезонная скидка",$AC$3="Welcome скидка")=TRUE,$AD$3,0)) | K22: =J22+L22 | L22: =J22*0.2 | M22: =(SUMIFS('Адресная программа'!$H$20:$H$4028,'Адресная программа'!$G$20:$G$4028,Фитнес!C22,'Адресная программа'!$C$20:$C$4028,Фитнес!B22,'Адресная программа'!$N$20:$N$4028,1)/31*$K$7) | N22: =IF(M22=0,0,J22/M22*1000)
B23: Санкт-Петербург | C23: World Class | D23: =SUMIFS('Адресная программа'!$O$20:$O$4021,'Адресная программа'!$G$20:$G$4021,C23,'Адресная программа'!$C$20:$C$4021,B23) | E23: =IF(D23=0,0,AVERAGEIFS('Адресная программа'!$S$20:$S$4028,'Адресная программа'!$C$20:$C$4028,Фитнес!B23,'Адресная программа'!$N$20:$N$4028,1,'Адресная программа'!$G$20:$G$4028,Фитнес!C23))/15*$K$9 | F23: =SUMIFS('Адресная программа'!$T$20:$T$4028,'Адресная программа'!$G$20:$G$4028,Фитнес!C23,'Адресная программа'!$C$20:$C$4028,Фитнес!B23)*$K$7/15*$K$9 | G23: =$D$11 | H23: =D$12 | I23: =IF(D23=0,0,1-J23/F23) | J23: =F23*(1-G23)*(1-H23)*(1-IF($AC$2="РА",$AD$2,0))*(1-IF(OR($AC$3="Доп скидка",$AC$3="Сезонная скидка",$AC$3="Welcome скидка")=TRUE,$AD$3,0)) | K23: =J23+L23 | L23: =J23*0.2 | M23: =(SUMIFS('Адресная программа'!$H$20:$H$4028,'Адресная программа'!$G$20:$G$4028,Фитнес!C23,'Адресная программа'!$C$20:$C$4028,Фитнес!B23,'Адресная программа'!$N$20:$N$4028,1)/31*$K$7) | N23: =IF(M23=0,0,J23/M23*1000)
B24: Уфа | C24: World Class | D24: =SUMIFS('Адресная программа'!$O$20:$O$4021,'Адресная программа'!$G$20:$G$4021,C24,'Адресная программа'!$C$20:$C$4021,B24) | E24: =IF(D24=0,0,AVERAGEIFS('Адресная программа'!$S$20:$S$4028,'Адресная программа'!$C$20:$C$4028,Фитнес!B24,'Адресная программа'!$N$20:$N$4028,1,'Адресная программа'!$G$20:$G$4028,Фитнес!C24))/15*$K$9 | F24: =SUMIFS('Адресная программа'!$T$20:$T$4028,'Адресная программа'!$G$20:$G$4028,Фитнес!C24,'Адресная программа'!$C$20:$C$4028,Фитнес!B24)*$K$7/15*$K$9 | G24: =$D$11 | H24: =D$12 | I24: =IF(D24=0,0,1-J24/F24) | J24: =F24*(1-G24)*(1-H24)*(1-IF($AC$2="РА",$AD$2,0))*(1-IF(OR($AC$3="Доп скидка",$AC$3="Сезонная скидка",$AC$3="Welcome скидка")=TRUE,$AD$3,0)) | K24: =J24+L24 | L24: =J24*0.2 | M24: =(SUMIFS('Адресная программа'!$H$20:$H$4028,'Адресная программа'!$G$20:$G$4028,Фитнес!C24,'Адресная программа'!$C$20:$C$4028,Фитнес!B24,'Адресная программа'!$N$20:$N$4028,1)/31*$K$7) | N24: =IF(M24=0,0,J24/M24*1000)
B25: Москва | C25: С.С.С.Р | D25: =SUMIFS('Адресная программа'!$O$20:$O$4021,'Адресная программа'!$G$20:$G$4021,C25,'Адресная программа'!$C$20:$C$4021,B25) | E25: =IF(D25=0,0,AVERAGEIFS('Адресная программа'!$S$20:$S$4028,'Адресная программа'!$C$20:$C$4028,Фитнес!B25,'Адресная программа'!$N$20:$N$4028,1,'Адресная программа'!$G$20:$G$4028,Фитнес!C25))/15*$K$9 | F25: =SUMIFS('Адресная программа'!$T$20:$T$4028,'Адресная программа'!$G$20:$G$4028,Фитнес!C25,'Адресная программа'!$C$20:$C$4028,Фитнес!B25)*$K$7/15*$K$9 | G25: =$D$11 | H25: =D$12 | I25: =IF(D25=0,0,1-J25/F25) | J25: =F25*(1-G25)*(1-H25)*(1-IF($AC$2="РА",$AD$2,0))*(1-IF(OR($AC$3="Доп скидка",$AC$3="Сезонная скидка",$AC$3="Welcome скидка")=TRUE,$AD$3,0)) | K25: =J25+L25 | L25: =J25*0.2 | M25: =(SUMIFS('Адресная программа'!$H$20:$H$4028,'Адресная программа'!$G$20:$G$4028,Фитнес!C25,'Адресная программа'!$C$20:$C$4028,Фитнес!B25,'Адресная программа'!$N$20:$N$4028,1)/31*$K$7) | N25: =IF(M25=0,0,J25/M25*1000)
B26: Москва | C26: Зебра | D26: =SUMIFS('Адресная программа'!$O$2938:$O$4021,'Адресная программа'!$G$2938:$G$4021,C26,'Адресная программа'!$C$2938:$C$4021,B26) | E26: =IF(D26=0,0,AVERAGEIFS('Адресная программа'!$S$2939:$S$3030,'Адресная программа'!$C$2939:$C$3030,Фитнес!B26,'Адресная программа'!$N$2939:$N$3030,1,'Адресная программа'!$G$2939:$G$3030,Фитнес!C26)) | F26: =SUMIFS('Адресная программа'!$T$2938:$T$3030,'Адресная программа'!$G$2938:$G$3030,Фитнес!C26,'Адресная программа'!$C$2938:$C$3030,Фитнес!B26)*$K$7/15*$K$9 | G26: =$D$11 | H26: =D$12 | I26: =IF(D26=0,0,1-J26/F26) | J26: =F26*(1-G26)*(1-H26)*(1-IF($AC$2="РА",$AD$2,0))*(1-IF(OR($AC$3="Доп скидка",$AC$3="Сезонная скидка",$AC$3="Welcome скидка")=TRUE,$AD$3,0)) | K26: =J26+L26 | L26: =J26*0.2 | M26: =(SUMIFS('Адресная программа'!$H$2938:$H$3030,'Адресная программа'!$G$2938:$G$3030,Фитнес!C26,'Адресная программа'!$C$2938:$C$3030,Фитнес!B26,'Адресная программа'!$N$2938:$N$3030,1)/31*$K$7) | N26: =IF(M26=0,0,J26/M26*1000)
B27: Москва | C27: Fit Остров | D27: =SUMIFS('Адресная программа'!$O$20:$O$4021,'Адресная программа'!$G$20:$G$4021,C27,'Адресная программа'!$C$20:$C$4021,B27) | E27: =IF(D27=0,0,AVERAGEIFS('Адресная программа'!$S$20:$S$4028,'Адресная программа'!$C$20:$C$4028,Фитнес!B27,'Адресная программа'!$N$20:$N$4028,1,'Адресная программа'!$G$20:$G$4028,Фитнес!C27))/15*$K$9 | F27: =SUMIFS('Адресная программа'!$T$20:$T$4028,'Адресная программа'!$G$20:$G$4028,Фитнес!C27,'Адресная программа'!$C$20:$C$4028,Фитнес!B27)*$K$7/15*$K$9 | G27: =$D$11 | H27: =D$12 | I27: =IF(D27=0,0,1-J27/F27) | J27: =F27*(1-G27)*(1-H27)*(1-IF($AC$2="РА",$AD$2,0))*(1-IF(OR($AC$3="Доп скидка",$AC$3="Сезонная скидка",$AC$3="Welcome скидка")=TRUE,$AD$3,0)) | K27: =J27+L27 | L27: =J27*0.2 | M27: =(SUMIFS('Адресная программа'!$H$20:$H$4028,'Адресная программа'!$G$20:$G$4028,Фитнес!C27,'Адресная программа'!$C$20:$C$4028,Фитнес!B27,'Адресная программа'!$N$20:$N$4028,1)/31*$K$7) | N27: =IF(M27=0,0,J27/M27*1000)
B28: Москва | C28: Спорт Квартал | D28: =SUMIFS('Адресная программа'!$O$2938:$O$4021,'Адресная программа'!$G$2938:$G$4021,C28,'Адресная программа'!$C$2938:$C$4021,B28) | E28: =IF(D28=0,0,AVERAGEIFS('Адресная программа'!$S$2939:$S$3030,'Адресная программа'!$C$2939:$C$3030,Фитнес!B28,'Адресная программа'!$N$2939:$N$3030,1,'Адресная программа'!$G$2939:$G$3030,Фитнес!C28)) | F28: =SUMIFS('Адресная программа'!$T$2938:$T$3030,'Адресная программа'!$G$2938:$G$3030,Фитнес!C28,'Адресная программа'!$C$2938:$C$3030,Фитнес!B28)*$K$7/15*$K$9 | G28: =$D$11 | H28: =D$12 | I28: =IF(D28=0,0,1-J28/F28) | J28: =F28*(1-G28)*(1-H28)*(1-IF($AC$2="РА",$AD$2,0))*(1-IF(OR($AC$3="Доп скидка",$AC$3="Сезонная скидка",$AC$3="Welcome скидка")=TRUE,$AD$3,0)) | K28: =J28+L28 | L28: =J28*0.2 | M28: =(SUMIFS('Адресная программа'!$H$2938:$H$3030,'Адресная программа'!$G$2938:$G$3030,Фитнес!C28,'Адресная программа'!$C$2938:$C$3030,Фитнес!B28,'Адресная программа'!$N$2938:$N$3030,1)/31*$K$7) | N28: =IF(M28=0,0,J28/M28*1000)
B29: Москва | C29: Фитнес-центр | D29: =SUMIFS('Адресная программа'!$O$2938:$O$4021,'Адресная программа'!$G$2938:$G$4021,C29,'Адресная программа'!$C$2938:$C$4021,B29) | E29: =IF(D29=0,0,AVERAGEIFS('Адресная программа'!$S$2939:$S$3030,'Адресная программа'!$C$2939:$C$3030,Фитнес!B29,'Адресная программа'!$N$2939:$N$3030,1,'Адресная программа'!$G$2939:$G$3030,Фитнес!C29)) | F29: =SUMIFS('Адресная программа'!$T$2938:$T$3030,'Адресная программа'!$G$2938:$G$3030,Фитнес!C29,'Адресная программа'!$C$2938:$C$3030,Фитнес!B29)*$K$7/15*$K$9 | G29: =$D$11 | H29: =D$12 | I29: =IF(D29=0,0,1-J29/F29) | J29: =F29*(1-G29)*(1-H29)*(1-IF($AC$2="РА",$AD$2,0))*(1-IF(OR($AC$3="Доп скидка",$AC$3="Сезонная скидка",$AC$3="Welcome скидка")=TRUE,$AD$3,0)) | K29: =J29+L29 | L29: =J29*0.2 | M29: =(SUMIFS('Адресная программа'!$H$2938:$H$3030,'Адресная программа'!$G$2938:$G$3030,Фитнес!C29,'Адресная программа'!$C$2938:$C$3030,Фитнес!B29,'Адресная программа'!$N$2938:$N$3030,1)/31*$K$7) | N29: =IF(M29=0,0,J29/M29*1000)
B30: Москва | C30: FITNESS ONE | D30: =SUMIFS('Адресная программа'!$O$20:$O$4021,'Адресная программа'!$G$20:$G$4021,C30,'Адресная программа'!$C$20:$C$4021,B30) | E30: =IF(D30=0,0,AVERAGEIFS('Адресная программа'!$S$20:$S$4028,'Адресная программа'!$C$20:$C$4028,Фитнес!B30,'Адресная программа'!$N$20:$N$4028,1,'Адресная программа'!$G$20:$G$4028,Фитнес!C30))/15*$K$9 | F30: =SUMIFS('Адресная программа'!$T$20:$T$4028,'Адресная программа'!$G$20:$G$4028,Фитнес!C30,'Адресная программа'!$C$20:$C$4028,Фитнес!B30)*$K$7/15*$K$9 | G30: =$D$11 | H30: =D$12 | I30: =IF(D30=0,0,1-J30/F30) | J30: =F30*(1-G30)*(1-H30)*(1-IF($AC$2="РА",$AD$2,0))*(1-IF(OR($AC$3="Доп скидка",$AC$3="Сезонная скидка",$AC$3="Welcome скидка")=TRUE,$AD$3,0)) | K30: =J30+L30 | L30: =J30*0.2 | M30: =(SUMIFS('Адресная программа'!$H$20:$H$4028,'Адресная программа'!$G$20:$G$4028,Фитнес!C30,'Адресная программа'!$C$20:$C$4028,Фитнес!B30,'Адресная программа'!$N$20:$N$4028,1)/31*$K$7) | N30: =IF(M30=0,0,J30/M30*1000)
B31: Москва | C31: Republíka | D31: =SUMIFS('Адресная программа'!$O$2938:$O$4021,'Адресная программа'!$G$2938:$G$4021,C31,'Адресная программа'!$C$2938:$C$4021,B31) | E31: =IF(D31=0,0,AVERAGEIFS('Адресная программа'!$S$2939:$S$3030,'Адресная программа'!$C$2939:$C$3030,Фитнес!B31,'Адресная программа'!$N$2939:$N$3030,1,'Адресная программа'!$G$2939:$G$3030,Фитнес!C31)) | F31: =SUMIFS('Адресная программа'!$T$2938:$T$3030,'Адресная программа'!$G$2938:$G$3030,Фитнес!C31,'Адресная программа'!$C$2938:$C$3030,Фитнес!B31)*$K$7/15*$K$9 | G31: =$D$11 | H31: =D$12 | I31: =IF(D31=0,0,1-J31/F31) | J31: =F31*(1-G31)*(1-H31)*(1-IF($AC$2="РА",$AD$2,0))*(1-IF(OR($AC$3="Доп скидка",$AC$3="Сезонная скидка",$AC$3="Welcome скидка")=TRUE,$AD$3,0)) | K31: =J31+L31 | L31: =J31*0.2 | M31: =(SUMIFS('Адресная программа'!$H$2938:$H$3030,'Адресная программа'!$G$2938:$G$3030,Фитнес!C31,'Адресная программа'!$C$2938:$C$3030,Фитнес!B31,'Адресная программа'!$N$2938:$N$3030,1)/31*$K$7) | N31: =IF(M31=0,0,J31/M31*1000)
B32: Москва | C32: MOSFITNESS | D32: =SUMIFS('Адресная программа'!$O$2938:$O$4021,'Адресная программа'!$G$2938:$G$4021,C32,'Адресная программа'!$C$2938:$C$4021,B32) | E32: =IF(D32=0,0,AVERAGEIFS('Адресная программа'!$S$2939:$S$3030,'Адресная программа'!$C$2939:$C$3030,Фитнес!B32,'Адресная программа'!$N$2939:$N$3030,1,'Адресная программа'!$G$2939:$G$3030,Фитнес!C32)) | F32: =SUMIFS('Адресная программа'!$T$2938:$T$3030,'Адресная программа'!$G$2938:$G$3030,Фитнес!C32,'Адресная программа'!$C$2938:$C$3030,Фитнес!B32)*$K$7/15*$K$9 | G32: =$D$11 | H32: =D$12 | I32: =IF(D32=0,0,1-J32/F32) | J32: =F32*(1-G32)*(1-H32)*(1-IF($AC$2="РА",$AD$2,0))*(1-IF(OR($AC$3="Доп скидка",$AC$3="Сезонная скидка",$AC$3="Welcome скидка")=TRUE,$AD$3,0)) | K32: =J32+L32 | L32: =J32*0.2 | M32: =(SUMIFS('Адресная программа'!$H$2938:$H$3030,'Адресная программа'!$G$2938:$G$3030,Фитнес!C32,'Адресная программа'!$C$2938:$C$3030,Фитнес!B32,'Адресная программа'!$N$2938:$N$3030,1)/31*$K$7) | N32: =IF(M32=0,0,J32/M32*1000)
B33: Москва | C33: Ideal Fitness | D33: =SUMIFS('Адресная программа'!$O$20:$O$4021,'Адресная программа'!$G$20:$G$4021,C33,'Адресная программа'!$C$20:$C$4021,B33) | E33: =IF(D33=0,0,AVERAGEIFS('Адресная программа'!$S$20:$S$4028,'Адресная программа'!$C$20:$C$4028,Фитнес!B33,'Адресная программа'!$N$20:$N$4028,1,'Адресная программа'!$G$20:$G$4028,Фитнес!C33))/15*$K$9 | F33: =SUMIFS('Адресная программа'!$T$20:$T$4028,'Адресная программа'!$G$20:$G$4028,Фитнес!C33,'Адресная программа'!$C$20:$C$4028,Фитнес!B33)*$K$7/15*$K$9 | G33: =$D$11 | H33: =D$12 | I33: =IF(D33=0,0,1-J33/F33) | J33: =F33*(1-G33)*(1-H33)*(1-IF($AC$2="РА",$AD$2,0))*(1-IF(OR($AC$3="Доп скидка",$AC$3="Сезонная скидка",$AC$3="Welcome скидка")=TRUE,$AD$3,0)) | K33: =J33+L33 | L33: =J33*0.2 | M33: =(SUMIFS('Адресная программа'!$H$20:$H$4028,'Адресная программа'!$G$20:$G$4028,Фитнес!C33,'Адресная программа'!$C$20:$C$4028,Фитнес!B33,'Адресная программа'!$N$20:$N$4028,1)/31*$K$7) | N33: =IF(M33=0,0,J33/M33*1000)
B34: Москва | C34: CityFitness | D34: =SUMIFS('Адресная программа'!$O$2938:$O$4021,'Адресная программа'!$G$2938:$G$4021,C34,'Адресная программа'!$C$2938:$C$4021,B34) | E34: =IF(D34=0,0,AVERAGEIFS('Адресная программа'!$S$2939:$S$3030,'Адресная программа'!$C$2939:$C$3030,Фитнес!B34,'Адресная программа'!$N$2939:$N$3030,1,'Адресная программа'!$G$2939:$G$3030,Фитнес!C34)) | F34: =SUMIFS('Адресная программа'!$T$2938:$T$3030,'Адресная программа'!$G$2938:$G$3030,Фитнес!C34,'Адресная программа'!$C$2938:$C$3030,Фитнес!B34)*$K$7/15*$K$9 | G34: =$D$11 | H34: =D$12 | I34: =IF(D34=0,0,1-J34/F34) | J34: =F34*(1-G34)*(1-H34)*(1-IF($AC$2="РА",$AD$2,0))*(1-IF(OR($AC$3="Доп скидка",$AC$3="Сезонная скидка",$AC$3="Welcome скидка")=TRUE,$AD$3,0)) | K34: =J34+L34 | L34: =J34*0.2 | M34: =(SUMIFS('Адресная программа'!$H$2938:$H$3030,'Адресная программа'!$G$2938:$G$3030,Фитнес!C34,'Адресная программа'!$C$2938:$C$3030,Фитнес!B34,'Адресная программа'!$N$2938:$N$3030,1)/31*$K$7) | N34: =IF(M34=0,0,J34/M34*1000)
B35: Москва | C35: FIRST&ONLY | D35: =SUMIFS('Адресная программа'!$O$20:$O$4021,'Адресная программа'!$G$20:$G$4021,C35,'Адресная программа'!$C$20:$C$4021,B35) | E35: =IF(D35=0,0,AVERAGEIFS('Адресная программа'!$S$20:$S$4028,'Адресная программа'!$C$20:$C$4028,Фитнес!B35,'Адресная программа'!$N$20:$N$4028,1,'Адресная программа'!$G$20:$G$4028,Фитнес!C35))/15*$K$9 | F35: =SUMIFS('Адресная программа'!$T$20:$T$4028,'Адресная программа'!$G$20:$G$4028,Фитнес!C35,'Адресная программа'!$C$20:$C$4028,Фитнес!B35)*$K$7/15*$K$9 | G35: =$D$11 | H35: =D$12 | I35: =IF(D35=0,0,1-J35/F35) | J35: =F35*(1-G35)*(1-H35)*(1-IF($AC$2="РА",$AD$2,0))*(1-IF(OR($AC$3="Доп скидка",$AC$3="Сезонная скидка",$AC$3="Welcome скидка")=TRUE,$AD$3,0)) | K35: =J35+L35 | L35: =J35*0.2 | M35: =(SUMIFS('Адресная программа'!$H$20:$H$4028,'Адресная программа'!$G$20:$G$4028,Фитнес!C35,'Адресная программа'!$C$20:$C$4028,Фитнес!B35,'Адресная программа'!$N$20:$N$4028,1)/31*$K$7) | N35: =IF(M35=0,0,J35/M35*1000)
B36: Москва | C36: N-ERGO | D36: =SUMIFS('Адресная программа'!$O$2938:$O$4021,'Адресная программа'!$G$2938:$G$4021,C36,'Адресная программа'!$C$2938:$C$4021,B36) | E36: =IF(D36=0,0,AVERAGEIFS('Адресная программа'!$S$2939:$S$3030,'Адресная программа'!$C$2939:$C$3030,Фитнес!B36,'Адресная программа'!$N$2939:$N$3030,1,'Адресная программа'!$G$2939:$G$3030,Фитнес!C36)) | F36: =SUMIFS('Адресная программа'!$T$2938:$T$3030,'Адресная программа'!$G$2938:$G$3030,Фитнес!C36,'Адресная программа'!$C$2938:$C$3030,Фитнес!B36)*$K$7/15*$K$9 | G36: =$D$11 | H36: =D$12 | I36: =IF(D36=0,0,1-J36/F36) | J36: =F36*(1-G36)*(1-H36)*(1-IF($AC$2="РА",$AD$2,0))*(1-IF(OR($AC$3="Доп скидка",$AC$3="Сезонная скидка",$AC$3="Welcome скидка")=TRUE,$AD$3,0)) | K36: =J36+L36 | L36: =J36*0.2 | M36: =(SUMIFS('Адресная программа'!$H$2938:$H$3030,'Адресная программа'!$G$2938:$G$3030,Фитнес!C36,'Адресная программа'!$C$2938:$C$3030,Фитнес!B36,'Адресная программа'!$N$2938:$N$3030,1)/31*$K$7) | N36: =IF(M36=0,0,J36/M36*1000)
D38: =SUBTOTAL(9,D22:D36) | F38: =SUBTOTAL(9,F22:F36) | J38: =SUBTOTAL(9,J22:J36) | K38: =SUBTOTAL(9,K22:K36) | L38: =SUBTOTAL(9,L22:L36) | M38: =(SUMIFS('Адресная программа'!H2938:H3030,'Адресная программа'!N2938:N3030,"1"))/31*$K$7 | N38: =IF(M38=0,0,J38/M38*1000)

Sheet БЦ
AR1: Праздники
B2: Сеть бизнес центров | AN2: ПК | AO2: 0 | AR2: 45658
B3: Клиент: | I3: Всего экранов: | K3: =D25 | AN3: РА | AO3: 0.05 | AP3: Доп скидка | AR3: 45659
B4: Бренд: | I4: Часов работы одного экрана в сутки: | K4: 12 | AD4: 0.2 | AO4: 0.1 | AP4: Welcome скидка | AR4: 45660
B5: Начало РК: | D5: =Общий!D5 | I5: Продолжительность блока в минутах: | K5: 2 | AO5: 0.15 | AP5: Сезонная скидка | AR5: 45661
B6: Окончание РК: | D6: =Общий!D6 | I6: Блоков в сутки на одном экране: | K6: =K4*60/K5 | AO6: 0.2 | AR6: 45662
B7: Ролик1, сек: | D7: =Общий!D7 | I7: Кол-во рабочих дней размещения: | K7: =NETWORKDAYS.INTL(D5,D6,1,AR2:AR17) | AO7: 0.25 | AR7: 45663
B8: Ролик2, сек: | I8: Кол-во роликов в блоке: | K8: =COUNT(D$7,D$8,D$9) | AR8: 45664
D9: Карта | I9: Итого секунд в блоке: | K9: =SUM(D7:D9) | AR9: 45665
B10: Применяемые скидки (последовательно) | I10: Показов в день на одном экране: | K10: =K6*K8 | AO10: 0 | AR10: 45711
B11: За кол-во экранов(средн): | D11: =AVERAGE(G22:G23) | I11: Минут в день на одном экране: | K11: =K6*K9/60 | AO11: 0.05 | AR11: 45724
B12: За период: | D12: =IF(K7>69,'Цены|Скидки'!$C$100,IF(K7>39,'Цены|Скидки'!$C$99,0%)) | I12: Показов на всех экранах за период: | K12: =K10*K7*K3 | AO12: 0.1 | AR12: 45778
B13: =IF(AC2="РА","Скидка для РА:"," ") | D13: =IF(AC2="РА",AD2," ") | I13: OTS: | K13: =M25 | AO13: 0.15 | AR13: 45779
B14: =IF(AC3=0," ",AC3) | D14: =IF(OR(AC3="Доп скидка",AC3="Сезонная скидка",AC3="Welcome скидка")=TRUE,AD3," ") | I14: CPT: | K14: =N25 | AO14: 0.2 | AR14: 45786
B15: Стоимость размещения | AO15: 0.25 | AR15: 45820
B16: Всего, руб. NET: | D16: =J25 | I16: Предоставление ролика до: | K16: =D5-3 | AR16: 45821
B17: Всего, руб. GROSS: | D17: =K25 | I17: Оплата до: | K17: =D5-5 | AR17: 45965
AN18: Автобренд | AR18: 46022
B20: Расчет стоимости кампании в бизнес центрах
B21: Регион | C21: Сеть | D21: Количество экранов | E21: Стоимость размещения в сутки на 1 экране, без НДС | F21: Стоимость размещения по выбранной АП за период, без НДС | G21: Скидка за кол-во экранов | H21: Скидка за период | I21: Итоговая скидка | J21: Стоимость c учетом всех скидок, без НДС | K21: Стоимость c учетом всех скидок, вкл. НДС | L21: Сумма НДС (20%) | M21: OTS | N21: CPT
B22: Москва | C22: Бизнес центр | D22: =SUMIFS('Адресная программа'!$O$20:$O$4286,'Адресная программа'!$C$20:$C$4286,БЦ!B22,'Адресная программа'!G20:G4286,БЦ!C22) | E22: =IF(D22=0,0,AVERAGEIFS('Адресная программа'!$S$20:$S$4286,'Адресная программа'!$N$20:$N$4286,1,'Адресная программа'!$C$20:$C$4286,БЦ!B22,'Адресная программа'!$F$20:$F$4286,БЦ!C22))/15*D7 | F22: =SUMIFS('Адресная программа'!$T$20:$T$4286,'Адресная программа'!$G$20:$G$4286,БЦ!C22,'Адресная программа'!$C$20:$C$4286,БЦ!B22)*$K$7/15*$K$9 | G22: =IF(SUMIFS('Адресная программа'!$O$20:$O$4940,'Адресная программа'!$N$20:$N$4940,1,'Адресная программа'!$C$20:$C$4940,БЦ!B22,'Адресная программа'!$G$20:$G$4940,БЦ!C22)=SUMIFS('Адресная программа'!$K$20:$K$4940,'Адресная программа'!$L$20:$L$4940,1,'Адресная программа'!$C$20:$C$4940,БЦ!B22,'Адресная программа'!$G$20:$G$4940,БЦ!C22),'Цены|Скидки'!$C$52,IF(SUMIFS('Адресная программа'!$O$20:$O$4940,'Адресная программа'!$N$20:$N$4940,1,'Адресная программа'!$C$20:$C$4940,БЦ!B22,'Адресная программа'!$G$20:$G$4940,БЦ!C22)>(SUMIFS('Адресная программа'!$K$20:$K$4940,'Адресная программа'!$L$20:$L$4940,1,'Адресная программа'!$C$20:$C$4940,БЦ!B22,'Адресная программа'!$G$20:$G$4940,БЦ!C22)*'Цены|Скидки'!$B$53-1),'Цены|Скидки'!$C$53,IF(SUMIFS('Адресная программа'!$O$20:$O$4940,'Адресная программа'!$N$20:$N$4940,1,'Адресная программа'!$C$20:$C$4940,БЦ!B22,'Адресная программа'!$G$20:$G$4940,БЦ!C22)>(SUMIFS('Адресная программа'!$K$20:$K$4940,'Адресная программа'!$L$20:$L$4940,1,'Адресная программа'!$C$20:$C$4940,БЦ!B22,'Адресная программа'!$G$20:$G$4940,БЦ!C22)*'Цены|Скидки'!$B$54-1),'Цены|Скидки'!$C$54,IF(SUMIFS('Адресная программа'!$O$20:$O$4940,'Адресная программа'!$N$20:$N$4940,1,'Адресная программа'!$C$20:$C$4940,БЦ!B22,'Адресная программа'!$G$20:$G$4940,БЦ!C22)>(SUMIFS('Адресная программа'!$K$20:$K$4940,'Адресная программа'!$L$20:$L$4940,1,'Адресная программа'!$C$20:$C$4940,БЦ!B22,'Адресная программа'!$G$20:$G$4940,БЦ!C22)*'Цены|Скидки'!$B$55-1),'Цены|Скидки'!$C$55,0%)))) | H22: =D$12 | I22: =IF(D22=0,0,1-J22/F22) | J22: =F22*(1-G22)*(1-H22)*(1-IF($AC$2="РА",$AD$2,0))*(1-IF(OR($AC$3="Доп скидка",$AC$3="Сезонная скидка",$AC$3="Welcome скидка")=TRUE,$AD$3,0)) | K22: =J22+L22 | L22: =J22*$AD$4 | M22: =(SUMIFS('Адресная программа'!$H$20:$H$4288,'Адресная программа'!$G$20:$G$4288,БЦ!C22,'Адресная программа'!$C$20:$C$4288,БЦ!B22,'Адресная программа'!N20:N4288,1)*$K$7) | N22: =IF(M22=0,0,J22/M22*1000)
B23: Санкт-Петербург | C23: Бизнес центр | D23: =SUMIFS('Адресная программа'!$O$20:$O$4286,'Адресная программа'!$C$20:$C$4286,БЦ!B23,'Адресная программа'!G20:G4286,БЦ!C23) | E23: =IF(D23=0,0,AVERAGEIFS('Адресная программа'!$S$20:$S$4286,'Адресная программа'!$N$20:$N$4286,1,'Адресная программа'!$C$20:$C$4286,БЦ!B23,'Адресная программа'!$F$20:$F$4286,БЦ!C23))/15*D7 | F23: =SUMIFS('Адресная программа'!$T$20:$T$4286,'Адресная программа'!$G$20:$G$4286,БЦ!C23,'Адресная программа'!$C$20:$C$4286,БЦ!B23)*$K$7/15*$K$9 | G23: =IF(SUMIFS('Адресная программа'!$O$20:$O$4940,'Адресная программа'!$N$20:$N$4940,1,'Адресная программа'!$C$20:$C$4940,БЦ!B23,'Адресная программа'!$G$20:$G$4940,БЦ!C23)=SUMIFS('Адресная программа'!$K$20:$K$4940,'Адресная программа'!$L$20:$L$4940,1,'Адресная программа'!$C$20:$C$4940,БЦ!B23,'Адресная программа'!$G$20:$G$4940,БЦ!C23),'Цены|Скидки'!$C$52,IF(SUMIFS('Адресная программа'!$O$20:$O$4940,'Адресная программа'!$N$20:$N$4940,1,'Адресная программа'!$C$20:$C$4940,БЦ!B23,'Адресная программа'!$G$20:$G$4940,БЦ!C23)>(SUMIFS('Адресная программа'!$K$20:$K$4940,'Адресная программа'!$L$20:$L$4940,1,'Адресная программа'!$C$20:$C$4940,БЦ!B23,'Адресная программа'!$G$20:$G$4940,БЦ!C23)*'Цены|Скидки'!$B$53-1),'Цены|Скидки'!$C$53,IF(SUMIFS('Адресная программа'!$O$20:$O$4940,'Адресная программа'!$N$20:$N$4940,1,'Адресная программа'!$C$20:$C$4940,БЦ!B23,'Адресная программа'!$G$20:$G$4940,БЦ!C23)>(SUMIFS('Адресная программа'!$K$20:$K$4940,'Адресная программа'!$L$20:$L$4940,1,'Адресная программа'!$C$20:$C$4940,БЦ!B23,'Адресная программа'!$G$20:$G$4940,БЦ!C23)*'Цены|Скидки'!$B$54-1),'Цены|Скидки'!$C$54,IF(SUMIFS('Адресная программа'!$O$20:$O$4940,'Адресная программа'!$N$20:$N$4940,1,'Адресная программа'!$C$20:$C$4940,БЦ!B23,'Адресная программа'!$G$20:$G$4940,БЦ!C23)>(SUMIFS('Адресная программа'!$K$20:$K$4940,'Адресная программа'!$L$20:$L$4940,1,'Адресная программа'!$C$20:$C$4940,БЦ!B23,'Адресная программа'!$G$20:$G$4940,БЦ!C23)*'Цены|Скидки'!$B$55-1),'Цены|Скидки'!$C$55,0%)))) | H23: =D$12 | I23: =IF(D23=0,0,1-J23/F23) | J23: =F23*(1-G23)*(1-H23)*(1-IF($AC$2="РА",$AD$2,0))*(1-IF(OR($AC$3="Доп скидка",$AC$3="Сезонная скидка",$AC$3="Welcome скидка")=TRUE,$AD$3,0)) | K23: =J23+L23 | L23: =J23*$AD$4 | M23: =(SUMIFS('Адресная программа'!$H$20:$H$4288,'Адресная программа'!$G$20:$G$4288,БЦ!C23,'Адресная программа'!$C$20:$C$4288,БЦ!B23,'Адресная программа'!$N$20:$N$4288,1)*$K$7) | N23: =IF(M23=0,0,J23/M23*1000)
D25: =SUBTOTAL(9,D22:D23) | F25: =SUBTOTAL(9,F22:F23) | J25: =SUBTOTAL(9,J22:J23) | K25: =SUBTOTAL(9,K22:K23) | L25: =SUBTOTAL(9,L22:L23) | M25: =SUBTOTAL(9,M22:M23) | N25: =IF(M25=0,0,J25/M25*1000)

Sheet ТРЦ
B2: Сеть Торгово-равлекательных центров | AD2: 0.25 | AN2: ПК | AO2: 0
B3: Клиент: | I3: Всего экранов: | K3: =SUMIF('Адресная программа'!G3304:G3306,"ТРЦ",'Адресная программа'!N3304:N3306) | AN3: РА | AO3: 0.05 | AP3: Доп скидка
B4: Бренд: | I4: Часов работы одного экрана в сутки: | K4: 12 | AO4: 0.1 | AP4: Welcome скидка
B5: Начало РК: | D5: =Общий!D5 | I5: Продолжительность блока в минутах: | K5: 5 | AO5: 0.15 | AP5: Сезонная скидка
B6: Окончание РК: | D6: =Общий!D6 | I6: Блоков в сутки на одном экране: | K6: =K4*60/K5 | AO6: 0.2
B7: Ролик1, сек: | D7: =Общий!D7 | I7: Кол-во дней размещения: | K7: =D6-D5+1 | AO7: 0.25
B8: Ролик2, сек: | I8: Выходов в блоке: | K8: 1
I9: Итого секунд в блоке: | K9: =SUM(D7:D9)
B10: Применяемые скидки (последовательно) | I10: Показов в день на одном экране: | K10: =K6*K8 | AO10: 0
B11: За кол-во экранов(средн): | D11: =IF(SUMIFS('Адресная программа'!$O$20:$O$4940,'Адресная программа'!$L$20:$L$4940,1,'Адресная программа'!$F$20:$F$4940,"ТРЦ")=SUMIFS('Адресная программа'!$L$20:$L$4940,'Адресная программа'!$L$20:$L$4940,1,'Адресная программа'!$F$20:$F$4940,"ТРЦ"),'Цены|Скидки'!C52,IF(SUMIFS('Адресная программа'!$O$20:$O$4940,'Адресная программа'!$L$20:$L$4940,1,'Адресная программа'!$F$20:$F$4940,"ТРЦ")>(SUMIFS('Адресная программа'!$L$20:$L$4940,'Адресная программа'!$L$20:$L$4940,1,'Адресная программа'!$F$20:$F$4940,"ТРЦ")*'Цены|Скидки'!B53-1),'Цены|Скидки'!C53,IF(SUMIFS('Адресная программа'!$O$20:$O$4940,'Адресная программа'!$L$20:$L$4940,1,'Адресная программа'!$F$20:$F$4940,"ТРЦ")>(SUMIFS('Адресная программа'!$L$20:$L$4940,'Адресная программа'!$L$20:$L$4940,1,'Адресная программа'!$F$20:$F$4940,"ТРЦ")*'Цены|Скидки'!B54-1),'Цены|Скидки'!C54,IF(SUMIFS('Адресная программа'!$O$20:$O$4940,'Адресная программа'!$L$20:$L$4940,1,'Адресная программа'!$F$20:$F$4940,"ТРЦ")>(SUMIFS('Адресная программа'!$L$20:$L$4940,'Адресная программа'!$L$20:$L$4940,1,'Адресная программа'!$F$20:$F$4940,"ТРЦ")*'Цены|Скидки'!B55-1),'Цены|Скидки'!C55,0%)))) | I11: Минут в день на одном экране: | K11: =K6*K9/60 | AO11: 0.05
B12: За период: | D12: =IF(K7>69,'Цены|Скидки'!$C$100,IF(K7>39,'Цены|Скидки'!$C$99,0%)) | I12: Показов на всех экранах за период: | K12: =K10*K7*K3 | AO12: 0.1
B13: =IF(AC2="РА","Скидка для РА:"," ") | D13: =IF(AC2="РА",AD2," ") | I13: OTS: | K13: =M28 | AO13: 0.15
B14: =IF(AC3=0," ",AC3) | D14: =IF(OR(AC3="Доп скидка",AC3="Сезонная скидка",AC3="Welcome скидка")=TRUE,AD3," ") | I14: CPT: | K14: =N28 | AO14: 0.2
B15: Стоимость размещения | AO15: 0.25
B16: Всего, руб. NET: | D16: =J28 | I16: Предоставление ролика до: | K16: =D5-3
B17: Всего, руб. GROSS: | D17: =K28 | I17: Оплата до: | K17: =D5-5
AN18: Автобренд
B20: Расчет стоимости кампании в ТРЦ
B21: Название | C21: Размер видеостены | D21: Проходимость в день | E21: Стоимость размещения в сутки на 1 экране, без НДС | F21: Стоимость размещения по выбранной АП за период, без НДС | G21: Скидка за кол-во экранов | H21: Скидка за период | I21: Итоговая скидка | J21: Стоимость c учетом всех скидок, без НДС | K21: Стоимость c учетом всех скидок, вкл. НДС | L21: Сумма НДС (20%) | M21: OTS | N21: CPT
B22: Афимолл Сити | C22: 4,86x2,74 | D22: 73770 | E22: =5265/15*K9 | F22: =IF('Адресная программа'!N3297=1,E22*$K$7*$K$8,0) | G22: =$D$11 | H22: =D$12 | I22: =IF(F22=0,0,1-J22/F22) | J22: =F22*(1-$D$11)*(1-$D$12)*(1-IF($AC$2="РА",$AD$2,0))*(1-IF(OR($AC$3="Доп скидка",$AC$3="Сезонная скидка",$AC$3="Welcome скидка")=TRUE,$AD$3,0)) | K22: =J22+L22 | L22: =J22*0.2 | M22: =IF(F22=0,0,(D22*$K$7)*(90/($K$5*60))) | N22: =IF(M22=0,0,J22/M22*1000)
B23: Афимолл Сити | C23: 4,86x2,74 | D23: 73770 | E23: =5265/15*K9 | F23: =IF('Адресная программа'!N3303=1,E23*$K$7*$K$8,0) | G23: =$D$11 | H23: =D$12 | I23: =IF(F23=0,0,1-J23/F23) | J23: =F23*(1-$D$11)*(1-$D$12)*(1-IF($AC$2="РА",$AD$2,0))*(1-IF(OR($AC$3="Доп скидка",$AC$3="Сезонная скидка",$AC$3="Welcome скидка")=TRUE,$AD$3,0)) | K23: =J23+L23 | L23: =J23*0.2 | M23: =IF(F23=0,0,(D23*$K$7)*(90/($K$5*60))) | N23: =IF(M23=0,0,J23/M23*1000)
B24: Афимолл Сити | C24: 3,67x2,08 | D24: 73770 | E24: =5265/15*K9 | F24: =IF(VLOOKUP("MSK_TRC_Afimoll_Siti_3",'Адресная программа'!J20:O6000,6,)=1,E24*$K$7*$K$8,0) | G24: =$D$11 | H24: =D$12 | I24: =IF(F24=0,0,1-J24/F24) | J24: =F24*(1-$D$11)*(1-$D$12)*(1-IF($AC$2="РА",$AD$2,0))*(1-IF(OR($AC$3="Доп скидка",$AC$3="Сезонная скидка",$AC$3="Welcome скидка")=TRUE,$AD$3,0)) | K24: =J24+L24 | L24: =J24*0.2 | M24: =IF(F24=0,0,(D24*$K$7)*(90/($K$5*60))) | N24: =IF(M24=0,0,J24/M24*1000)
B25: Афимолл Сити | C25: 4,7x1,3 | D25: 73770 | E25: =1980/15*K9 | F25: =IF(VLOOKUP("MSK_TRC_Afimoll_Siti_4",'Адресная программа'!J20:O6000,6,)=1,E25*$K$7*$K$8,0) | G25: =$D$11 | H25: =D$12 | I25: =IF(F25=0,0,1-J25/F25) | J25: =F25*(1-$D$11)*(1-$D$12)*(1-IF($AC$2="РА",$AD$2,0))*(1-IF(OR($AC$3="Доп скидка",$AC$3="Сезонная скидка",$AC$3="Welcome скидка")=TRUE,$AD$3,0)) | K25: =J25+L25 | L25: =J25*0.2 | M25: =IF(F25=0,0,(D25*$K$7)*(90/($K$5*60))) | N25: =IF(M25=0,0,J25/M25*1000)
B26: Афимолл Сити | C26: 4,7x1,3 | D26: 73770 | E26: =1980/15*K9 | F26: =IF(VLOOKUP("MSK_TRC_Afimoll_Siti_5",'Адресная программа'!J20:O6000,6,)=1,E26*$K$7*$K$8,0) | G26: =$D$11 | H26: =D$12 | I26: =IF(F26=0,0,1-J26/F26) | J26: =F26*(1-$D$11)*(1-$D$12)*(1-IF($AC$2="РА",$AD$2,0))*(1-IF(OR($AC$3="Доп скидка",$AC$3="Сезонная скидка",$AC$3="Welcome скидка")=TRUE,$AD$3,0)) | K26: =J26+L26 | L26: =J26*0.2 | M26: =IF(F26=0,0,(D26*$K$7)*(90/($K$5*60))) | N26: =IF(M26=0,0,J26/M26*1000)
F28: =SUBTOTAL(9,F22:F26) | J28: =SUBTOTAL(9,J22:J26) | K28: =SUBTOTAL(9,K22:K26) | L28: =SUBTOTAL(9,L22:L26) | M28: =SUBTOTAL(9,M22:M26) | N28: =IF(M28=0,0,J28/M28*1000)

Sheet Афимолл - Цетральный атриум
B2: Размещение на цифровых носителях в ТРК АФИМОЛЛ | AN2: 0
B3: Клиент: | H3: Всего экранов: | J3: =D22 | AM3: РА | AN3: 0.05 | AO3: Доп скидка
B4: Бренд: | H4: Часов работы одного экрана в сутки: | J4: 13 | AN4: 0.1 | AO4: Welcome скидка
B5: Начало РК: | D5: =Общий!D5 | H5: Продолжительность блока в минутах: | J5: =IF(MAX(MIN(EOMONTH("01.12.2025",0),D6)-MAX("01.12.2025",D5)+1,0)=J7,5,IF(MAX(MIN(EOMONTH("01.12.2025",0),D6)-MAX("01.12.2025",D5)+1,0)=0,3,"3")) | AN5: 0.15 | AO5: Сезонная скидка
B6: Окончание РК: | D6: =Общий!D6 | E6: =IF(J7<14,"Минимальный период размещения 14 дней","") | H6: Блоков в сутки на одном экране: | J6: =J4*60/J5
B7: Ролик, сек: | D7: 15 | H7: Кол-во дней размещения: | J7: =D6-D5+1 | AM7: Коэфф | AN7: =IF(I7<25,1.2,IF(I7<30,1.1,1))
B8: Доля эфира: | D8: =IF(D7=B34,C34,IF(D7=B35,C35,IF(D7=B36,C36,IF(D7=B37,C37,IF(D7=B38,C38,IF(D7=B39,C39,C40)))))) | H8: Кол-во роликов в блоке: | J8: 1
H9: Итого секунд в блоке: | J9: =SUM(D7:D8)
B10: Применяемые скидки (последовательно) | H10: Показов в день на одном экране: | J10: =J6*J8 | AN10: 0
B11: Итоговая скидка: | D11: =AVERAGE(G22:G22) | H11: Минут в день на одном экране: | J11: =J6*J9/60 | AN11: 0.05
B12: =IF(AC2="РА","Скидка для РА:"," ") | D12: =IF(AC2="РА",AD2," ") | H12: Показов на всех экранах за период: | J12: =(J3*(J7-(MAX(MIN(EOMONTH("01.12.2025",0),D6)-MAX("01.12.2025",D5)+1,0)))*J10)+(J3*(MAX(MIN(EOMONTH("01.12.2025",0),D6)-MAX("01.12.2025",D5)+1,0))*((J4*60/5)*J8)) | AN12: 0.1
B13: =IF(AC3=0," ",AC3) | D13: =IF(OR(AC3="Доп скидка",AC3="Сезонная скидка",AC3="Welcome скидка")=TRUE,AD3," ") | H13: Размер конструкции: | J13: 1-й ярус: 150,72х2,08м 2-й ярус: 159,04х2,08м | AN13: 0.15
AN14: 0.2
B15: Стоимость размещения | H15: Фото | AN15: 0.25
B16: Всего, руб. NET: | D16: =H22 | H16: Предоставление ролика до: | J16: =D5-3 | AN16: 0.3
B17: Всего, руб. GROSS: | D17: =I22 | H17: Оплата до: | J17: =D5-5
AM18: Автобренд
B20: Расчет стоимости кампании
B21: Название | C21: Местоположение | D21: Количество экранов | E21: Cтоимость размещения за 1 день (с учетом объемной скидки), без НДС | F21: Стоимость размещения за период (с учетом скидки за период), без НДС | G21: Итоговая скидка | H21: Стоимость c учетом всех скидок, без НДС | I21: Стоимость c учетом всех скидок, вкл. НДС | J21: Сумма НДС (20%) | K21: Проходимость | L21: OTS | M21: CPT
B22: ТРК Афимолл | C22: Центральный атриум | D22: =IF(F22=0,0,2) | E22: =IF(VLOOKUP("MSK_TRC_Afimoll_Siti_6",'Адресная программа'!J20:O6000,6,)=2,IF(D7=15,E34,IF(D7=30,E35,IF(D7=60,E36,IF(D7=90,E37,IF(D7=120,E38,IF(D7=150,E39,IF(D7=180,E40,))))))),0) | F22: =IF(MAX(MIN(EOMONTH("01.12.2025",0),D6)-MAX("01.12.2025",D5)+1,0)=0,E22*J7,(MAX(MIN(EOMONTH("01.12.2025",0),D6)-MAX("01.12.2025",D5)+1,0)*(E22*1.2))+(J7-MAX(MIN(EOMONTH("01.12.2025",0),D6)-MAX("01.12.2025",D5)+1,0))*E22) | G22: =IF(E22=0,0,IF(MONTH(D5)=12,1-H22/(D7/15*E34*1.2*J7),1-H22/(D7/15*E34*J7))) | H22: =IF('Адресная программа'!O3930=2,IF(MAX(MIN(EOMONTH("01.12.2025",0),D6)-MAX("01.12.2025",D5)+1,0)=0,IF(D7=15,E34,IF(D7=30,E35,IF(D7=60,E36,IF(D7=90,E37,IF(D7=120,E38,IF(D7=150,E39,IF(D7=180,E40,)))))))*J7,(MAX(MIN(EOMONTH("01.12.2025",0),D6)-MAX("01.12.2025",D5)+1,0)*(IF(D7=15,E34,IF(D7=30,E35,IF(D7=60,E36,IF(D7=90,E37,IF(D7=120,E38,IF(D7=150,E39,IF(D7=180,E40,)))))))*1.2))+(J7-MAX(MIN(EOMONTH("01.12.2025",0),D6)-MAX("01.12.2025",D5)+1,0))*IF(D7=15,E34,IF(D7=30,E35,IF(D7=60,E36,IF(D7=90,E37,IF(D7=120,E38,IF(D7=150,E39,IF(D7=180,E40,))))))))*(1-IF(J7>69,C31,IF(J7>39,C30,IF(J7>21,C29,0%))))*(1-IF($AC$2="РА",$AD$2,0))*(1-IF(OR($AC$3="Доп скидка",$AC$3="Сезонная скидка",$AC$3="Welcome скидка")=TRUE,$AD$3,0)),0) | I22: =H22+J22 | J22: =H22*0.2 | K22: 73770 | L22: =IF(F22=0,0,(K22*$J$7)*(90/($J$5*60))*J3) | M22: =IF(L22=0,0,H22/L22*1000)
B25: * В декабре действует повышающий коэф. 1,2.
B26: * Минимальный срок размещения 14 дней
B28: Скидка за период размещения:
B29: от 22 дней | C29: 0.1
B30: от 40 дней | C30: 0.15
B31: от 70 дней | C31: 0.2
B33: Хронометраж ролика, сек | C33: Доля эфира | D33: Объмная скидка | E33: Стоимость размещения ролика в день, без НДС
B34: 15 | C34: 1/12 | D34: 0 | E34: 49700
B35: 30 | C35: 1/6 | D35: =(B35/B$34*E$34-E35)/(B35/B$34*E$34) | E35: 70990
B36: 60 | C36: 1/3 | D36: =(B36/B$34*E$34-E36)/(B36/B$34*E$34) | E36: 117130
B37: 90 | C37: 1/2 | D37: =(B37/B$34*E$34-E37)/(B37/B$34*E$34) | E37: 157950
B38: 120 | C38: 2/3 | D38: =(B38/B$34*E$34-E38)/(B38/B$34*E$34) | E38: 198765
B39: 150 | C39: 5/6 | D39: =(B39/B$34*E$34-E39)/(B39/B$34*E$34) | E39: 239585
B40: 180 | C40: 1/1 | D40: =(B40/B$34*E$34-E40)/(B40/B$34*E$34) | E40: 283950

Sheet Wi-Fi
J2: Продажа Wifi: | K2: Нет | AN2: ПК | AO2: 0
AN3: РА | AO3: 0.05 | AP3: Доп скидка
B4: Аудитория | AO4: 0.1 | AP4: Welcome скидка
B5: Клиент: | F5: Базовая стоимость аренды оборудования и программного обеспечения для предоставления услуги выгрузки по сегменту | AO5: 0.15 | AP5: Сезонная скидка
B6: Бренд: | AO6: 0.2
B7: Начало РК: | D7: =Общий!D5 | F7: Стоимость услуги 1-го дня по 1 адресу: | K7: 79 | AO7: 0.25
B8: Окончание РК: | D8: =Общий!D6 | G8: * - стоимость без учёта НДС 20 %
B9: Период кол-во дней: | D9: =(D8-D7)+1 | F9: Система скидок
B10: Применяемые скидки (последовательно) | F10: % выборки от общего кол-ва адресов | G10: Скидка за кол-во адресов | H10: Рассчет по кол-ву станций | J10: Скидка за период размещения: | AO10: 0
B11: За кол-во экранов(средн): | D11: =SUBTOTAL(1,F22:F34) | F11: 0.75 | G11: 0.15 | H11: =F11*$G$15 | J11: от 40-69 дней | K11: 0.05 | AO11: 0.05
B12: За период: | D12: =IF(D9>69,K12,IF(D9>39,K11,0%)) | F12: 0.5 | G12: 0.1 | H12: =F12*$G$15 | J12: от 70 дней | K12: 0.1 | AO12: 0.1
B13: =IF(AC2="РА","Скидка для РА:"," ") | D13: =IF(AC2="РА",AD2," ") | F13: 0.25 | G13: 0.05 | H13: =F13*$G$15 | AO13: 0.15
B14: =IF(AC3=0," ",AC3) | D14: =IF(OR(AC3="Доп скидка",AC3="Сезонная скидка",AC3="Welcome скидка")=TRUE,AD3," ") | F14: менее 25% | G14: 0 | AO14: 0.2
B15: Стоимость размещения | F15: Всего точек: | G15: =COUNTIFS('Адресная программа'!$B$20:$B$4169,"WF",'Адресная программа'!$L$20:$L$4169,1) | AO15: 0.25
B16: Всего, руб. NET: | D16: =I36
B17: Всего, руб. GROSS: | D17: =J36
AN18: Автобренд
B19: Расчет стоимости выгрузки аудиторного сегмента
B21: Регион | C21: Сеть | D21: Количество адресов | E21: Базова стоимость услуги | F21: Скидка за обьем | G21: скидка за период | H21: Итоговая скидка | I21: Стоимость c учетом всех скидок, без НДС | J21: Стоимость c учетом всех скидок, вкл. НДС | K21: Сумма НДС (20%)
B22: Москва | C22: Роснефть | D22: =IF($K$2="Да",COUNTIFS('Адресная программа'!$B$20:$B$4169,"WF",'Адресная программа'!$C$20:$C$4169,'Wi-Fi'!B22,'Адресная программа'!$N$20:$N$4169,1,'Адресная программа'!$G$20:$G$4169,C22),0) | E22: =D22*D$9*K$7 | F22: =IF(SUM(D$22:D$34)<G$15*F$13,G$14,IF(SUM(D$22:D$34)<F$12*G$15,G$13,IF(SUM(D$22:D$34)<F$11*G$15,G$12,G$11))) | G22: =IF(D$9<15,0%,IF(D$9<32,5%,IF(D$9<61,10%,15%))) | H22: =IF(D22=0,0,1-I22/E22) | I22: =E22*(1-F22)*(1-G22)*(1-IF($AC$2="РА",$AD$2,0))*(1-IF(OR($AC$3="Доп скидка",$AC$3="Сезонная скидка",$AC$3="Welcome скидка")=TRUE,$AD$3,0)) | J22: =I22+K22 | K22: =I22*0.2
B23: Москва | C23: Лукойл | D23: =IF($K$2="Да",COUNTIFS('Адресная программа'!$B$20:$B$4169,"WF",'Адресная программа'!$C$20:$C$4169,'Wi-Fi'!B23,'Адресная программа'!$N$20:$N$4169,1,'Адресная программа'!$G$20:$G$4169,C23),0) | E23: =D23*D$9*K$7 | F23: =IF(SUM(D$22:D$34)<G$15*F$13,G$14,IF(SUM(D$22:D$34)<F$12*G$15,G$13,IF(SUM(D$22:D$34)<F$11*G$15,G$12,G$11))) | G23: =IF(D$9<15,0%,IF(D$9<32,5%,IF(D$9<61,10%,15%))) | H23: =IF(D23=0,0,1-I23/E23) | I23: =E23*(1-F23)*(1-G23)*(1-IF($AC$2="РА",$AD$2,0))*(1-IF(OR($AC$3="Доп скидка",$AC$3="Сезонная скидка",$AC$3="Welcome скидка")=TRUE,$AD$3,0)) | J23: =I23+K23 | K23: =I23*0.2
B24: Москва | C24: ЕКА | D24: =IF($K$2="Да",COUNTIFS('Адресная программа'!$B$20:$B$4169,"WF",'Адресная программа'!$C$20:$C$4169,'Wi-Fi'!B24,'Адресная программа'!$N$20:$N$4169,1,'Адресная программа'!$G$20:$G$4169,C24),0) | E24: =D24*D$9*K$7 | F24: =IF(SUM(D$22:D$34)<G$15*F$13,G$14,IF(SUM(D$22:D$34)<F$12*G$15,G$13,IF(SUM(D$22:D$34)<F$11*G$15,G$12,G$11))) | G24: =IF(D$9<15,0%,IF(D$9<32,5%,IF(D$9<61,10%,15%))) | H24: =IF(D24=0,0,1-I24/E24) | I24: =E24*(1-F24)*(1-G24)*(1-IF($AC$2="РА",$AD$2,0))*(1-IF(OR($AC$3="Доп скидка",$AC$3="Сезонная скидка",$AC$3="Welcome скидка")=TRUE,$AD$3,0)) | J24: =I24+K24 | K24: =I24*0.2
B25: Москва | C25: Азбука вкуса | D25: =IF($K$2="Да",COUNTIFS('Адресная программа'!$B$20:$B$4169,"WF",'Адресная программа'!$C$20:$C$4169,'Wi-Fi'!B25,'Адресная программа'!$N$20:$N$4169,1,'Адресная программа'!$G$20:$G$4169,C25),0) | E25: =D25*D$9*K$7 | F25: =IF(SUM(D$22:D$34)<G$15*F$13,G$14,IF(SUM(D$22:D$34)<F$12*G$15,G$13,IF(SUM(D$22:D$34)<F$11*G$15,G$12,G$11))) | G25: =IF(D$9<15,0%,IF(D$9<32,5%,IF(D$9<61,10%,15%))) | H25: =IF(D25=0,0,1-I25/E25) | I25: =E25*(1-F25)*(1-G25)*(1-IF($AC$2="РА",$AD$2,0))*(1-IF(OR($AC$3="Доп скидка",$AC$3="Сезонная скидка",$AC$3="Welcome скидка")=TRUE,$AD$3,0)) | J25: =I25+K25 | K25: =I25*0.2
B26: Москва | C26: Metro C&C | D26: =IF($K$2="Да",COUNTIFS('Адресная программа'!$B$20:$B$4169,"WF",'Адресная программа'!$C$20:$C$4169,'Wi-Fi'!B26,'Адресная программа'!$N$20:$N$4169,1,'Адресная программа'!$G$20:$G$4169,C26),0) | E26: =D26*D$9*K$7 | F26: =IF(SUM(D$22:D$34)<G$15*F$13,G$14,IF(SUM(D$22:D$34)<F$12*G$15,G$13,IF(SUM(D$22:D$34)<F$11*G$15,G$12,G$11))) | G26: =IF(D$9<15,0%,IF(D$9<32,5%,IF(D$9<61,10%,15%))) | H26: =IF(D26=0,0,1-I26/E26) | I26: =E26*(1-F26)*(1-G26)*(1-IF($AC$2="РА",$AD$2,0))*(1-IF(OR($AC$3="Доп скидка",$AC$3="Сезонная скидка",$AC$3="Welcome скидка")=TRUE,$AD$3,0)) | J26: =I26+K26 | K26: =I26*0.2
B27: Москва | C27: Бизнес центр | D27: =IF($K$2="Да",COUNTIFS('Адресная программа'!$B$20:$B$4169,"WF",'Адресная программа'!$C$20:$C$4169,'Wi-Fi'!B27,'Адресная программа'!$N$20:$N$4169,1,'Адресная программа'!$G$20:$G$4169,C27),0) | E27: =D27*D$9*K$7 | F27: =IF(SUM(D$22:D$34)<G$15*F$13,G$14,IF(SUM(D$22:D$34)<F$12*G$15,G$13,IF(SUM(D$22:D$34)<F$11*G$15,G$12,G$11))) | G27: =IF(D$9<15,0%,IF(D$9<32,5%,IF(D$9<61,10%,15%))) | H27: =IF(D27=0,0,1-I27/E27) | I27: =E27*(1-F27)*(1-G27)*(1-IF($AC$2="РА",$AD$2,0))*(1-IF(OR($AC$3="Доп скидка",$AC$3="Сезонная скидка",$AC$3="Welcome скидка")=TRUE,$AD$3,0)) | J27: =I27+K27 | K27: =I27*0.2
B28: Санкт-Петербург | C28: Азбука вкуса | D28: =IF($K$2="Да",COUNTIFS('Адресная программа'!$B$20:$B$4169,"WF",'Адресная программа'!$C$20:$C$4169,'Wi-Fi'!B28,'Адресная программа'!$N$20:$N$4169,1,'Адресная программа'!$G$20:$G$4169,C28),0) | E28: =D28*D$9*K$7 | F28: =IF(SUM(D$22:D$34)<G$15*F$13,G$14,IF(SUM(D$22:D$34)<F$12*G$15,G$13,IF(SUM(D$22:D$34)<F$11*G$15,G$12,G$11))) | G28: =IF(D$9<15,0%,IF(D$9<32,5%,IF(D$9<61,10%,15%))) | H28: =IF(D28=0,0,1-I28/E28) | I28: =E28*(1-F28)*(1-G28)*(1-IF($AC$2="РА",$AD$2,0))*(1-IF(OR($AC$3="Доп скидка",$AC$3="Сезонная скидка",$AC$3="Welcome скидка")=TRUE,$AD$3,0)) | J28: =I28+K28 | K28: =I28*0.2
B29: Санкт-Петербург | C29: Бизнес центр | D29: =IF($K$2="Да",COUNTIFS('Адресная программа'!$B$20:$B$4169,"WF",'Адресная программа'!$C$20:$C$4169,'Wi-Fi'!B29,'Адресная программа'!$N$20:$N$4169,1,'Адресная программа'!$G$20:$G$4169,C29),0) | E29: =D29*D$9*K$7 | F29: =IF(SUM(D$22:D$34)<G$15*F$13,G$14,IF(SUM(D$22:D$34)<F$12*G$15,G$13,IF(SUM(D$22:D$34)<F$11*G$15,G$12,G$11))) | G29: =IF(D$9<15,0%,IF(D$9<32,5%,IF(D$9<61,10%,15%))) | H29: =IF(D29=0,0,1-I29/E29) | I29: =E29*(1-F29)*(1-G29)*(1-IF($AC$2="РА",$AD$2,0))*(1-IF(OR($AC$3="Доп скидка",$AC$3="Сезонная скидка",$AC$3="Welcome скидка")=TRUE,$AD$3,0)) | J29: =I29+K29 | K29: =I29*0.2
B30: Владимир | C30: Лукойл | D30: =COUNTIFS('Адресная программа'!$B$20:$B$4169,"WF",'Адресная программа'!$C$20:$C$4169,'Wi-Fi'!B30,'Адресная программа'!$N$20:$N$4169,1,'Адресная программа'!$G$20:$G$4169,C30) | E30: =D30*D$9*K$7 | F30: =IF(SUM(D$22:D$34)<G$15*F$13,G$14,IF(SUM(D$22:D$34)<F$12*G$15,G$13,IF(SUM(D$22:D$34)<F$11*G$15,G$12,G$11))) | G30: =IF(D$9<15,0%,IF(D$9<32,5%,IF(D$9<61,10%,15%))) | H30: =IF(D30=0,0,1-I30/E30) | I30: =E30*(1-F30)*(1-G30)*(1-IF($AC$2="РА",$AD$2,0))*(1-IF(OR($AC$3="Доп скидка",$AC$3="Сезонная скидка",$AC$3="Welcome скидка")=TRUE,$AD$3,0)) | J30: =I30+K30 | K30: =I30*0.2
B31: Нижний Новгород | C31: Лукойл | D31: =COUNTIFS('Адресная программа'!$B$20:$B$4169,"WF",'Адресная программа'!$C$20:$C$4169,'Wi-Fi'!B31,'Адресная программа'!$N$20:$N$4169,1,'Адресная программа'!$G$20:$G$4169,C31) | E31: =D31*D$9*K$7 | F31: =IF(SUM(D$22:D$34)<G$15*F$13,G$14,IF(SUM(D$22:D$34)<F$12*G$15,G$13,IF(SUM(D$22:D$34)<F$11*G$15,G$12,G$11))) | G31: =IF(D$9<15,0%,IF(D$9<32,5%,IF(D$9<61,10%,15%))) | H31: =IF(D31=0,0,1-I31/E31) | I31: =E31*(1-F31)*(1-G31)*(1-IF($AC$2="РА",$AD$2,0))*(1-IF(OR($AC$3="Доп скидка",$AC$3="Сезонная скидка",$AC$3="Welcome скидка")=TRUE,$AD$3,0)) | J31: =I31+K31 | K31: =I31*0.2
B32: Саранск | C32: Лукойл | D32: =COUNTIFS('Адресная программа'!$B$20:$B$4169,"WF",'Адресная программа'!$C$20:$C$4169,'Wi-Fi'!B32,'Адресная программа'!$N$20:$N$4169,1,'Адресная программа'!$G$20:$G$4169,C32) | E32: =D32*D$9*K$7 | F32: =IF(SUM(D$22:D$34)<G$15*F$13,G$14,IF(SUM(D$22:D$34)<F$12*G$15,G$13,IF(SUM(D$22:D$34)<F$11*G$15,G$12,G$11))) | G32: =IF(D$9<15,0%,IF(D$9<32,5%,IF(D$9<61,10%,15%))) | H32: =IF(D32=0,0,1-I32/E32) | I32: =E32*(1-F32)*(1-G32)*(1-IF($AC$2="РА",$AD$2,0))*(1-IF(OR($AC$3="Доп скидка",$AC$3="Сезонная скидка",$AC$3="Welcome скидка")=TRUE,$AD$3,0)) | J32: =I32+K32 | K32: =I32*0.2
B33: Смоленск | C33: Лукойл | D33: =COUNTIFS('Адресная программа'!$B$20:$B$4169,"WF",'Адресная программа'!$C$20:$C$4169,'Wi-Fi'!B33,'Адресная программа'!$N$20:$N$4169,1,'Адресная программа'!$G$20:$G$4169,C33) | E33: =D33*D$9*K$7 | F33: =IF(SUM(D$22:D$34)<G$15*F$13,G$14,IF(SUM(D$22:D$34)<F$12*G$15,G$13,IF(SUM(D$22:D$34)<F$11*G$15,G$12,G$11))) | G33: =IF(D$9<15,0%,IF(D$9<32,5%,IF(D$9<61,10%,15%))) | H33: =IF(D33=0,0,1-I33/E33) | I33: =E33*(1-F33)*(1-G33)*(1-IF($AC$2="РА",$AD$2,0))*(1-IF(OR($AC$3="Доп скидка",$AC$3="Сезонная скидка",$AC$3="Welcome скидка")=TRUE,$AD$3,0)) | J33: =I33+K33 | K33: =I33*0.2
